Workbook

Sheet Guida
A1: CONTROLLO DI GESTIONE CON L'INTELLIGENZA ARTIFICIALE
A2: File Excel che accompagna il libro · Autrice: Tania Cilio
A3: © 2026 Tania Cilio. Tutti i diritti riservati.
A4: Il file segue il libro capitolo per capitolo, con le formule scritte nelle celle: si vede come nasce ogni numero e lo si può rifare con i propri dati.
A5: Il foglio «Impresa_guida» contiene i dati di partenza del caso del libro. I fogli «Cap_01» … «Cap_20» li usano nei calcoli di ogni capitolo.
A6: Celle blu su fondo giallo: dati da cambiare. Celle nere: formule. Colonna «Valore atteso (libro)»: il numero stampato nel libro o il risultato atteso di un controllo (per esempio una differenza uguale a zero). Colonna «Controllo»: OK se il calcolo lo ritrova.
A7: Se si cambiano i dati, i controlli possono diventare «DIVERSO»: è normale, perché i numeri non sono più quelli del libro.
A8: Il foglio «Controlli» riunisce tutti i confronti con il libro. Il foglio «Bilancio_Alfa_2024» è la base delle richieste 16-22 e 30 del file Word con le trenta richieste.
A10: Foglio | B10: Contenuto | C10: Capitoli del libro
A11: Impresa_guida | B11: Dati di partenza del caso del libro (paragrafo 19.3) | C11: tutti
A12: Parte I - Fondamenti di contabilità e analisi economica
A13: Cap_01 | B13: Capitolo 1 - Leggere la realtà economica dell'impresa | C13: 1
A14: Cap_02 | B14: Capitolo 2 - Contabilità generale e contabilità analitica | C14: 2
A15: Cap_03 | B15: Capitolo 3 - Il concetto di costo e le classificazioni | C15: 3
A16: Cap_04 | B16: Capitolo 4 - Comportamento dei costi | C16: 4
A17: Parte II - Contabilità analitica, costing, ABC e ABM
A18: Cap_05 | B18: Capitolo 5 - Oggetti di costo e centri di costo | C18: 5
A19: Cap_06 | B19: Capitolo 6 - Costi diretti, indiretti e allocazione | C19: 6
A20: Cap_07 | B20: Capitolo 7 - Full Costing | C20: 7
A21: Cap_08 | B21: Capitolo 8 - Direct Costing e margine di contribuzione | C21: 8
A22: Cap_09 | B22: Capitolo 9 - Break-even e analisi costo-volume-risultato | C22: 9
A23: Cap_10 | B23: Capitolo 10 - Activity Based Costing | C23: 10
A24: Cap_11 | B24: Capitolo 11 - Activity Based Management | C24: 11
A25: Parte III - Programmazione, budget e analisi degli scostamenti
A26: Cap_12 | B26: Capitolo 12 - Budget | C26: 12
A27: Cap_13 | B27: Capitolo 13 - Budget operativo | C27: 13
A28: Cap_14 | B28: Capitolo 14 - Budget, consuntivo e analisi degli scostamenti | C28: 14
A29: Parte IV - Decisioni economiche
A30: Cap_15 | B30: Capitolo 15 - Costi rilevanti e decisioni | C30: 15
A31: Cap_16 | B31: Capitolo 16 - Make or Buy | C31: 16
A32: Cap_17 | B32: Capitolo 17 - Pricing | C32: 17
A33: Cap_18 | B33: Capitolo 18 - Ottimizzazione dei margini e alternative produttive | C33: 18
A34: Parte V - Intelligenza artificiale e misurazione delle prestazioni
A35: Cap_19 | B35: Capitolo 19 - L'intelligenza artificiale nel controllo di gestione | C35: 19
A36: Cap_20 | B36: Capitolo 20 - KPI essenziali per il controllo di gestione | C36: 20
A37: Esercizi, formule, glossario e controlli
A38: Esercizi_Costi | B38: Classificare i costi (18 voci) | C38: 3, 4, 8, 15, 16
A39: Esercizi_Analitica | B39: Allocazione, centri e basi | C39: 5, 6, 10, 11
A40: Esercizi_Costing | B40: Full Costing, Direct Costing, pareggio, ABC | C40: 7, 8, 9, 10
A41: Esercizi_Pianificazione | B41: Budget e scostamenti | C41: 13, 14
A42: Esercizi_Decisioni | B42: Ordine speciale, Make or Buy, prezzi, mix | C42: 15, 16, 17, 18
A43: Esercizi_IA | B43: Controllare il lavoro di uno strumento di IA | C43: 19
A44: Esercizi_Bilancio | B44: Leggere un bilancio (esempio con numeri inventati) | C44: 1, 20
A45: Soluzioni_Esercizi | B45: Soluzioni degli esercizi | C45: -
A46: Formule | B46: Formule del libro | C46: tutti
A47: Glossario | B47: Termini del libro | C47: tutti
A48: Bilancio_Alfa_2024 | B48: Bilancio di esempio 2024 e 2023 con numeri inventati (base delle richieste 16-22 e 30) | C48: 1, 20
A49: Controlli | B49: Tutti i confronti con i numeri del libro | C49: tutti

Sheet Impresa_guida
A1: Impresa guida - dataset master (paragrafo 19.3)
A2: Controllo di gestione con l'intelligenza artificiale - file Excel che accompagna il libro
A3: Celle blu su fondo giallo: dati da cambiare. Celle nere: formule. «Valore atteso (libro)» e «Controllo» confrontano il calcolo con il numero stampato nel libro.
A4: I dati di partenza di tutto il libro. Le celle blu su fondo giallo sono dati: cambiandole si ricalcolano tutti i fogli dei capitoli.
A6: Linee di prodotto
A7: Voce | B7: Valore | C7: Unità | D7: Valore atteso (libro) | E7: Controllo | F7: Fonte nel libro
A8: Linea A - unità vendute | B8: 8000 | C8: unità | F8: paragrafo 19.3
A9: Linea A - prezzo netto unitario | B9: 180 | C9: euro/unità | F9: paragrafo 19.3
A10: Linea A - costo variabile unitario | B10: 117 | C10: euro/unità | F10: paragrafo 19.3
A11: Linea A - ore macchina per unità | B11: 1.5 | C11: ore/unità | F11: paragrafo 19.3
A12: Linea B - unità vendute | B12: 12000 | C12: unità | F12: paragrafo 19.3
A13: Linea B - prezzo netto unitario | B13: 114 | C13: euro/unità | F13: paragrafo 19.3
A14: Linea B - costo variabile unitario | B14: 76 | C14: euro/unità | F14: paragrafo 19.3
A15: Linea B - ore macchina per unità | B15: 0.5 | C15: ore/unità | F15: paragrafo 19.3
A16: Linea C - unità vendute | B16: 2000 | C16: unità | F16: paragrafo 19.3
A17: Linea C - prezzo netto unitario | B17: 289 | C17: euro/unità | F17: paragrafo 19.3
A18: Linea C - costo variabile unitario | B18: 238 | C18: euro/unità | F18: paragrafo 19.3
A19: Linea C - ore macchina per unità | B19: 3 | C19: ore/unità | F19: paragrafo 19.3
A21: Struttura e capacità
A22: Voce | B22: Valore | C22: Unità | D22: Valore atteso (libro) | E22: Controllo | F22: Fonte nel libro
A23: Struttura base - attività commerciali e logistiche | B23: 570000 | C23: euro | F23: paragrafo 19.3
A24: Struttura base - costi indiretti di produzione | B24: 120000 | C24: euro | F24: paragrafo 19.3
A25: Struttura base - costi amministrativi | B25: 46000 | C25: euro | F25: paragrafo 19.3
A26: Capacità ordinaria del reparto | B26: 21000 | C26: ore | F26: paragrafo 19.3
A27: Costo di un'ora di capacità esterna | B27: 28 | C27: euro/ora | F27: paragrafo 19.3
A29: Risultati (calcolati)
A30: Voce | B30: Valore | C30: Unità | D30: Valore atteso (libro) | E30: Controllo | F30: Fonte nel libro
A31: Ricavi linea A | B31: =$B$8*$B$9 -> 1440000 | C31: euro | D31: 1440000 | E31: =IF(ABS(B31-D31)<=0.5,"OK","DIVERSO") -> OK | F31: capitolo 1; paragrafo 19.3
A32: Ricavi linea B | B32: =$B$12*$B$13 -> 1368000 | C32: euro | D32: 1368000 | E32: =IF(ABS(B32-D32)<=0.5,"OK","DIVERSO") -> OK | F32: capitolo 1; paragrafo 19.3
A33: Ricavi linea C | B33: =$B$16*$B$17 -> 578000 | C33: euro | D33: 578000 | E33: =IF(ABS(B33-D33)<=0.5,"OK","DIVERSO") -> OK | F33: capitolo 1; paragrafo 19.3
A34: Ricavi totali | B34: =$B$31+$B$32+$B$33 -> 3386000 | C34: euro | D34: 3386000 | E34: =IF(ABS(B34-D34)<=0.5,"OK","DIVERSO") -> OK | F34: capitolo 1; paragrafo 19.3
A35: Costi variabili totali | B35: =$B$8*$B$10+$B$12*$B$14+$B$16*$B$18 -> 2324000 | C35: euro | D35: 2324000 | E35: =IF(ABS(B35-D35)<=0.5,"OK","DIVERSO") -> OK | F35: capitolo 1; paragrafo 19.3
A36: Margine di contribuzione totale | B36: =$B$34-$B$35 -> 1062000 | C36: euro | D36: 1062000 | E36: =IF(ABS(B36-D36)<=0.5,"OK","DIVERSO") -> OK | F36: capitolo 1; paragrafo 19.3
A37: Ore macchina richieste | B37: =$B$8*$B$11+$B$12*$B$15+$B$16*$B$19 -> 24000 | C37: ore | D37: 24000 | E37: =IF(ABS(B37-D37)<=0.5,"OK","DIVERSO") -> OK | F37: capitolo 1; paragrafo 19.3
A38: Ore di capacità esterna | B38: =MAX($B$37-$B$26,0) -> 3000 | C38: ore | D38: 3000 | E38: =IF(ABS(B38-D38)<=0.5,"OK","DIVERSO") -> OK | F38: capitolo 1; paragrafo 19.3
A39: Costo della capacità esterna | B39: =$B$38*$B$27 -> 84000 | C39: euro | D39: 84000 | E39: =IF(ABS(B39-D39)<=0.5,"OK","DIVERSO") -> OK | F39: capitolo 1; paragrafo 19.3
A40: Struttura base | B40: =$B$23+$B$24+$B$25 -> 736000 | C40: euro | D40: 736000 | E40: =IF(ABS(B40-D40)<=0.5,"OK","DIVERSO") -> OK | F40: capitolo 1; paragrafo 19.3
A41: Costi della struttura | B41: =$B$40+$B$39 -> 820000 | C41: euro | D41: 820000 | E41: =IF(ABS(B41-D41)<=0.5,"OK","DIVERSO") -> OK | F41: capitolo 1; paragrafo 19.3
A42: Risultato operativo | B42: =$B$36-$B$41 -> 242000 | C42: euro | D42: 242000 | E42: =IF(ABS(B42-D42)<=0.5,"OK","DIVERSO") -> OK | F42: capitolo 1; paragrafo 19.3

Sheet Cap_01
A1: Capitolo 1 - Leggere la realtà economica dell'impresa
A2: Controllo di gestione con l'intelligenza artificiale - file Excel che accompagna il libro
A3: Celle blu su fondo giallo: dati da cambiare. Celle nere: formule. «Valore atteso (libro)» e «Controllo» confrontano il calcolo con il numero stampato nel libro.
A4: Il Conto Economico letto per gradini e la differenza fra costo, acquisto, pagamento, ricavo e incasso.
A6: Conto Economico per gradini - esempio
A7: Il risultato si forma per gradini: margine di contribuzione, risultato operativo, risultato economico; capitolo 1
A8: Voce | B8: Valore | C8: Unità | D8: Valore atteso (libro) | E8: Controllo | F8: Fonte nel libro
A9: Ricavi di vendita | B9: 200000 | C9: euro | F9: capitolo 1
A10: Costi variabili | B10: 120000 | C10: euro | F10: capitolo 1
A11: Margine di contribuzione | B11: =$B$9-$B$10 -> 80000 | C11: euro | D11: 80000 | E11: =IF(ABS(B11-D11)<=0.5,"OK","DIVERSO") -> OK | F11: capitolo 1
A12: Costi fissi di struttura | B12: 55000 | C12: euro | F12: capitolo 1
A13: Risultato operativo | B13: =$B$11-$B$12 -> 25000 | C13: euro | D13: 25000 | E13: =IF(ABS(B13-D13)<=0.5,"OK","DIVERSO") -> OK | F13: capitolo 1
A14: Oneri finanziari | B14: 5000 | C14: euro | F14: capitolo 1
A15: Risultato economico del periodo | B15: =$B$13-$B$14 -> 20000 | C15: euro | D15: 20000 | E15: =IF(ABS(B15-D15)<=0.5,"OK","DIVERSO") -> OK | F15: capitolo 1
A17: Acquisto, costo e magazzino
A18: Il costo è la risorsa consumata, non l'acquisto: la parte non consumata resta in magazzino; capitolo 1
A19: Voce | B19: Valore | C19: Unità | D19: Valore atteso (libro) | E19: Controllo | F19: Fonte nel libro
A20: Acquisto di materia prima | B20: 30000 | C20: euro | F20: capitolo 1
A21: Materia consumata nel periodo | B21: 20000 | C21: euro | F21: capitolo 1
A22: Costo del periodo | B22: =$B$21 -> 20000 | C22: euro | D22: 20000 | E22: =IF(ABS(B22-D22)<=0.5,"OK","DIVERSO") -> OK | F22: capitolo 1
A23: Rimane in magazzino (attività) | B23: =$B$20-$B$21 -> 10000 | C23: euro | D23: 10000 | E23: =IF(ABS(B23-D23)<=0.5,"OK","DIVERSO") -> OK | F23: capitolo 1
A25: Ammortamento: costo senza pagamento
A26: Un macchinario pagato una volta diventa costo anno per anno; capitolo 1
A27: Voce | B27: Valore | C27: Unità | D27: Valore atteso (libro) | E27: Controllo | F27: Fonte nel libro
A28: Costo del macchinario | B28: 100000 | C28: euro | F28: capitolo 1
A29: Anni di utilizzo | B29: 10 | C29: anni | F29: capitolo 1
A30: Ammortamento annuo | B30: =$B$28/$B$29 -> 10000 | C30: euro | D30: 10000 | E30: =IF(ABS(B30-D30)<=0.5,"OK","DIVERSO") -> OK | F30: capitolo 1
A32: Impresa guida - Conto Economico per gradini
A33: Il Conto Economico dell'esercizio letto per gradini, dai dati del foglio Impresa_guida; capitolo 1
A34: Voce | B34: Valore | C34: Unità | D34: Valore atteso (libro) | E34: Controllo | F34: Fonte nel libro
A35: Ricavi di vendita | B35: =Impresa_guida!$B$34 -> 3386000 | C35: euro | D35: 3386000 | E35: =IF(ABS(B35-D35)<=0.5,"OK","DIVERSO") -> OK | F35: capitolo 1
A36: Costi variabili | B36: =Impresa_guida!$B$35 -> 2324000 | C36: euro | D36: 2324000 | E36: =IF(ABS(B36-D36)<=0.5,"OK","DIVERSO") -> OK | F36: capitolo 1
A37: Margine di contribuzione | B37: =$B$35-$B$36 -> 1062000 | C37: euro | D37: 1062000 | E37: =IF(ABS(B37-D37)<=0.5,"OK","DIVERSO") -> OK | F37: capitolo 1
A38: Costi della struttura | B38: =Impresa_guida!$B$41 -> 820000 | C38: euro | D38: 820000 | E38: =IF(ABS(B38-D38)<=0.5,"OK","DIVERSO") -> OK | F38: capitolo 1
A39: Risultato operativo | B39: =$B$37-$B$38 -> 242000 | C39: euro | D39: 242000 | E39: =IF(ABS(B39-D39)<=0.5,"OK","DIVERSO") -> OK | F39: capitolo 1
A41: Impresa guida - lettura finanziaria
A42: Ricavi e incassi non coincidono: con i crediti in aumento l'incasso è minore del ricavo; l'ammortamento è costo senza pagamento; capitolo 1
A43: Voce | B43: Valore | C43: Unità | D43: Valore atteso (libro) | E43: Controllo | F43: Fonte nel libro
A44: Ammortamento impianti (costo senza pagamento) | B44: 74000 | C44: euro | F44: capitolo 1
A45: Aumento dei crediti verso clienti (ipotesi del caso) | B45: 180000 | C45: euro | F45: capitolo 1
A46: Incassi dalle vendite | B46: =$B$35-$B$45 -> 3206000 | C46: euro | D46: 3206000 | E46: =IF(ABS(B46-D46)<=0.5,"OK","DIVERSO") -> OK | F46: capitolo 1

Sheet Cap_02
A1: Capitolo 2 - Contabilità generale e contabilità analitica
A2: Controllo di gestione con l'intelligenza artificiale - file Excel che accompagna il libro
A3: Celle blu su fondo giallo: dati da cambiare. Celle nere: formule. «Valore atteso (libro)» e «Controllo» confrontano il calcolo con il numero stampato nel libro.
A4: Il partitario della struttura dell'impresa guida letto per natura e per destinazione, con le quadrature.
A6: Partitario della struttura - reparto di lavorazione
A7: Destinazione reparto: le voci per natura; capitolo 2
A8: Voce | B8: Valore | C8: Unità | D8: Valore atteso (libro) | E8: Controllo | F8: Fonte nel libro
A9: Retribuzioni | B9: 46000 | C9: euro | F9: capitolo 2
A10: Ammortamenti | B10: =Cap_01!$B$44 -> 74000 | C10: euro | F10: capitolo 2
A11: Lavorazioni esterne e straordinari | B11: =Impresa_guida!$B$39 -> 84000 | C11: euro | D11: 84000 | E11: =IF(ABS(B11-D11)<=0.5,"OK","DIVERSO") -> OK | F11: capitolo 2
A12: Servizi, sistemi e materiali | B12: 0 | C12: euro | F12: capitolo 2
A13: Totale reparto | B13: =$B$9+$B$10+$B$11+$B$12 -> 204000 | C13: euro | D13: 204000 | E13: =IF(ABS(B13-D13)<=0.5,"OK","DIVERSO") -> OK | F13: capitolo 2
A15: Partitario della struttura - funzioni che servono i clienti
A16: Gestione ordini, consegne, assistenza tecnica; capitolo 2
A17: Voce | B17: Valore | C17: Unità | D17: Valore atteso (libro) | E17: Controllo | F17: Fonte nel libro
A18: Gestione ordini - retribuzioni | B18: 186000 | C18: euro | F18: capitolo 2
A19: Gestione ordini - servizi, sistemi e materiali | B19: 54000 | C19: euro | F19: capitolo 2
A20: Totale gestione ordini | B20: =$B$18+$B$19 -> 240000 | C20: euro | D20: 240000 | E20: =IF(ABS(B20-D20)<=0.5,"OK","DIVERSO") -> OK | F20: capitolo 2
A21: Consegne - retribuzioni | B21: 42000 | C21: euro | F21: capitolo 2
A22: Consegne - servizi (trasporti su vendite) | B22: 138000 | C22: euro | F22: capitolo 2
A23: Totale consegne | B23: =$B$21+$B$22 -> 180000 | C23: euro | D23: 180000 | E23: =IF(ABS(B23-D23)<=0.5,"OK","DIVERSO") -> OK | F23: capitolo 2
A24: Assistenza tecnica - retribuzioni | B24: 118000 | C24: euro | F24: capitolo 2
A25: Assistenza tecnica - ricambi e trasferte | B25: 32000 | C25: euro | F25: capitolo 2
A26: Totale assistenza tecnica | B26: =$B$24+$B$25 -> 150000 | C26: euro | D26: 150000 | E26: =IF(ABS(B26-D26)<=0.5,"OK","DIVERSO") -> OK | F26: capitolo 2
A27: Funzioni che servono i clienti | B27: =$B$20+$B$23+$B$26 -> 570000 | C27: euro | D27: 570000 | E27: =IF(ABS(B27-D27)<=0.5,"OK","DIVERSO") -> OK | F27: capitolo 2
A29: Partitario della struttura - amministrazione
A30: Destinazione amministrazione; capitolo 2
A31: Voce | B31: Valore | C31: Unità | D31: Valore atteso (libro) | E31: Controllo | F31: Fonte nel libro
A32: Retribuzioni amministrative | B32: =Impresa_guida!$B$25 -> 46000 | C32: euro | D32: 46000 | E32: =IF(ABS(B32-D32)<=0.5,"OK","DIVERSO") -> OK | F32: capitolo 2
A33: Totale amministrazione | B33: =$B$32 -> 46000 | C33: euro | D33: 46000 | E33: =IF(ABS(B33-D33)<=0.5,"OK","DIVERSO") -> OK | F33: capitolo 2
A35: Totali per natura
A36: La lettura della contabilità generale; capitolo 2
A37: Voce | B37: Valore | C37: Unità | D37: Valore atteso (libro) | E37: Controllo | F37: Fonte nel libro
A38: Retribuzioni | B38: =$B$9+$B$18+$B$21+$B$24+$B$32 -> 438000 | C38: euro | D38: 438000 | E38: =IF(ABS(B38-D38)<=0.5,"OK","DIVERSO") -> OK | F38: capitolo 2
A39: Ammortamenti | B39: =$B$10 -> 74000 | C39: euro | D39: 74000 | E39: =IF(ABS(B39-D39)<=0.5,"OK","DIVERSO") -> OK | F39: capitolo 2
A40: Lavorazioni esterne e straordinari | B40: =$B$11 -> 84000 | C40: euro | D40: 84000 | E40: =IF(ABS(B40-D40)<=0.5,"OK","DIVERSO") -> OK | F40: capitolo 2
A41: Servizi, sistemi e materiali | B41: =$B$12+$B$19+$B$22+$B$25 -> 224000 | C41: euro | D41: 224000 | E41: =IF(ABS(B41-D41)<=0.5,"OK","DIVERSO") -> OK | F41: capitolo 2
A42: Totale per natura | B42: =$B$38+$B$39+$B$40+$B$41 -> 820000 | C42: euro | D42: 820000 | E42: =IF(ABS(B42-D42)<=0.5,"OK","DIVERSO") -> OK | F42: capitolo 2
A44: Quadratura natura - destinazione
A45: La riclassificazione sposta gli importi, non li crea e non li perde; capitolo 2
A46: Voce | B46: Valore | C46: Unità | D46: Valore atteso (libro) | E46: Controllo | F46: Fonte nel libro
A47: Totale per destinazione | B47: =$B$13+$B$20+$B$23+$B$26+$B$33 -> 820000 | C47: euro | D47: 820000 | E47: =IF(ABS(B47-D47)<=0.5,"OK","DIVERSO") -> OK | F47: capitolo 2
A48: Differenza natura - destinazione | B48: =$B$42-$B$47 -> 0 | C48: euro | D48: 0 | E48: =IF(ABS(B48-D48)<=0.5,"OK","DIVERSO") -> OK | F48: capitolo 2
A49: Differenza con i costi della struttura del master | B49: =$B$47-Impresa_guida!$B$41 -> 0 | C49: euro | D49: 0 | E49: =IF(ABS(B49-D49)<=0.5,"OK","DIVERSO") -> OK | F49: capitolo 2
A50: Differenza costi indiretti di produzione (retribuzioni + ammortamenti di reparto) con il master | B50: =$B$9+$B$10-Impresa_guida!$B$24 -> 0 | C50: euro | D50: 0 | E50: =IF(ABS(B50-D50)<=0.5,"OK","DIVERSO") -> OK | F50: capitolo 2
A51: Differenza funzioni clienti con il master | B51: =$B$27-Impresa_guida!$B$23 -> 0 | C51: euro | D51: 0 | E51: =IF(ABS(B51-D51)<=0.5,"OK","DIVERSO") -> OK | F51: capitolo 2
A53: Lavorazioni esterne: un importo, tre domande
A54: Gli 84.000 euro sono 3.000 ore di capacità aggiuntiva a 28 euro oltre le 21.000 ore del reparto; capitolo 2
A55: Voce | B55: Valore | C55: Unità | D55: Valore atteso (libro) | E55: Controllo | F55: Fonte nel libro
A56: Ore di capacità aggiuntiva | B56: =Impresa_guida!$B$37-Impresa_guida!$B$26 -> 3000 | C56: ore | D56: 3000 | E56: =IF(ABS(B56-D56)<=0.5,"OK","DIVERSO") -> OK | F56: capitolo 2
A57: Costo della capacità aggiuntiva | B57: =$B$56*Impresa_guida!$B$27 -> 84000 | C57: euro | D57: 84000 | E57: =IF(ABS(B57-D57)<=0.5,"OK","DIVERSO") -> OK | F57: capitolo 2
A58: Differenza con il partitario | B58: =$B$57-$B$11 -> 0 | C58: euro | D58: 0 | E58: =IF(ABS(B58-D58)<=0.5,"OK","DIVERSO") -> OK | F58: capitolo 2

Sheet Cap_03
A1: Capitolo 3 - Il concetto di costo e le classificazioni
A2: Controllo di gestione con l'intelligenza artificiale - file Excel che accompagna il libro
A3: Celle blu su fondo giallo: dati da cambiare. Celle nere: formule. «Valore atteso (libro)» e «Controllo» confrontano il calcolo con il numero stampato nel libro.
A4: Il costo come risorsa consumata e la stessa voce letta da più prospettive.
A6: Costo della risorsa consumata
A7: Costo = quantità consumata x valore unitario; il non consumato resta in magazzino; capitolo 3
A8: Voce | B8: Valore | C8: Unità | D8: Valore atteso (libro) | E8: Controllo | F8: Fonte nel libro
A9: Materiale acquistato | B9: 1000 | C9: unità | F9: capitolo 3
A10: Materiale consumato nel mese | B10: 600 | C10: unità | F10: capitolo 3
A11: Valore al chilogrammo | B11: 8 | C11: euro/kg | F11: capitolo 3
A12: Costo del materiale consumato | B12: =$B$10*$B$11 -> 4800 | C12: euro | D12: 4800 | E12: =IF(ABS(B12-D12)<=0.5,"OK","DIVERSO") -> OK | F12: capitolo 3
A13: Valore rimasto in magazzino | B13: =($B$9-$B$10)*$B$11 -> 3200 | C13: euro | D13: 3200 | E13: =IF(ABS(B13-D13)<=0.5,"OK","DIVERSO") -> OK | F13: capitolo 3
A15: Lettura per natura del personale
A16: Il dato per natura segnala l'aumento ma non dice dove nasce; capitolo 3
A17: Voce | B17: Valore | C17: Unità | D17: Valore atteso (libro) | E17: Controllo | F17: Fonte nel libro
A18: Costo del personale - prima | B18: 500000 | C18: euro | F18: capitolo 3
A19: Costo del personale - dopo | B19: 600000 | C19: euro | F19: capitolo 3
A20: Aumento | B20: =$B$19-$B$18 -> 100000 | C20: euro | D20: 100000 | E20: =IF(ABS(B20-D20)<=0.5,"OK","DIVERSO") -> OK | F20: capitolo 3
A22: Costo variabile e costo fisso
A23: Il variabile segue i volumi; il fisso resta nel totale ma scende per unità; capitolo 3
A24: Voce | B24: Valore | C24: Unità | D24: Valore atteso (libro) | E24: Controllo | F24: Fonte nel libro
A25: Materiale per unità | B25: 4 | C25: euro/unità | F25: capitolo 3
A26: Volume 1 | B26: 1000 | C26: unità | F26: capitolo 3
A27: Volume 2 | B27: 1500 | C27: unità | F27: capitolo 3
A28: Costo variabile - volume 1 | B28: =$B$25*$B$26 -> 4000 | C28: euro | D28: 4000 | E28: =IF(ABS(B28-D28)<=0.5,"OK","DIVERSO") -> OK | F28: capitolo 3
A29: Costo variabile - volume 2 | B29: =$B$25*$B$27 -> 6000 | C29: euro | D29: 6000 | E29: =IF(ABS(B29-D29)<=0.5,"OK","DIVERSO") -> OK | F29: capitolo 3
A30: Canone mensile | B30: 10000 | C30: euro | F30: capitolo 3
A31: Costo fisso per unità - volume 1 | B31: =$B$30/$B$26 -> 10 | C31: euro/unità | D31: 10 | E31: =IF(ABS(B31-D31)<=0.005,"OK","DIVERSO") -> OK | F31: capitolo 3
A32: Costo fisso per unità - volume 2 | B32: =$B$30/$B$27 -> 6.6666667 | C32: euro/unità | D32: 6.67 | E32: =IF(ABS(B32-D32)<=0.005,"OK","DIVERSO") -> OK | F32: capitolo 3
A34: Impresa guida - la voce lavorazioni esterne
A35: Il comportamento dipende dalle ore oltre le 21.000: 84.000 / 28 = 3.000 ore; capitolo 3
A36: Voce | B36: Valore | C36: Unità | D36: Valore atteso (libro) | E36: Controllo | F36: Fonte nel libro
A37: Ore coperte dalla voce (84.000 / 28) | B37: =Cap_02!$B$11/Impresa_guida!$B$27 -> 3000 | C37: ore | D37: 3000 | E37: =IF(ABS(B37-D37)<=0.5,"OK","DIVERSO") -> OK | F37: capitolo 3
A38: Ore richieste oltre la capacità | B38: =Impresa_guida!$B$37-Impresa_guida!$B$26 -> 3000 | C38: ore | D38: 3000 | E38: =IF(ABS(B38-D38)<=0.5,"OK","DIVERSO") -> OK | F38: capitolo 3
A39: Differenza | B39: =$B$37-$B$38 -> 0 | C39: ore | D39: 0 | E39: =IF(ABS(B39-D39)<=0.5,"OK","DIVERSO") -> OK | F39: capitolo 3
A41: Impresa guida - struttura rispetto alla decisione sui volumi
A42: I dieci conti divisi in tre gruppi; capitolo 3
A43: Voce | B43: Valore | C43: Unità | D43: Valore atteso (libro) | E43: Controllo | F43: Fonte nel libro
A44: Riducibili entro l'esercizio (lavorazioni, trasporti, ricambi) | B44: =Cap_02!$B$11+Cap_02!$B$22+Cap_02!$B$25 -> 254000 | C44: euro | D44: 254000 | E44: =IF(ABS(B44-D44)<=0.5,"OK","DIVERSO") -> OK | F44: capitolo 3
A45: Riducibili nelle decisioni di volume del caso | B45: =Cap_02!$B$11 -> 84000 | C45: euro | D45: 84000 | E45: =IF(ABS(B45-D45)<=0.5,"OK","DIVERSO") -> OK | F45: capitolo 3
A46: Riducibili solo sugli organici (retribuzioni) | B46: =Cap_02!$B$9+Cap_02!$B$18+Cap_02!$B$21+Cap_02!$B$24 -> 392000 | C46: euro | D46: 392000 | E46: =IF(ABS(B46-D46)<=0.5,"OK","DIVERSO") -> OK | F46: capitolo 3
A47: Invariati (ammortamento, sistemi ordini, amministrazione) | B47: =Cap_02!$B$10+Cap_02!$B$19+Cap_02!$B$32 -> 174000 | C47: euro | D47: 174000 | E47: =IF(ABS(B47-D47)<=0.5,"OK","DIVERSO") -> OK | F47: capitolo 3
A48: Totale dei tre gruppi | B48: =$B$44+$B$46+$B$47 -> 820000 | C48: euro | D48: 820000 | E48: =IF(ABS(B48-D48)<=0.5,"OK","DIVERSO") -> OK | F48: capitolo 3

Sheet Cap_04
A1: Capitolo 4 - Comportamento dei costi
A2: Controllo di gestione con l'intelligenza artificiale - file Excel che accompagna il libro
A3: Celle blu su fondo giallo: dati da cambiare. Celle nere: formule. «Valore atteso (libro)» e «Controllo» confrontano il calcolo con il numero stampato nel libro.
A4: Costi variabili, fissi, misti e a gradini, la funzione di costo e la simulazione dei livelli di attività dell'impresa guida.
A6: Costo variabile
A7: Costo variabile totale = costo variabile unitario x quantità; capitolo 4
A8: Voce | B8: Valore | C8: Unità | D8: Valore atteso (libro) | E8: Controllo | F8: Fonte nel libro
A9: Materiale per unità | B9: 6 | C9: euro/unità | F9: capitolo 4
A10: Quantità 1 | B10: 1000 | C10: unità | F10: capitolo 4
A11: Quantità 2 | B11: 1500 | C11: unità | F11: capitolo 4
A12: Quantità 3 | B12: 2000 | C12: unità | F12: capitolo 4
A13: Costo variabile totale - quantità 1 | B13: =$B$9*$B$10 -> 6000 | C13: euro | D13: 6000 | E13: =IF(ABS(B13-D13)<=0.5,"OK","DIVERSO") -> OK | F13: capitolo 4
A14: Costo variabile totale - quantità 2 | B14: =$B$9*$B$11 -> 9000 | C14: euro | D14: 9000 | E14: =IF(ABS(B14-D14)<=0.5,"OK","DIVERSO") -> OK | F14: capitolo 4
A15: Costo variabile totale - quantità 3 | B15: =$B$9*$B$12 -> 12000 | C15: euro | D15: 12000 | E15: =IF(ABS(B15-D15)<=0.5,"OK","DIVERSO") -> OK | F15: capitolo 4
A17: Costo fisso e costo fisso unitario
A18: Costo fisso unitario = costo fisso totale / quantità: scende quando il volume cresce; capitolo 4
A19: Voce | B19: Valore | C19: Unità | D19: Valore atteso (libro) | E19: Controllo | F19: Fonte nel libro
A20: Canone mensile | B20: 12000 | C20: euro | F20: capitolo 4
A21: Costo fisso unitario - quantità 1 | B21: =$B$20/$B$10 -> 12 | C21: euro/unità | D21: 12 | E21: =IF(ABS(B21-D21)<=0.005,"OK","DIVERSO") -> OK | F21: capitolo 4
A22: Costo fisso unitario - quantità 2 | B22: =$B$20/$B$11 -> 8 | C22: euro/unità | D22: 8 | E22: =IF(ABS(B22-D22)<=0.005,"OK","DIVERSO") -> OK | F22: capitolo 4
A23: Costo fisso unitario - quantità 3 | B23: =$B$20/$B$12 -> 6 | C23: euro/unità | D23: 6 | E23: =IF(ABS(B23-D23)<=0.005,"OK","DIVERSO") -> OK | F23: capitolo 4
A25: Capacità inutilizzata - esempio
A26: Le ore non impiegate si espongono a parte, non si caricano sui prodotti; capitolo 4
A27: Voce | B27: Valore | C27: Unità | D27: Valore atteso (libro) | E27: Controllo | F27: Fonte nel libro
A28: Costo della struttura | B28: 120000 | C28: euro | F28: capitolo 4
A29: Ore sostenibili | B29: 12000 | C29: ore | F29: capitolo 4
A30: Ore utilizzate | B30: 9000 | C30: ore | F30: capitolo 4
A31: Costo teorico della capacità per ora | B31: =$B$28/$B$29 -> 10 | C31: euro/ora | D31: 10 | E31: =IF(ABS(B31-D31)<=0.005,"OK","DIVERSO") -> OK | F31: capitolo 4
A32: Capacità disponibile non impiegata | B32: =($B$29-$B$30)*$B$31 -> 30000 | C32: euro | D32: 30000 | E32: =IF(ABS(B32-D32)<=0.5,"OK","DIVERSO") -> OK | F32: capitolo 4
A34: Metodo dei livelli massimo e minimo
A35: Stima della funzione di un costo misto: variabile per ora e componente fissa; capitolo 4
A36: Voce | B36: Valore | C36: Unità | D36: Valore atteso (libro) | E36: Controllo | F36: Fonte nel libro
A37: Livello alto - ore macchina | B37: 8000 | C37: ore | F37: capitolo 4
A38: Livello alto - costo manutenzione | B38: 34000 | C38: euro | F38: capitolo 4
A39: Livello basso - ore macchina | B39: 4000 | C39: ore | F39: capitolo 4
A40: Livello basso - costo manutenzione | B40: 22000 | C40: euro | F40: capitolo 4
A41: Differenza ore | B41: =$B$37-$B$39 -> 4000 | C41: ore | D41: 4000 | E41: =IF(ABS(B41-D41)<=0.5,"OK","DIVERSO") -> OK | F41: capitolo 4
A42: Differenza costo | B42: =$B$38-$B$40 -> 12000 | C42: euro | D42: 12000 | E42: =IF(ABS(B42-D42)<=0.5,"OK","DIVERSO") -> OK | F42: capitolo 4
A43: Costo variabile per ora | B43: =$B$42/$B$41 -> 3 | C43: euro/ora | D43: 3 | E43: =IF(ABS(B43-D43)<=0.005,"OK","DIVERSO") -> OK | F43: capitolo 4
A44: Componente fissa | B44: =$B$38-$B$43*$B$37 -> 10000 | C44: euro | D44: 10000 | E44: =IF(ABS(B44-D44)<=0.5,"OK","DIVERSO") -> OK | F44: capitolo 4
A45: Controllo sul livello basso (funzione - costo) | B45: =$B$44+$B$43*$B$39-$B$40 -> 0 | C45: euro | D45: 0 | E45: =IF(ABS(B45-D45)<=0.5,"OK","DIVERSO") -> OK | F45: capitolo 4
A47: Previsione mensile con un gradino
A48: Ogni voce si ricostruisce secondo il suo comportamento, soglia compresa; capitolo 4
A49: Voce | B49: Valore | C49: Unità | D49: Valore atteso (libro) | E49: Controllo | F49: Fonte nel libro
A50: Volume atteso | B50: 6000 | C50: unità | F50: capitolo 4
A51: Costo variabile unitario | B51: 14 | C51: euro/unità | F51: capitolo 4
A52: Struttura fissa | B52: 70000 | C52: euro | F52: capitolo 4
A53: Soglia del supervisore aggiuntivo | B53: 5000 | C53: unità | F53: capitolo 4
A54: Costo del supervisore aggiuntivo | B54: 8000 | C54: euro | F54: capitolo 4
A55: Costi variabili | B55: =$B$50*$B$51 -> 84000 | C55: euro | D55: 84000 | E55: =IF(ABS(B55-D55)<=0.5,"OK","DIVERSO") -> OK | F55: capitolo 4
A56: Gradino di capacità | B56: =IF($B$50>$B$53,$B$54,0) -> 8000 | C56: euro | D56: 8000 | E56: =IF(ABS(B56-D56)<=0.5,"OK","DIVERSO") -> OK | F56: capitolo 4
A57: Costo previsto | B57: =$B$55+$B$52+$B$56 -> 162000 | C57: euro | D57: 162000 | E57: =IF(ABS(B57-D57)<=0.5,"OK","DIVERSO") -> OK | F57: capitolo 4
A59: Impresa guida - funzione di costo a tratti
A60: Costo totale = struttura base + costi variabili di linea + 28 x ore oltre 21.000; capitolo 4
A61: Voce | B61: Valore | C61: Unità | D61: Valore atteso (libro) | E61: Controllo | F61: Fonte nel libro
A62: Costi variabili di linea | B62: =Impresa_guida!$B$35 -> 2324000 | C62: euro | D62: 2324000 | E62: =IF(ABS(B62-D62)<=0.5,"OK","DIVERSO") -> OK | F62: capitolo 4
A63: Struttura base (820.000 - 84.000) | B63: =Impresa_guida!$B$41-Impresa_guida!$B$39 -> 736000 | C63: euro | D63: 736000 | E63: =IF(ABS(B63-D63)<=0.5,"OK","DIVERSO") -> OK | F63: capitolo 4
A64: Capacità aggiuntiva | B64: =MAX(Impresa_guida!$B$37-Impresa_guida!$B$26,0)*Impresa_guida!$B$27 -> 84000 | C64: euro | D64: 84000 | E64: =IF(ABS(B64-D64)<=0.5,"OK","DIVERSO") -> OK | F64: capitolo 4
A65: Costo totale | B65: =$B$63+$B$62+$B$64 -> 3144000 | C65: euro | D65: 3144000 | E65: =IF(ABS(B65-D65)<=0.5,"OK","DIVERSO") -> OK | F65: capitolo 4
A66: Controllo: ricavi - risultato operativo - costo totale | B66: =Impresa_guida!$B$34-Impresa_guida!$B$42-$B$65 -> 0 | C66: euro | D66: 0 | E66: =IF(ABS(B66-D66)<=0.5,"OK","DIVERSO") -> OK | F66: capitolo 4
A68: Impresa guida - simulazione dei livelli di attività
A69: Stesse proporzioni fra le linee, prezzi e costi unitari invariati, struttura base costante; capitolo 4
A70: Voce | B70: Valore | C70: Unità | D70: Valore atteso (libro) | E70: Controllo | F70: Fonte nel libro
A71: Livello 80% - livello di attività | B71: 0.8 | C71: % | F71: capitolo 4
A72: Livello 80% - unità | B72: =$B$71*(Impresa_guida!$B$8+Impresa_guida!$B$12+Impresa_guida!$B$16) -> 17600 | C72: unità | D72: 17600 | E72: =IF(ABS(B72-D72)<=0.5,"OK","DIVERSO") -> OK | F72: capitolo 4
A73: Livello 80% - ore macchina | B73: =$B$71*Impresa_guida!$B$37 -> 19200 | C73: ore | D73: 19200 | E73: =IF(ABS(B73-D73)<=0.5,"OK","DIVERSO") -> OK | F73: capitolo 4
A74: Livello 80% - costi variabili | B74: =$B$71*Impresa_guida!$B$35 -> 1859200 | C74: euro | D74: 1859200 | E74: =IF(ABS(B74-D74)<=0.5,"OK","DIVERSO") -> OK | F74: capitolo 4
A75: Livello 80% - ore di capacità aggiuntiva | B75: =MAX($B$73-Impresa_guida!$B$26,0) -> 0 | C75: ore | D75: 0 | E75: =IF(ABS(B75-D75)<=0.5,"OK","DIVERSO") -> OK | F75: capitolo 4
A76: Livello 80% - capacità aggiuntiva | B76: =$B$75*Impresa_guida!$B$27 -> 0 | C76: euro | D76: 0 | E76: =IF(ABS(B76-D76)<=0.5,"OK","DIVERSO") -> OK | F76: capitolo 4
A77: Livello 80% - costo totale | B77: =Impresa_guida!$B$40+$B$74+$B$76 -> 2595200 | C77: euro | D77: 2595200 | E77: =IF(ABS(B77-D77)<=0.5,"OK","DIVERSO") -> OK | F77: capitolo 4
A78: Livello 80% - struttura base per ora | B78: =Impresa_guida!$B$40/$B$73 -> 38.333333 | C78: euro/ora | D78: 38.33 | E78: =IF(ABS(B78-D78)<=0.005,"OK","DIVERSO") -> OK | F78: capitolo 4
A79: Livello 87,5% - livello di attività | B79: 0.875 | C79: % | F79: capitolo 4
A80: Livello 87,5% - unità | B80: =$B$79*(Impresa_guida!$B$8+Impresa_guida!$B$12+Impresa_guida!$B$16) -> 19250 | C80: unità | D80: 19250 | E80: =IF(ABS(B80-D80)<=0.5,"OK","DIVERSO") -> OK | F80: capitolo 4
A81: Livello 87,5% - ore macchina | B81: =$B$79*Impresa_guida!$B$37 -> 21000 | C81: ore | D81: 21000 | E81: =IF(ABS(B81-D81)<=0.5,"OK","DIVERSO") -> OK | F81: capitolo 4
A82: Livello 87,5% - costi variabili | B82: =$B$79*Impresa_guida!$B$35 -> 2033500 | C82: euro | D82: 2033500 | E82: =IF(ABS(B82-D82)<=0.5,"OK","DIVERSO") -> OK | F82: capitolo 4
A83: Livello 87,5% - ore di capacità aggiuntiva | B83: =MAX($B$81-Impresa_guida!$B$26,0) -> 0 | C83: ore | D83: 0 | E83: =IF(ABS(B83-D83)<=0.5,"OK","DIVERSO") -> OK | F83: capitolo 4
A84: Livello 87,5% - capacità aggiuntiva | B84: =$B$83*Impresa_guida!$B$27 -> 0 | C84: euro | D84: 0 | E84: =IF(ABS(B84-D84)<=0.5,"OK","DIVERSO") -> OK | F84: capitolo 4
A85: Livello 87,5% - costo totale | B85: =Impresa_guida!$B$40+$B$82+$B$84 -> 2769500 | C85: euro | D85: 2769500 | E85: =IF(ABS(B85-D85)<=0.5,"OK","DIVERSO") -> OK | F85: capitolo 4
A86: Livello 87,5% - struttura base per ora | B86: =Impresa_guida!$B$40/$B$81 -> 35.047619 | C86: euro/ora | D86: 35.05 | E86: =IF(ABS(B86-D86)<=0.005,"OK","DIVERSO") -> OK | F86: capitolo 4
A87: Livello 90% - livello di attività | B87: 0.9 | C87: % | F87: capitolo 4
A88: Livello 90% - unità | B88: =$B$87*(Impresa_guida!$B$8+Impresa_guida!$B$12+Impresa_guida!$B$16) -> 19800 | C88: unità | D88: 19800 | E88: =IF(ABS(B88-D88)<=0.5,"OK","DIVERSO") -> OK | F88: capitolo 4
A89: Livello 90% - ore macchina | B89: =$B$87*Impresa_guida!$B$37 -> 21600 | C89: ore | D89: 21600 | E89: =IF(ABS(B89-D89)<=0.5,"OK","DIVERSO") -> OK | F89: capitolo 4
A90: Livello 90% - costi variabili | B90: =$B$87*Impresa_guida!$B$35 -> 2091600 | C90: euro | D90: 2091600 | E90: =IF(ABS(B90-D90)<=0.5,"OK","DIVERSO") -> OK | F90: capitolo 4
A91: Livello 90% - ore di capacità aggiuntiva | B91: =MAX($B$89-Impresa_guida!$B$26,0) -> 600 | C91: ore | D91: 600 | E91: =IF(ABS(B91-D91)<=0.5,"OK","DIVERSO") -> OK | F91: capitolo 4
A92: Livello 90% - capacità aggiuntiva | B92: =$B$91*Impresa_guida!$B$27 -> 16800 | C92: euro | D92: 16800 | E92: =IF(ABS(B92-D92)<=0.5,"OK","DIVERSO") -> OK | F92: capitolo 4
A93: Livello 90% - costo totale | B93: =Impresa_guida!$B$40+$B$90+$B$92 -> 2844400 | C93: euro | D93: 2844400 | E93: =IF(ABS(B93-D93)<=0.5,"OK","DIVERSO") -> OK | F93: capitolo 4
A94: Livello 90% - struttura base per ora | B94: =Impresa_guida!$B$40/$B$89 -> 34.074074 | C94: euro/ora | D94: 34.07 | E94: =IF(ABS(B94-D94)<=0.005,"OK","DIVERSO") -> OK | F94: capitolo 4
A95: Livello 100% - livello di attività | B95: 1 | C95: % | F95: capitolo 4
A96: Livello 100% - unità | B96: =$B$95*(Impresa_guida!$B$8+Impresa_guida!$B$12+Impresa_guida!$B$16) -> 22000 | C96: unità | D96: 22000 | E96: =IF(ABS(B96-D96)<=0.5,"OK","DIVERSO") -> OK | F96: capitolo 4
A97: Livello 100% - ore macchina | B97: =$B$95*Impresa_guida!$B$37 -> 24000 | C97: ore | D97: 24000 | E97: =IF(ABS(B97-D97)<=0.5,"OK","DIVERSO") -> OK | F97: capitolo 4
A98: Livello 100% - costi variabili | B98: =$B$95*Impresa_guida!$B$35 -> 2324000 | C98: euro | D98: 2324000 | E98: =IF(ABS(B98-D98)<=0.5,"OK","DIVERSO") -> OK | F98: capitolo 4
A99: Livello 100% - ore di capacità aggiuntiva | B99: =MAX($B$97-Impresa_guida!$B$26,0) -> 3000 | C99: ore | D99: 3000 | E99: =IF(ABS(B99-D99)<=0.5,"OK","DIVERSO") -> OK | F99: capitolo 4
A100: Livello 100% - capacità aggiuntiva | B100: =$B$99*Impresa_guida!$B$27 -> 84000 | C100: euro | D100: 84000 | E100: =IF(ABS(B100-D100)<=0.5,"OK","DIVERSO") -> OK | F100: capitolo 4
A101: Livello 100% - costo totale | B101: =Impresa_guida!$B$40+$B$98+$B$100 -> 3144000 | C101: euro | D101: 3144000 | E101: =IF(ABS(B101-D101)<=0.5,"OK","DIVERSO") -> OK | F101: capitolo 4
A102: Livello 100% - struttura base per ora | B102: =Impresa_guida!$B$40/$B$97 -> 30.666667 | C102: euro/ora | D102: 30.67 | E102: =IF(ABS(B102-D102)<=0.005,"OK","DIVERSO") -> OK | F102: capitolo 4
A104: Impresa guida - capacità inutilizzata all'80%
A105: Le ore libere valorizzate al costo della capacità del reparto, calcolato senza arrotondare; capitolo 4
A106: Voce | B106: Valore | C106: Unità | D106: Valore atteso (libro) | E106: Controllo | F106: Fonte nel libro
A107: Ore libere all'80% | B107: =Impresa_guida!$B$26-$B$73 -> 1800 | C107: ore | D107: 1800 | E107: =IF(ABS(B107-D107)<=0.5,"OK","DIVERSO") -> OK | F107: capitolo 4
A108: Costi indiretti di produzione (46.000 + 74.000) | B108: =Cap_02!$B$9+Cap_02!$B$10 -> 120000 | C108: euro | D108: 120000 | E108: =IF(ABS(B108-D108)<=0.5,"OK","DIVERSO") -> OK | F108: capitolo 4
...

Sheet Cap_05
A1: Capitolo 5 - Oggetti di costo e centri di costo
A2: Controllo di gestione con l'intelligenza artificiale - file Excel che accompagna il libro
A3: Celle blu su fondo giallo: dati da cambiare. Celle nere: formule. «Valore atteso (libro)» e «Controllo» confrontano il calcolo con il numero stampato nel libro.
A4: Il piano dei sette centri dell'impresa guida e la sua quadratura con i costi della struttura, prima di qualsiasi allocazione.
A6: Oggetti di costo dell'impresa guida
A7: Linee e canali come oggetti finali: unità, ricavi e clienti per canale; capitolo 5
A8: Voce | B8: Valore | C8: Unità | D8: Valore atteso (libro) | E8: Controllo | F8: Fonte nel libro
A9: Unità vendute, tre linee | B9: =Impresa_guida!$B$8+Impresa_guida!$B$12+Impresa_guida!$B$16 -> 22000 | C9: unità | D9: 22000 | E9: =IF(ABS(B9-D9)<=0.5,"OK","DIVERSO") -> OK | F9: capitolo 5
A10: Ricavi delle tre linee | B10: =Impresa_guida!$B$34 -> 3386000 | C10: euro | D10: 3386000 | E10: =IF(ABS(B10-D10)<=0.5,"OK","DIVERSO") -> OK | F10: capitolo 5
A11: Canale diretto - clienti | B11: 218 | C11: clienti | F11: capitolo 5
A12: Canale diretto - ricavi | B12: 1220000 | C12: euro | F12: capitolo 5
A13: Distributori - ricavi | B13: 2166000 | C13: euro | F13: capitolo 5
A14: Ricavi dei due canali | B14: =$B$12+$B$13 -> 3386000 | C14: euro | D14: 3386000 | E14: =IF(ABS(B14-D14)<=0.5,"OK","DIVERSO") -> OK | F14: capitolo 5
A15: Controllo canali meno linee | B15: =$B$14-Impresa_guida!$B$34 -> 0 | C15: euro | D15: 0 | E15: =IF(ABS(B15-D15)<=0.5,"OK","DIVERSO") -> OK | F15: capitolo 5
A16: Ore macchina richieste dai volumi | B16: =Impresa_guida!$B$37 -> 24000 | C16: ore | D16: 24000 | E16: =IF(ABS(B16-D16)<=0.5,"OK","DIVERSO") -> OK | F16: capitolo 5
A17: Ore di cui il reparto dispone | B17: =Impresa_guida!$B$26 -> 21000 | C17: ore | D17: 21000 | E17: =IF(ABS(B17-D17)<=0.5,"OK","DIVERSO") -> OK | F17: capitolo 5
A19: Piano dei centri - reparto
A20: Tre centri del reparto: due ausiliari e un produttivo, con la misura di attività; capitolo 5
A21: Voce | B21: Valore | C21: Unità | D21: Valore atteso (libro) | E21: Controllo | F21: Fonte nel libro
A22: Manutenzione (ausiliario) | B22: 36000 | C22: euro | F22: capitolo 5
A23: Programmazione e qualità (ausiliario) | B23: 18000 | C23: euro | F23: capitolo 5
A24: Lavorazione (produttivo) | B24: 66000 | C24: euro | F24: capitolo 5
A25: Lavorazione - ore macchina (con le 3.000 esterne) | B25: =Impresa_guida!$B$37 -> 24000 | C25: ore | D25: 24000 | E25: =IF(ABS(B25-D25)<=0.5,"OK","DIVERSO") -> OK | F25: capitolo 5
A26: di cui ore di capacità esterna | B26: =Impresa_guida!$B$38 -> 3000 | C26: ore | D26: 3000 | E26: =IF(ABS(B26-D26)<=0.5,"OK","DIVERSO") -> OK | F26: capitolo 5
A27: Totale centri del reparto | B27: =$B$22+$B$23+$B$24 -> 120000 | C27: euro | D27: 120000 | E27: =IF(ABS(B27-D27)<=0.5,"OK","DIVERSO") -> OK | F27: capitolo 5
A28: Controllo con i costi indiretti di produzione | B28: =$B$27-Impresa_guida!$B$24 -> 0 | C28: euro | D28: 0 | E28: =IF(ABS(B28-D28)<=0.5,"OK","DIVERSO") -> OK | F28: capitolo 5
A30: Piano dei centri - commerciali e logistici
A31: Tre centri che servono i clienti, con il volume della loro misura di attività; capitolo 5
A32: Voce | B32: Valore | C32: Unità | D32: Valore atteso (libro) | E32: Controllo | F32: Fonte nel libro
A33: Gestione ordini | B33: =Cap_02!$B$20 -> 240000 | C33: euro | F33: capitolo 5
A34: Gestione ordini - numero ordini | B34: 12000 | C34: ordini | F34: capitolo 5
A35: Consegne | B35: =Cap_02!$B$23 -> 180000 | C35: euro | F35: capitolo 5
A36: Consegne - numero consegne | B36: 6000 | C36: consegne | F36: capitolo 5
A37: Assistenza tecnica | B37: =Cap_02!$B$26 -> 150000 | C37: euro | F37: capitolo 5
A38: Assistenza tecnica - ore di assistenza | B38: 7500 | C38: ore | F38: capitolo 5
A39: Totale centri commerciali e logistici | B39: =$B$33+$B$35+$B$37 -> 570000 | C39: euro | D39: 570000 | E39: =IF(ABS(B39-D39)<=0.5,"OK","DIVERSO") -> OK | F39: capitolo 5
A40: Controllo con le attività commerciali e logistiche | B40: =$B$39-Impresa_guida!$B$23 -> 0 | C40: euro | D40: 0 | E40: =IF(ABS(B40-D40)<=0.5,"OK","DIVERSO") -> OK | F40: paragrafo 19.3
A42: Piano dei centri - struttura
A43: Amministrazione: centro di struttura in gestione separata, non ripartito; capitolo 5
A44: Voce | B44: Valore | C44: Unità | D44: Valore atteso (libro) | E44: Controllo | F44: Fonte nel libro
A45: Amministrazione (struttura) | B45: 46000 | C45: euro | F45: capitolo 5
A46: Controllo con i costi amministrativi | B46: =$B$45-Impresa_guida!$B$25 -> 0 | C46: euro | D46: 0 | E46: =IF(ABS(B46-D46)<=0.5,"OK","DIVERSO") -> OK | F46: paragrafo 19.3
A48: Quadratura del piano
A49: Sette centri, riga propria della capacità esterna e ritorno ai costi della struttura; capitolo 5
A50: Voce | B50: Valore | C50: Unità | D50: Valore atteso (libro) | E50: Controllo | F50: Fonte nel libro
A51: Costi raccolti dai sette centri | B51: =$B$27+$B$39+$B$45 -> 736000 | C51: euro | D51: 736000 | E51: =IF(ABS(B51-D51)<=0.5,"OK","DIVERSO") -> OK | F51: capitolo 5
A52: Controllo con la struttura base | B52: =$B$51-Impresa_guida!$B$40 -> 0 | C52: euro | D52: 0 | E52: =IF(ABS(B52-D52)<=0.5,"OK","DIVERSO") -> OK | F52: capitolo 5
A53: Capacità aggiuntiva - ore | B53: =Impresa_guida!$B$38 -> 3000 | C53: ore | D53: 3000 | E53: =IF(ABS(B53-D53)<=0.5,"OK","DIVERSO") -> OK | F53: capitolo 5
A54: Capacità aggiuntiva - costo orario | B54: =Impresa_guida!$B$27 -> 28 | C54: euro/ora | D54: 28 | E54: =IF(ABS(B54-D54)<=0.5,"OK","DIVERSO") -> OK | F54: capitolo 5
A55: Lavorazioni esterne e straordinari (riga propria) | B55: =$B$53*$B$54 -> 84000 | C55: euro | D55: 84000 | E55: =IF(ABS(B55-D55)<=0.5,"OK","DIVERSO") -> OK | F55: capitolo 5
A56: Totale costi della struttura | B56: =$B$51+$B$55 -> 820000 | C56: euro | D56: 820000 | E56: =IF(ABS(B56-D56)<=0.5,"OK","DIVERSO") -> OK | F56: capitolo 5
A57: Controllo con il Conto Economico gestionale | B57: =$B$56-Impresa_guida!$B$41 -> 0 | C57: euro | D57: 0 | E57: =IF(ABS(B57-D57)<=0.5,"OK","DIVERSO") -> OK | F57: capitolo 5
A59: Partitario e piano per funzione
A60: Gli stessi 120.000 euro letti per natura nel partitario e per funzione nel piano; capitolo 5
A61: Voce | B61: Valore | C61: Unità | D61: Valore atteso (libro) | E61: Controllo | F61: Fonte nel libro
A62: Partitario - ammortamento impianti | B62: =Cap_02!$B$10 -> 74000 | C62: euro | F62: capitolo 5
A63: Partitario - retribuzioni produzione indiretta | B63: =Cap_02!$B$9 -> 46000 | C63: euro | F63: capitolo 5
A64: Partitario - costi indiretti di produzione | B64: =$B$62+$B$63 -> 120000 | C64: euro | D64: 120000 | E64: =IF(ABS(B64-D64)<=0.5,"OK","DIVERSO") -> OK | F64: capitolo 5
A65: Partitario meno piano per funzione | B65: =$B$64-$B$27 -> 0 | C65: euro | D65: 0 | E65: =IF(ABS(B65-D65)<=0.5,"OK","DIVERSO") -> OK | F65: capitolo 5

Sheet Cap_06
A1: Capitolo 6 - Costi diretti, indiretti e allocazione
A2: Controllo di gestione con l'intelligenza artificiale - file Excel che accompagna il libro
A3: Celle blu su fondo giallo: dati da cambiare. Celle nere: formule. «Valore atteso (libro)» e «Controllo» confrontano il calcolo con il numero stampato nel libro.
A4: Coefficienti di allocazione, ribaltamento dei centri ausiliari con tre metodi e allocazione dei costi indiretti dell'impresa guida sulle ore e sulle unità.
A6: Coefficiente di allocazione
A7: Coefficiente = costi del centro / volume della base; costo allocato = coefficiente x base; capitolo 6
A8: Voce | B8: Valore | C8: Unità | D8: Valore atteso (libro) | E8: Controllo | F8: Fonte nel libro
A9: Costi del centro produttivo | B9: 240000 | C9: euro | F9: capitolo 6
A10: Ore macchina previste | B10: 12000 | C10: ore | F10: capitolo 6
A11: Coefficiente | B11: =$B$9/$B$10 -> 20 | C11: euro/ora | D11: 20 | E11: =IF(ABS(B11-D11)<=0.005,"OK","DIVERSO") -> OK | F11: capitolo 6
A12: Ore usate dal prodotto | B12: 150 | C12: ore | F12: capitolo 6
A13: Costo allocato al prodotto | B13: =$B$11*$B$12 -> 3000 | C13: euro | D13: 3000 | E13: =IF(ABS(B13-D13)<=0.5,"OK","DIVERSO") -> OK | F13: capitolo 6
A15: Tre metodi - dati
A16: Stabilimento con due ausiliari che si servono a vicenda: costi propri e percentuali di servizio; capitolo 6
A17: Voce | B17: Valore | C17: Unità | D17: Valore atteso (libro) | E17: Controllo | F17: Fonte nel libro
A18: Manutenzione - costi propri | B18: 50000 | C18: euro | F18: capitolo 6
A19: Servizi energetici - costi propri | B19: 35000 | C19: euro | F19: capitolo 6
A20: Lavorazione - costi propri | B20: 180000 | C20: euro | F20: capitolo 6
A21: Assemblaggio - costi propri | B21: 120000 | C21: euro | F21: capitolo 6
A22: Totale costi propri | B22: =$B$18+$B$19+$B$20+$B$21 -> 385000 | C22: euro | D22: 385000 | E22: =IF(ABS(B22-D22)<=0.5,"OK","DIVERSO") -> OK | F22: capitolo 6
A23: Manutenzione a Servizi energetici | B23: 0.25 | C23: % | F23: capitolo 6
A24: Manutenzione a Lavorazione | B24: 0.45 | C24: % | F24: capitolo 6
A25: Manutenzione ad Assemblaggio | B25: 0.3 | C25: % | F25: capitolo 6
A26: Servizi energetici a Manutenzione | B26: 0.2 | C26: % | F26: capitolo 6
A27: Servizi energetici a Lavorazione | B27: 0.2 | C27: % | F27: capitolo 6
A28: Servizi energetici ad Assemblaggio | B28: 0.6 | C28: % | F28: capitolo 6
A30: Metodo diretto
A31: Scambi fra ausiliari ignorati, percentuali ricalcolate sui soli produttivi; capitolo 6
A32: Voce | B32: Valore | C32: Unità | D32: Valore atteso (libro) | E32: Controllo | F32: Fonte nel libro
A33: Manutenzione - quota Lavorazione | B33: =$B$24/($B$24+$B$25) -> 0.6 | C33: % | D33: 0.6 | E33: =IF(ABS(B33-D33)<=0.0005,"OK","DIVERSO") -> OK | F33: capitolo 6
A34: Manutenzione - quota Assemblaggio | B34: =$B$25/($B$24+$B$25) -> 0.4 | C34: % | D34: 0.4 | E34: =IF(ABS(B34-D34)<=0.0005,"OK","DIVERSO") -> OK | F34: capitolo 6
A35: Manutenzione a Lavorazione | B35: =$B$18*$B$33 -> 30000 | C35: euro | D35: 30000 | E35: =IF(ABS(B35-D35)<=0.5,"OK","DIVERSO") -> OK | F35: capitolo 6
A36: Manutenzione ad Assemblaggio | B36: =$B$18*$B$34 -> 20000 | C36: euro | D36: 20000 | E36: =IF(ABS(B36-D36)<=0.5,"OK","DIVERSO") -> OK | F36: capitolo 6
A37: Servizi energetici - quota Lavorazione | B37: =$B$27/($B$27+$B$28) -> 0.25 | C37: % | D37: 0.25 | E37: =IF(ABS(B37-D37)<=0.0005,"OK","DIVERSO") -> OK | F37: capitolo 6
A38: Servizi energetici - quota Assemblaggio | B38: =$B$28/($B$27+$B$28) -> 0.75 | C38: % | D38: 0.75 | E38: =IF(ABS(B38-D38)<=0.0005,"OK","DIVERSO") -> OK | F38: capitolo 6
A39: Servizi energetici a Lavorazione | B39: =$B$19*$B$37 -> 8750 | C39: euro | D39: 8750 | E39: =IF(ABS(B39-D39)<=0.5,"OK","DIVERSO") -> OK | F39: capitolo 6
A40: Servizi energetici ad Assemblaggio | B40: =$B$19*$B$38 -> 26250 | C40: euro | D40: 26250 | E40: =IF(ABS(B40-D40)<=0.5,"OK","DIVERSO") -> OK | F40: capitolo 6
A41: Lavorazione dopo il metodo diretto | B41: =$B$20+$B$35+$B$39 -> 218750 | C41: euro | D41: 218750 | E41: =IF(ABS(B41-D41)<=0.5,"OK","DIVERSO") -> OK | F41: capitolo 6
A42: Assemblaggio dopo il metodo diretto | B42: =$B$21+$B$36+$B$40 -> 166250 | C42: euro | D42: 166250 | E42: =IF(ABS(B42-D42)<=0.5,"OK","DIVERSO") -> OK | F42: capitolo 6
A43: Totale dopo il metodo diretto | B43: =$B$41+$B$42 -> 385000 | C43: euro | D43: 385000 | E43: =IF(ABS(B43-D43)<=0.5,"OK","DIVERSO") -> OK | F43: capitolo 6
A45: Metodo a cascata
A46: Si chiude per primo l'ausiliario che presta più servizi all'altro; capitolo 6
A47: Voce | B47: Valore | C47: Unità | D47: Valore atteso (libro) | E47: Controllo | F47: Fonte nel libro
A48: Servizi della Manutenzione ai Servizi energetici | B48: =$B$18*$B$23 -> 12500 | C48: euro | D48: 12500 | E48: =IF(ABS(B48-D48)<=0.5,"OK","DIVERSO") -> OK | F48: capitolo 6
A49: Servizi dei Servizi energetici alla Manutenzione | B49: =$B$19*$B$26 -> 7000 | C49: euro | D49: 7000 | E49: =IF(ABS(B49-D49)<=0.5,"OK","DIVERSO") -> OK | F49: capitolo 6
A50: Centro da chiudere per primo | B50: =IF($B$48>$B$49,"Manutenzione","Servizi energetici") -> Manutenzione | D50: Manutenzione | E50: =IF(B50=D50,"OK","DIVERSO") -> OK | F50: capitolo 6
A51: Manutenzione a Lavorazione | B51: =$B$18*$B$24 -> 22500 | C51: euro | D51: 22500 | E51: =IF(ABS(B51-D51)<=0.5,"OK","DIVERSO") -> OK | F51: capitolo 6
A52: Manutenzione ad Assemblaggio | B52: =$B$18*$B$25 -> 15000 | C52: euro | D52: 15000 | E52: =IF(ABS(B52-D52)<=0.5,"OK","DIVERSO") -> OK | F52: capitolo 6
A53: Servizi energetici dopo la Manutenzione | B53: =$B$19+$B$48 -> 47500 | C53: euro | D53: 47500 | E53: =IF(ABS(B53-D53)<=0.5,"OK","DIVERSO") -> OK | F53: capitolo 6
A54: Servizi energetici a Lavorazione | B54: =$B$53*$B$37 -> 11875 | C54: euro | D54: 11875 | E54: =IF(ABS(B54-D54)<=0.5,"OK","DIVERSO") -> OK | F54: capitolo 6
A55: Servizi energetici ad Assemblaggio | B55: =$B$53*$B$38 -> 35625 | C55: euro | D55: 35625 | E55: =IF(ABS(B55-D55)<=0.5,"OK","DIVERSO") -> OK | F55: capitolo 6
A56: Lavorazione dopo la cascata | B56: =$B$20+$B$51+$B$54 -> 214375 | C56: euro | D56: 214375 | E56: =IF(ABS(B56-D56)<=0.5,"OK","DIVERSO") -> OK | F56: capitolo 6
A57: Assemblaggio dopo la cascata | B57: =$B$21+$B$52+$B$55 -> 170625 | C57: euro | D57: 170625 | E57: =IF(ABS(B57-D57)<=0.5,"OK","DIVERSO") -> OK | F57: capitolo 6
A58: Totale dopo la cascata | B58: =$B$56+$B$57 -> 385000 | C58: euro | D58: 385000 | E58: =IF(ABS(B58-D58)<=0.5,"OK","DIVERSO") -> OK | F58: capitolo 6
A60: Metodo reciproco
A61: Sistema M = 50.000 + 0,20 x S e S = 35.000 + 0,25 x M, poi distribuzione con le percentuali originali; capitolo 6
A62: Voce | B62: Valore | C62: Unità | D62: Valore atteso (libro) | E62: Controllo | F62: Fonte nel libro
A63: Manutenzione - costo complessivo M | B63: =($B$18+$B$26*$B$19)/(1-$B$26*$B$23) -> 60000 | C63: euro | D63: 60000 | E63: =IF(ABS(B63-D63)<=0.5,"OK","DIVERSO") -> OK | F63: capitolo 6
A64: Servizi energetici - costo complessivo S | B64: =$B$19+$B$23*$B$63 -> 50000 | C64: euro | D64: 50000 | E64: =IF(ABS(B64-D64)<=0.5,"OK","DIVERSO") -> OK | F64: capitolo 6
A65: Manutenzione a Lavorazione | B65: =$B$63*$B$24 -> 27000 | C65: euro | D65: 27000 | E65: =IF(ABS(B65-D65)<=0.5,"OK","DIVERSO") -> OK | F65: capitolo 6
A66: Servizi energetici a Lavorazione | B66: =$B$64*$B$27 -> 10000 | C66: euro | D66: 10000 | E66: =IF(ABS(B66-D66)<=0.5,"OK","DIVERSO") -> OK | F66: capitolo 6
A67: Manutenzione ad Assemblaggio | B67: =$B$63*$B$25 -> 18000 | C67: euro | D67: 18000 | E67: =IF(ABS(B67-D67)<=0.5,"OK","DIVERSO") -> OK | F67: capitolo 6
A68: Servizi energetici ad Assemblaggio | B68: =$B$64*$B$28 -> 30000 | C68: euro | D68: 30000 | E68: =IF(ABS(B68-D68)<=0.5,"OK","DIVERSO") -> OK | F68: capitolo 6
A69: Scambio Manutenzione a Servizi energetici | B69: =$B$63*$B$23 -> 15000 | C69: euro | D69: 15000 | E69: =IF(ABS(B69-D69)<=0.5,"OK","DIVERSO") -> OK | F69: capitolo 6
A70: Scambio Servizi energetici a Manutenzione | B70: =$B$64*$B$26 -> 10000 | C70: euro | D70: 10000 | E70: =IF(ABS(B70-D70)<=0.5,"OK","DIVERSO") -> OK | F70: capitolo 6
A71: Arrivato ai centri produttivi | B71: =$B$65+$B$66+$B$67+$B$68 -> 85000 | C71: euro | D71: 85000 | E71: =IF(ABS(B71-D71)<=0.5,"OK","DIVERSO") -> OK | F71: capitolo 6
A72: Lavorazione dopo il reciproco | B72: =$B$20+$B$65+$B$66 -> 217000 | C72: euro | D72: 217000 | E72: =IF(ABS(B72-D72)<=0.5,"OK","DIVERSO") -> OK | F72: capitolo 6
A73: Assemblaggio dopo il reciproco | B73: =$B$21+$B$67+$B$68 -> 168000 | C73: euro | D73: 168000 | E73: =IF(ABS(B73-D73)<=0.5,"OK","DIVERSO") -> OK | F73: capitolo 6
A74: Totale dopo il reciproco | B74: =$B$72+$B$73 -> 385000 | C74: euro | D74: 385000 | E74: =IF(ABS(B74-D74)<=0.5,"OK","DIVERSO") -> OK | F74: capitolo 6
A76: Confronto dei metodi
A77: Differenze sulla Lavorazione rispetto al reciproco e cascata in ordine inverso; capitolo 6
A78: Voce | B78: Valore | C78: Unità | D78: Valore atteso (libro) | E78: Controllo | F78: Fonte nel libro
A79: Lavorazione: diretto meno reciproco | B79: =$B$41-$B$72 -> 1750 | C79: euro | D79: 1750 | E79: =IF(ABS(B79-D79)<=0.5,"OK","DIVERSO") -> OK | F79: capitolo 6
A80: Lavorazione: cascata meno reciproco | B80: =$B$56-$B$72 -> -2625 | C80: euro | D80: -2625 | E80: =IF(ABS(B80-D80)<=0.5,"OK","DIVERSO") -> OK | F80: capitolo 6
A81: Ordine inverso - Servizi energetici a Manutenzione | B81: =$B$19*$B$26 -> 7000 | C81: euro | F81: capitolo 6
A82: Ordine inverso - Manutenzione salita a | B82: =$B$18+$B$81 -> 57000 | C82: euro | F82: capitolo 6
A83: Ordine inverso - Lavorazione | B83: =$B$20+$B$19*$B$27+$B$82*$B$33 -> 221200 | C83: euro | D83: 221200 | E83: =IF(ABS(B83-D83)<=0.5,"OK","DIVERSO") -> OK | F83: capitolo 6
A84: Ordine inverso - Assemblaggio | B84: =$B$21+$B$19*$B$28+$B$82*$B$34 -> 163800 | C84: euro | D84: 163800 | E84: =IF(ABS(B84-D84)<=0.5,"OK","DIVERSO") -> OK | F84: capitolo 6
A85: Ordine inverso - totale | B85: =$B$83+$B$84 -> 385000 | C85: euro | D85: 385000 | E85: =IF(ABS(B85-D85)<=0.5,"OK","DIVERSO") -> OK | F85: capitolo 6
A87: Esempio completo di allocazione
A88: Centro di 180.000 euro su 9.000 ore macchina, due prodotti; capitolo 6
A89: Voce | B89: Valore | C89: Unità | D89: Valore atteso (libro) | E89: Controllo | F89: Fonte nel libro
A90: Costi indiretti del centro | B90: 180000 | C90: euro | F90: capitolo 6
A91: Prodotto A - ore macchina | B91: 4000 | C91: ore | F91: capitolo 6
A92: Prodotto B - ore macchina | B92: 5000 | C92: ore | F92: capitolo 6
A93: Totale ore macchina | B93: =$B$91+$B$92 -> 9000 | C93: ore | D93: 9000 | E93: =IF(ABS(B93-D93)<=0.5,"OK","DIVERSO") -> OK | F93: capitolo 6
A94: Coefficiente | B94: =$B$90/$B$93 -> 20 | C94: euro/ora | D94: 20 | E94: =IF(ABS(B94-D94)<=0.005,"OK","DIVERSO") -> OK | F94: capitolo 6
A95: Prodotto A - costo allocato | B95: =$B$94*$B$91 -> 80000 | C95: euro | D95: 80000 | E95: =IF(ABS(B95-D95)<=0.5,"OK","DIVERSO") -> OK | F95: capitolo 6
A96: Prodotto B - costo allocato | B96: =$B$94*$B$92 -> 100000 | C96: euro | D96: 100000 | E96: =IF(ABS(B96-D96)<=0.5,"OK","DIVERSO") -> OK | F96: capitolo 6
A97: Totale allocato | B97: =$B$95+$B$96 -> 180000 | C97: euro | D97: 180000 | E97: =IF(ABS(B97-D97)<=0.5,"OK","DIVERSO") -> OK | F97: capitolo 6
A99: Tariffa prestabilita
A100: Scostamento del centro = costi effettivi - costi applicati; capitolo 6
A101: Voce | B101: Valore | C101: Unità | D101: Valore atteso (libro) | E101: Controllo | F101: Fonte nel libro
A102: Costi effettivi del centro | B102: 210000 | C102: euro | F102: capitolo 6
A103: Costi applicati ai prodotti | B103: 195000 | C103: euro | F103: capitolo 6
A104: Scostamento del centro | B104: =$B$102-$B$103 -> 15000 | C104: euro | D104: 15000 | E104: =IF(ABS(B104-D104)<=0.5,"OK","DIVERSO") -> OK | F104: capitolo 6
A106: Impresa guida - ribaltamento
A107: Manutenzione chiusa per prima a cascata; Lavorazione arriva ai 120.000 euro; capitolo 6
A108: Voce | B108: Valore | C108: Unità | D108: Valore atteso (libro) | E108: Controllo | F108: Fonte nel libro
A109: Manutenzione a Programmazione e qualità | B109: 0.25 | C109: % | F109: capitolo 6
...

Sheet Cap_07
A1: Capitolo 7 - Full Costing
A2: Controllo di gestione con l'intelligenza artificiale - file Excel che accompagna il libro
A3: Celle blu su fondo giallo: dati da cambiare. Celle nere: formule. «Valore atteso (libro)» e «Controllo» confrontano il calcolo con il numero stampato nel libro.
A4: Configurazioni progressive di costo e costo pieno complessivo delle tre linee dell'impresa guida, riconciliato con il risultato operativo.
A6: Configurazioni progressive
A7: Costo primo, industriale e complessivo per strati; capitolo 7
A8: Voce | B8: Valore | C8: Unità | D8: Valore atteso (libro) | E8: Controllo | F8: Fonte nel libro
A9: Materiali diretti | B9: 45 | C9: euro/unità | F9: capitolo 7
A10: Lavoro diretto | B10: 25 | C10: euro/unità | F10: capitolo 7
A11: Indiretti di produzione | B11: 18 | C11: euro/unità | F11: capitolo 7
A12: Commerciali e amministrativi | B12: 12 | C12: euro/unità | F12: capitolo 7
A13: Costo primo | B13: =$B$9+$B$10 -> 70 | C13: euro/unità | D13: 70 | E13: =IF(ABS(B13-D13)<=0.5,"OK","DIVERSO") -> OK | F13: capitolo 7
A14: Costo industriale | B14: =$B$13+$B$11 -> 88 | C14: euro/unità | D14: 88 | E14: =IF(ABS(B14-D14)<=0.5,"OK","DIVERSO") -> OK | F14: capitolo 7
A15: Costo complessivo | B15: =$B$14+$B$12 -> 100 | C15: euro/unità | D15: 100 | E15: =IF(ABS(B15-D15)<=0.5,"OK","DIVERSO") -> OK | F15: capitolo 7
A17: Redditività a costo pieno
A18: Due prodotti: costo pieno e margine pieno unitario; capitolo 7
A19: Voce | B19: Valore | C19: Unità | D19: Valore atteso (libro) | E19: Controllo | F19: Fonte nel libro
A20: Prodotto A - prezzo netto | B20: 140 | C20: euro/unità | F20: capitolo 7
A21: Prodotto A - costi diretti | B21: 65 | C21: euro/unità | F21: capitolo 7
A22: Prodotto A - indiretti allocati | B22: 35 | C22: euro/unità | F22: capitolo 7
A23: Prodotto A - costo pieno | B23: =$B$21+$B$22 -> 100 | C23: euro/unità | D23: 100 | E23: =IF(ABS(B23-D23)<=0.5,"OK","DIVERSO") -> OK | F23: capitolo 7
A24: Prodotto A - margine pieno | B24: =$B$20-$B$23 -> 40 | C24: euro/unità | D24: 40 | E24: =IF(ABS(B24-D24)<=0.5,"OK","DIVERSO") -> OK | F24: capitolo 7
A25: Prodotto B - prezzo netto | B25: 110 | C25: euro/unità | F25: capitolo 7
A26: Prodotto B - costi diretti | B26: 50 | C26: euro/unità | F26: capitolo 7
A27: Prodotto B - indiretti allocati | B27: 45 | C27: euro/unità | F27: capitolo 7
A28: Prodotto B - costo pieno | B28: =$B$26+$B$27 -> 95 | C28: euro/unità | D28: 95 | E28: =IF(ABS(B28-D28)<=0.5,"OK","DIVERSO") -> OK | F28: capitolo 7
A29: Prodotto B - margine pieno | B29: =$B$25-$B$28 -> 15 | C29: euro/unità | D29: 15 | E29: =IF(ABS(B29-D29)<=0.5,"OK","DIVERSO") -> OK | F29: capitolo 7
A31: Impresa guida - struttura da ripartire
A32: Struttura meno indiretti di produzione, ripartita in proporzione ai ricavi; capitolo 7
A33: Voce | B33: Valore | C33: Unità | D33: Valore atteso (libro) | E33: Controllo | F33: Fonte nel libro
A34: Struttura da ripartire (con la capacità esterna) | B34: =Impresa_guida!$B$41-Cap_06!$B$115 -> 700000 | C34: euro | D34: 700000 | E34: =IF(ABS(B34-D34)<=0.5,"OK","DIVERSO") -> OK | F34: capitolo 7
A35: Quota di struttura linea A | B35: =$B$34*Impresa_guida!$B$31/Impresa_guida!$B$34 -> 297696.4 | C35: euro | D35: 297696 | E35: =IF(ABS(B35-D35)<=0.5,"OK","DIVERSO") -> OK | F35: capitolo 7
A36: Quota di struttura linea B | B36: =$B$34*Impresa_guida!$B$32/Impresa_guida!$B$34 -> 282811.58 | C36: euro | D36: 282812 | E36: =IF(ABS(B36-D36)<=0.5,"OK","DIVERSO") -> OK | F36: capitolo 7
A37: Quota di struttura linea C | B37: =$B$34*Impresa_guida!$B$33/Impresa_guida!$B$34 -> 119492.03 | C37: euro | D37: 119492 | E37: =IF(ABS(B37-D37)<=0.5,"OK","DIVERSO") -> OK | F37: capitolo 7
A38: Totale quote di struttura | B38: =$B$35+$B$36+$B$37 -> 700000 | C38: euro | D38: 700000 | E38: =IF(ABS(B38-D38)<=0.5,"OK","DIVERSO") -> OK | F38: capitolo 7
A40: Impresa guida - costo pieno per unità
A41: Strati per unità: costo variabile, indiretti sulle ore, quota di struttura; capitolo 7
A42: Voce | B42: Valore | C42: Unità | D42: Valore atteso (libro) | E42: Controllo | F42: Fonte nel libro
A43: Linea A - indiretti di produzione | B43: =Cap_06!$B$131 -> 7.5 | C43: euro/unità | D43: 7.5 | E43: =IF(ABS(B43-D43)<=0.005,"OK","DIVERSO") -> OK | F43: capitolo 7
A44: Linea A - costo industriale | B44: =Impresa_guida!$B$10+$B$43 -> 124.5 | C44: euro/unità | D44: 124.5 | E44: =IF(ABS(B44-D44)<=0.005,"OK","DIVERSO") -> OK | F44: capitolo 7
A45: Linea A - quota di struttura | B45: =$B$35/Impresa_guida!$B$8 -> 37.21205 | C45: euro/unità | D45: 37.21 | E45: =IF(ABS(B45-D45)<=0.005,"OK","DIVERSO") -> OK | F45: capitolo 7
A46: Linea A - costo pieno complessivo | B46: =$B$44+$B$45 -> 161.71205 | C46: euro/unità | D46: 161.71 | E46: =IF(ABS(B46-D46)<=0.005,"OK","DIVERSO") -> OK | F46: capitolo 7
A47: Linea A - risultato pieno per unità | B47: =Impresa_guida!$B$9-$B$46 -> 18.28795 | C47: euro/unità | D47: 18.29 | E47: =IF(ABS(B47-D47)<=0.005,"OK","DIVERSO") -> OK | F47: capitolo 7
A48: Linea B - indiretti di produzione | B48: =Cap_06!$B$136 -> 2.5 | C48: euro/unità | D48: 2.5 | E48: =IF(ABS(B48-D48)<=0.005,"OK","DIVERSO") -> OK | F48: capitolo 7
A49: Linea B - costo industriale | B49: =Impresa_guida!$B$14+$B$48 -> 78.5 | C49: euro/unità | D49: 78.5 | E49: =IF(ABS(B49-D49)<=0.005,"OK","DIVERSO") -> OK | F49: capitolo 7
A50: Linea B - quota di struttura | B50: =$B$36/Impresa_guida!$B$12 -> 23.567631 | C50: euro/unità | D50: 23.57 | E50: =IF(ABS(B50-D50)<=0.005,"OK","DIVERSO") -> OK | F50: capitolo 7
A51: Linea B - costo pieno complessivo | B51: =$B$49+$B$50 -> 102.06763 | C51: euro/unità | D51: 102.07 | E51: =IF(ABS(B51-D51)<=0.005,"OK","DIVERSO") -> OK | F51: capitolo 7
A52: Linea B - risultato pieno per unità | B52: =Impresa_guida!$B$13-$B$51 -> 11.932369 | C52: euro/unità | D52: 11.93 | E52: =IF(ABS(B52-D52)<=0.005,"OK","DIVERSO") -> OK | F52: capitolo 7
A53: Linea C - indiretti di produzione | B53: =Cap_06!$B$141 -> 15 | C53: euro/unità | D53: 15 | E53: =IF(ABS(B53-D53)<=0.005,"OK","DIVERSO") -> OK | F53: capitolo 7
A54: Linea C - costo industriale | B54: =Impresa_guida!$B$18+$B$53 -> 253 | C54: euro/unità | D54: 253 | E54: =IF(ABS(B54-D54)<=0.005,"OK","DIVERSO") -> OK | F54: capitolo 7
A55: Linea C - quota di struttura | B55: =$B$37/Impresa_guida!$B$16 -> 59.746013 | C55: euro/unità | D55: 59.75 | E55: =IF(ABS(B55-D55)<=0.005,"OK","DIVERSO") -> OK | F55: capitolo 7
A56: Linea C - costo pieno complessivo | B56: =$B$54+$B$55 -> 312.74601 | C56: euro/unità | D56: 312.75 | E56: =IF(ABS(B56-D56)<=0.005,"OK","DIVERSO") -> OK | F56: capitolo 7
A57: Linea C - risultato pieno per unità | B57: =Impresa_guida!$B$17-$B$56 -> -23.746013 | C57: euro/unità | D57: -23.75 | E57: =IF(ABS(B57-D57)<=0.005,"OK","DIVERSO") -> OK | F57: capitolo 7
A59: Impresa guida - risultati a costo pieno
A60: Risultati per linea sui valori non arrotondati e riconciliazione con il risultato operativo; capitolo 7
A61: Voce | B61: Valore | C61: Unità | D61: Valore atteso (libro) | E61: Controllo | F61: Fonte nel libro
A62: Risultato a costo pieno linea A | B62: =Impresa_guida!$B$31-Impresa_guida!$B$8*$B$44-$B$35 -> 146303.6 | C62: euro | D62: 146304 | E62: =IF(ABS(B62-D62)<=0.5,"OK","DIVERSO") -> OK | F62: capitolo 7
A63: Risultato a costo pieno linea B | B63: =Impresa_guida!$B$32-Impresa_guida!$B$12*$B$49-$B$36 -> 143188.42 | C63: euro | D63: 143188 | E63: =IF(ABS(B63-D63)<=0.5,"OK","DIVERSO") -> OK | F63: capitolo 7
A64: Risultato a costo pieno linea C | B64: =Impresa_guida!$B$33-Impresa_guida!$B$16*$B$54-$B$37 -> -47492.026 | C64: euro | D64: -47492 | E64: =IF(ABS(B64-D64)<=0.5,"OK","DIVERSO") -> OK | F64: capitolo 7
A65: Somma dei risultati | B65: =$B$62+$B$63+$B$64 -> 242000 | C65: euro | D65: 242000 | E65: =IF(ABS(B65-D65)<=0.5,"OK","DIVERSO") -> OK | F65: capitolo 7
A66: Controllo con il risultato operativo | B66: =$B$65-Impresa_guida!$B$42 -> 0 | C66: euro | D66: 0 | E66: =IF(ABS(B66-D66)<=0.5,"OK","DIVERSO") -> OK | F66: capitolo 7
A67: Linea C - prezzo netto meno costo industriale | B67: =Impresa_guida!$B$17-$B$54 -> 36 | C67: euro/unità | D67: 36 | E67: =IF(ABS(B67-D67)<=0.005,"OK","DIVERSO") -> OK | F67: capitolo 7
A69: Impresa guida - costo pieno e costo evitabile
A70: Costi allocati a C che non scompaiono con la linea e risultato senza C nelle due ipotesi; capitolo 7
A71: Voce | B71: Valore | C71: Unità | D71: Valore atteso (libro) | E71: Controllo | F71: Fonte nel libro
A72: Costi allocati alla linea C | B72: =Cap_06!$B$140+$B$37 -> 149492.03 | C72: euro | D72: 149492 | E72: =IF(ABS(B72-D72)<=0.5,"OK","DIVERSO") -> OK | F72: capitolo 7
A73: Risultato senza C, se tutta la struttura resta | B73: =Impresa_guida!$B$42-(Impresa_guida!$B$33-Impresa_guida!$B$16*Impresa_guida!$B$18) -> 140000 | C73: euro | D73: 140000 | E73: =IF(ABS(B73-D73)<=0.5,"OK","DIVERSO") -> OK | F73: capitolo 7
A74: Ore macchina senza C | B74: =Cap_06!$B$129+Cap_06!$B$134 -> 18000 | C74: ore | F74: capitolo 7
A75: Capacità esterna senza C | B75: =MAX($B$74-Impresa_guida!$B$26,0)*Impresa_guida!$B$27 -> 0 | C75: euro | D75: 0 | E75: =IF(ABS(B75-D75)<=0.5,"OK","DIVERSO") -> OK | F75: capitolo 7
A76: Risultato senza C, ipotesi più favorevole | B76: =$B$73+Impresa_guida!$B$39-$B$75 -> 224000 | C76: euro | D76: 224000 | E76: =IF(ABS(B76-D76)<=0.5,"OK","DIVERSO") -> OK | F76: capitolo 7

Sheet Cap_08
A1: Capitolo 8 - Direct Costing e margine di contribuzione
A2: Controllo di gestione con l'intelligenza artificiale - file Excel che accompagna il libro
A3: Celle blu su fondo giallo: dati da cambiare. Celle nere: formule. «Valore atteso (libro)» e «Controllo» confrontano il calcolo con il numero stampato nel libro.
A4: Margine di contribuzione unitario, totale e percentuale, secondo margine e prospetto a margine dell'impresa guida per linea e per canale.
A6: Margine unitario e percentuale
A7: Tre prodotti: margine = prezzo - costo variabile e margine percentuale; capitolo 8
A8: Voce | B8: Valore | C8: Unità | D8: Valore atteso (libro) | E8: Controllo | F8: Fonte nel libro
A9: Prodotto A - prezzo | B9: 100 | C9: euro/unità | F9: capitolo 8
A10: Prodotto A - costo variabile | B10: 60 | C10: euro/unità | F10: capitolo 8
A11: Prodotto A - margine | B11: =$B$9-$B$10 -> 40 | C11: euro/unità | D11: 40 | E11: =IF(ABS(B11-D11)<=0.5,"OK","DIVERSO") -> OK | F11: capitolo 8
A12: Prodotto A - margine percentuale | B12: =$B$11/$B$9 -> 0.4 | C12: % | D12: 0.4 | E12: =IF(ABS(B12-D12)<=0.0005,"OK","DIVERSO") -> OK | F12: capitolo 8
A13: Prodotto B - prezzo | B13: 70 | C13: euro/unità | F13: capitolo 8
A14: Prodotto B - costo variabile | B14: 35 | C14: euro/unità | F14: capitolo 8
A15: Prodotto B - margine | B15: =$B$13-$B$14 -> 35 | C15: euro/unità | D15: 35 | E15: =IF(ABS(B15-D15)<=0.5,"OK","DIVERSO") -> OK | F15: capitolo 8
A16: Prodotto B - margine percentuale | B16: =$B$15/$B$13 -> 0.5 | C16: % | D16: 0.5 | E16: =IF(ABS(B16-D16)<=0.0005,"OK","DIVERSO") -> OK | F16: capitolo 8
A17: Prodotto C - prezzo | B17: 150 | C17: euro/unità | F17: capitolo 8
A18: Prodotto C - costo variabile | B18: 105 | C18: euro/unità | F18: capitolo 8
A19: Prodotto C - margine | B19: =$B$17-$B$18 -> 45 | C19: euro/unità | D19: 45 | E19: =IF(ABS(B19-D19)<=0.5,"OK","DIVERSO") -> OK | F19: capitolo 8
A20: Prodotto C - margine percentuale | B20: =$B$19/$B$17 -> 0.3 | C20: % | D20: 0.3 | E20: =IF(ABS(B20-D20)<=0.0005,"OK","DIVERSO") -> OK | F20: capitolo 8
A22: Conto Economico a margine
A23: Primo margine, secondo margine e risultato operativo; capitolo 8
A24: Voce | B24: Valore | C24: Unità | D24: Valore atteso (libro) | E24: Controllo | F24: Fonte nel libro
A25: Ricavi | B25: 500000 | C25: euro | F25: capitolo 8
A26: Costi variabili | B26: 300000 | C26: euro | F26: capitolo 8
A27: Costi fissi specifici | B27: 70000 | C27: euro | F27: capitolo 8
A28: Costi fissi comuni | B28: 90000 | C28: euro | F28: capitolo 8
A29: Margine di contribuzione | B29: =$B$25-$B$26 -> 200000 | C29: euro | D29: 200000 | E29: =IF(ABS(B29-D29)<=0.5,"OK","DIVERSO") -> OK | F29: capitolo 8
A30: Secondo margine | B30: =$B$29-$B$27 -> 130000 | C30: euro | D30: 130000 | E30: =IF(ABS(B30-D30)<=0.5,"OK","DIVERSO") -> OK | F30: capitolo 8
A31: Risultato operativo | B31: =$B$30-$B$28 -> 40000 | C31: euro | D31: 40000 | E31: =IF(ABS(B31-D31)<=0.5,"OK","DIVERSO") -> OK | F31: capitolo 8
A33: Margini per cliente
A34: Cliente Z: margine di prodotto, dopo i costi di servizio e secondo margine; capitolo 8
A35: Voce | B35: Valore | C35: Unità | D35: Valore atteso (libro) | E35: Controllo | F35: Fonte nel libro
A36: Ricavi netti | B36: 250000 | C36: euro | F36: capitolo 8
A37: Costi variabili prodotto | B37: 145000 | C37: euro | F37: capitolo 8
A38: Logistica, gestione dei resi e assistenza | B38: 32000 | C38: euro | F38: capitolo 8
A39: Costi fissi specifici | B39: 18000 | C39: euro | F39: capitolo 8
A40: Margine di prodotto | B40: =$B$36-$B$37 -> 105000 | C40: euro | D40: 105000 | E40: =IF(ABS(B40-D40)<=0.5,"OK","DIVERSO") -> OK | F40: capitolo 8
A41: Margine dopo i costi variabili di servizio | B41: =$B$40-$B$38 -> 73000 | C41: euro | D41: 73000 | E41: =IF(ABS(B41-D41)<=0.5,"OK","DIVERSO") -> OK | F41: capitolo 8
A42: Secondo margine | B42: =$B$41-$B$39 -> 55000 | C42: euro | D42: 55000 | E42: =IF(ABS(B42-D42)<=0.5,"OK","DIVERSO") -> OK | F42: capitolo 8
A44: Impresa guida - prospetto a margine
A45: Ricavi, costi variabili, margine, struttura e risultato con le incidenze sui ricavi; capitolo 8
A46: Voce | B46: Valore | C46: Unità | D46: Valore atteso (libro) | E46: Controllo | F46: Fonte nel libro
A47: Ricavi | B47: =Impresa_guida!$B$34 -> 3386000 | C47: euro | D47: 3386000 | E47: =IF(ABS(B47-D47)<=0.5,"OK","DIVERSO") -> OK | F47: capitolo 8
A48: Costi variabili | B48: =Impresa_guida!$B$35 -> 2324000 | C48: euro | D48: 2324000 | E48: =IF(ABS(B48-D48)<=0.5,"OK","DIVERSO") -> OK | F48: capitolo 8
A49: Margine di contribuzione | B49: =$B$47-$B$48 -> 1062000 | C49: euro | D49: 1062000 | E49: =IF(ABS(B49-D49)<=0.5,"OK","DIVERSO") -> OK | F49: capitolo 8
A50: Costi della struttura | B50: =Impresa_guida!$B$41 -> 820000 | C50: euro | D50: 820000 | E50: =IF(ABS(B50-D50)<=0.5,"OK","DIVERSO") -> OK | F50: capitolo 8
A51: di cui capacità aggiuntiva | B51: =Impresa_guida!$B$39 -> 84000 | C51: euro | D51: 84000 | E51: =IF(ABS(B51-D51)<=0.5,"OK","DIVERSO") -> OK | F51: capitolo 8
A52: Risultato operativo | B52: =$B$49-$B$50 -> 242000 | C52: euro | D52: 242000 | E52: =IF(ABS(B52-D52)<=0.5,"OK","DIVERSO") -> OK | F52: capitolo 8
A53: Margine di contribuzione su ricavi | B53: =$B$49/$B$47 -> 0.31364442 | C53: % | D53: 0.314 | E53: =IF(ABS(B53-D53)<=0.0005,"OK","DIVERSO") -> OK | F53: capitolo 8
A54: Costi variabili su ricavi | B54: =$B$48/$B$47 -> 0.68635558 | C54: % | D54: 0.686 | E54: =IF(ABS(B54-D54)<=0.0005,"OK","DIVERSO") -> OK | F54: capitolo 8
A55: Struttura su ricavi | B55: =$B$50/$B$47 -> 0.24217366 | C55: % | D55: 0.242 | E55: =IF(ABS(B55-D55)<=0.0005,"OK","DIVERSO") -> OK | F55: capitolo 8
A56: Risultato operativo su ricavi | B56: =$B$52/$B$47 -> 0.071470762 | C56: % | D56: 0.071 | E56: =IF(ABS(B56-D56)<=0.0005,"OK","DIVERSO") -> OK | F56: capitolo 8
A57: Somma delle incidenze arrotondate | B57: =ROUND($B$54,3)+ROUND($B$55,3)+ROUND($B$56,3) -> 0.999 | C57: % | D57: 0.999 | E57: =IF(ABS(B57-D57)<=0.0005,"OK","DIVERSO") -> OK | F57: capitolo 8
A59: Impresa guida - primo margine per linea
A60: Ricavi, costi variabili, margine totale, percentuale e unitario per linea; capitolo 8
A61: Voce | B61: Valore | C61: Unità | D61: Valore atteso (libro) | E61: Controllo | F61: Fonte nel libro
A62: Ricavi linea A | B62: =Impresa_guida!$B$31 -> 1440000 | C62: euro | D62: 1440000 | E62: =IF(ABS(B62-D62)<=0.5,"OK","DIVERSO") -> OK | F62: capitolo 8
A63: Ricavi linea B | B63: =Impresa_guida!$B$32 -> 1368000 | C63: euro | D63: 1368000 | E63: =IF(ABS(B63-D63)<=0.5,"OK","DIVERSO") -> OK | F63: capitolo 8
A64: Ricavi linea C | B64: =Impresa_guida!$B$33 -> 578000 | C64: euro | D64: 578000 | E64: =IF(ABS(B64-D64)<=0.5,"OK","DIVERSO") -> OK | F64: capitolo 8
A65: Costi variabili linea A | B65: =Impresa_guida!$B$8*Impresa_guida!$B$10 -> 936000 | C65: euro | D65: 936000 | E65: =IF(ABS(B65-D65)<=0.5,"OK","DIVERSO") -> OK | F65: capitolo 8
A66: Costi variabili linea B | B66: =Impresa_guida!$B$12*Impresa_guida!$B$14 -> 912000 | C66: euro | D66: 912000 | E66: =IF(ABS(B66-D66)<=0.5,"OK","DIVERSO") -> OK | F66: capitolo 8
A67: Costi variabili linea C | B67: =Impresa_guida!$B$16*Impresa_guida!$B$18 -> 476000 | C67: euro | D67: 476000 | E67: =IF(ABS(B67-D67)<=0.5,"OK","DIVERSO") -> OK | F67: capitolo 8
A68: Costi variabili totali | B68: =$B$65+$B$66+$B$67 -> 2324000 | C68: euro | D68: 2324000 | E68: =IF(ABS(B68-D68)<=0.5,"OK","DIVERSO") -> OK | F68: capitolo 8
A69: Margine linea A | B69: =$B$62-$B$65 -> 504000 | C69: euro | D69: 504000 | E69: =IF(ABS(B69-D69)<=0.5,"OK","DIVERSO") -> OK | F69: capitolo 8
A70: Margine linea B | B70: =$B$63-$B$66 -> 456000 | C70: euro | D70: 456000 | E70: =IF(ABS(B70-D70)<=0.5,"OK","DIVERSO") -> OK | F70: capitolo 8
A71: Margine linea C | B71: =$B$64-$B$67 -> 102000 | C71: euro | D71: 102000 | E71: =IF(ABS(B71-D71)<=0.5,"OK","DIVERSO") -> OK | F71: capitolo 8
A72: Margine totale | B72: =$B$69+$B$70+$B$71 -> 1062000 | C72: euro | D72: 1062000 | E72: =IF(ABS(B72-D72)<=0.5,"OK","DIVERSO") -> OK | F72: capitolo 8
A73: Margine percentuale linea A | B73: =$B$69/$B$62 -> 0.35 | C73: % | D73: 0.35 | E73: =IF(ABS(B73-D73)<=0.0005,"OK","DIVERSO") -> OK | F73: capitolo 8
A74: Margine percentuale linea B | B74: =$B$70/$B$63 -> 0.33333333 | C74: % | D74: 0.333 | E74: =IF(ABS(B74-D74)<=0.0005,"OK","DIVERSO") -> OK | F74: capitolo 8
A75: Margine percentuale linea C | B75: =$B$71/$B$64 -> 0.17647059 | C75: % | D75: 0.176 | E75: =IF(ABS(B75-D75)<=0.0005,"OK","DIVERSO") -> OK | F75: capitolo 8
A76: Margine percentuale totale | B76: =$B$72/Impresa_guida!$B$34 -> 0.31364442 | C76: % | D76: 0.314 | E76: =IF(ABS(B76-D76)<=0.0005,"OK","DIVERSO") -> OK | F76: capitolo 8
A77: Margine unitario linea A | B77: =Impresa_guida!$B$9-Impresa_guida!$B$10 -> 63 | C77: euro/unità | D77: 63 | E77: =IF(ABS(B77-D77)<=0.5,"OK","DIVERSO") -> OK | F77: capitolo 8
A78: Margine unitario linea B | B78: =Impresa_guida!$B$13-Impresa_guida!$B$14 -> 38 | C78: euro/unità | D78: 38 | E78: =IF(ABS(B78-D78)<=0.5,"OK","DIVERSO") -> OK | F78: capitolo 8
A79: Margine unitario linea C | B79: =Impresa_guida!$B$17-Impresa_guida!$B$18 -> 51 | C79: euro/unità | D79: 51 | E79: =IF(ABS(B79-D79)<=0.5,"OK","DIVERSO") -> OK | F79: capitolo 8
A80: Margine unitario più alto fra B e C | B80: =IF($B$79>$B$78,"Linea C","Linea B") -> Linea C | D80: Linea C | E80: =IF(B80=D80,"OK","DIVERSO") -> OK | F80: capitolo 8
A81: Margine totale più alto fra B e C | B81: =IF($B$70>$B$71,"Linea B","Linea C") -> Linea B | D81: Linea B | E81: =IF(B81=D81,"OK","DIVERSO") -> OK | F81: capitolo 8
A83: Impresa guida - primo margine per canale
A84: Margine e percentuale per canale, riconciliati con margine e risultato operativo; capitolo 8
A85: Voce | B85: Valore | C85: Unità | D85: Valore atteso (libro) | E85: Controllo | F85: Fonte nel libro
A86: Canale diretto - margine | B86: 459000 | C86: euro | F86: capitolo 8
A87: Distributori - margine | B87: 603000 | C87: euro | F87: capitolo 8
A88: Canale diretto - margine percentuale | B88: =$B$86/Cap_05!$B$12 -> 0.37622951 | C88: % | D88: 0.376 | E88: =IF(ABS(B88-D88)<=0.0005,"OK","DIVERSO") -> OK | F88: capitolo 8
A89: Distributori - margine percentuale | B89: =$B$87/Cap_05!$B$13 -> 0.27839335 | C89: % | D89: 0.278 | E89: =IF(ABS(B89-D89)<=0.0005,"OK","DIVERSO") -> OK | F89: capitolo 8
A90: Somma dei margini dei canali | B90: =$B$86+$B$87 -> 1062000 | C90: euro | D90: 1062000 | E90: =IF(ABS(B90-D90)<=0.5,"OK","DIVERSO") -> OK | F90: capitolo 8
A91: Controllo con il margine per linea | B91: =$B$90-$B$72 -> 0 | C91: euro | D91: 0 | E91: =IF(ABS(B91-D91)<=0.5,"OK","DIVERSO") -> OK | F91: capitolo 8
A92: Risultato operativo dai canali | B92: =$B$90-Impresa_guida!$B$41 -> 242000 | C92: euro | D92: 242000 | E92: =IF(ABS(B92-D92)<=0.5,"OK","DIVERSO") -> OK | F92: capitolo 8
A94: Canale diretto con il mix dell'impresa
A95: Margine percentuale ai prezzi di listino con le quantità dell'impresa; capitolo 8
A96: Voce | B96: Valore | C96: Unità | D96: Valore atteso (libro) | E96: Controllo | F96: Fonte nel libro
A97: Listino linea A | B97: 200 | C97: euro/unità | F97: capitolo 8
A98: Listino linea B | B98: 120 | C98: euro/unità | F98: capitolo 8
A99: Listino linea C | B99: 305 | C99: euro/unità | F99: capitolo 8
A100: Ricavi a listino con il mix dell'impresa | B100: =Impresa_guida!$B$8*$B$97+Impresa_guida!$B$12*$B$98+Impresa_guida!$B$16*$B$99 -> 3650000 | C100: euro | F100: capitolo 8
A101: Margine a listino con il mix dell'impresa | B101: =$B$100-Impresa_guida!$B$35 -> 1326000 | C101: euro | F101: capitolo 8
A102: Margine percentuale a listino | B102: =$B$101/$B$100 -> 0.36328767 | C102: % | D102: 0.363 | E102: =IF(ABS(B102-D102)<=0.0005,"OK","DIVERSO") -> OK | F102: capitolo 8

Sheet Cap_09
A1: Capitolo 9 - Break-even e analisi costo-volume-risultato
A2: Controllo di gestione con l'intelligenza artificiale - file Excel che accompagna il libro
A3: Celle blu su fondo giallo: dati da cambiare. Celle nere: formule. «Valore atteso (libro)» e «Controllo» confrontano il calcolo con il numero stampato nel libro.
A4: Pareggio in unità e fatturato, utile obiettivo, margine di sicurezza, leva operativa, mix e sensibilità, poi il pareggio a tratti dell'impresa guida.
A6: Pareggio in unità - esempio base
A7: Pareggio con prezzo 100, costo variabile 60 e costi fissi 200.000, con la verifica al pareggio; capitolo 9
A8: Voce | B8: Valore | C8: Unità | D8: Valore atteso (libro) | E8: Controllo | F8: Fonte nel libro
A9: Prezzo unitario | B9: 100 | C9: euro/unità | F9: capitolo 9
A10: Costo variabile unitario | B10: 60 | C10: euro/unità | F10: capitolo 9
A11: Costi fissi | B11: 200000 | C11: euro | F11: capitolo 9
A12: Margine di contribuzione unitario | B12: =$B$9-$B$10 -> 40 | C12: euro/unità | D12: 40 | E12: =IF(ABS(B12-D12)<=0.5,"OK","DIVERSO") -> OK | F12: capitolo 9
A13: Pareggio in unità | B13: =ROUNDUP($B$11/$B$12,0) -> 5000 | C13: unità | D13: 5000 | E13: =IF(ABS(B13-D13)<=0.5,"OK","DIVERSO") -> OK | F13: capitolo 9
A14: Ricavi al pareggio | B14: =$B$13*$B$9 -> 500000 | C14: euro | D14: 500000 | E14: =IF(ABS(B14-D14)<=0.5,"OK","DIVERSO") -> OK | F14: capitolo 9
A15: Costi variabili al pareggio | B15: =$B$13*$B$10 -> 300000 | C15: euro | D15: 300000 | E15: =IF(ABS(B15-D15)<=0.5,"OK","DIVERSO") -> OK | F15: capitolo 9
A16: Margine al pareggio | B16: =$B$13*$B$12 -> 200000 | C16: euro | D16: 200000 | E16: =IF(ABS(B16-D16)<=0.5,"OK","DIVERSO") -> OK | F16: capitolo 9
A17: Risultato al pareggio | B17: =$B$16-$B$11 -> 0 | C17: euro | D17: 0 | E17: =IF(ABS(B17-D17)<=0.5,"OK","DIVERSO") -> OK | F17: capitolo 9
A19: Arrotondamento per eccesso
A20: Con margine 35 la divisione non è intera: a 5.714 unità si è ancora in perdita, il pareggio è 5.715; capitolo 9
A21: Voce | B21: Valore | C21: Unità | D21: Valore atteso (libro) | E21: Controllo | F21: Fonte nel libro
A22: Margine unitario dell'esempio | B22: 35 | C22: euro/unità | F22: capitolo 9
A23: Costi fissi / margine (non arrotondato) | B23: =$B$11/$B$22 -> 5714.2857 | C23: unità | D23: 5714.3 | E23: =IF(ABS(B23-D23)<=0.05,"OK","DIVERSO") -> OK | F23: capitolo 9
A24: Unità arrotondate per difetto | B24: =ROUNDDOWN($B$23,0) -> 5714 | C24: unità | D24: 5714 | E24: =IF(ABS(B24-D24)<=0.5,"OK","DIVERSO") -> OK | F24: capitolo 9
A25: Margine totale a 5.714 unità | B25: =$B$24*$B$22 -> 199990 | C25: euro | D25: 199990 | E25: =IF(ABS(B25-D25)<=0.5,"OK","DIVERSO") -> OK | F25: capitolo 9
A26: Risultato a 5.714 unità | B26: =$B$25-$B$11 -> -10 | C26: euro | D26: -10 | E26: =IF(ABS(B26-D26)<=0.5,"OK","DIVERSO") -> OK | F26: capitolo 9
A27: Pareggio in unità (per eccesso) | B27: =ROUNDUP($B$23,0) -> 5715 | C27: unità | D27: 5715 | E27: =IF(ABS(B27-D27)<=0.5,"OK","DIVERSO") -> OK | F27: capitolo 9
A28: Risultato a 5.715 unità | B28: =$B$27*$B$22-$B$11 -> 25 | C28: euro | D28: 25 | E28: =IF(ABS(B28-D28)<=0.5,"OK","DIVERSO") -> OK | F28: capitolo 9
A30: Pareggio in fatturato
A31: Pareggio espresso in fatturato con il margine percentuale; capitolo 9
A32: Voce | B32: Valore | C32: Unità | D32: Valore atteso (libro) | E32: Controllo | F32: Fonte nel libro
A33: Margine percentuale | B33: =$B$12/$B$9 -> 0.4 | C33: % | D33: 0.4 | E33: =IF(ABS(B33-D33)<=0.0005,"OK","DIVERSO") -> OK | F33: capitolo 9
A34: Fatturato di pareggio | B34: =$B$11/$B$33 -> 500000 | C34: euro | D34: 500000 | E34: =IF(ABS(B34-D34)<=0.5,"OK","DIVERSO") -> OK | F34: capitolo 9
A36: Utile obiettivo
A37: Volume per un utile obiettivo, anche partendo da un utile netto dopo imposte; capitolo 9
A38: Voce | B38: Valore | C38: Unità | D38: Valore atteso (libro) | E38: Controllo | F38: Fonte nel libro
A39: Utile obiettivo (risultato operativo) | B39: 80000 | C39: euro | F39: capitolo 9
A40: Volume per utile obiettivo | B40: =ROUNDUP(($B$11+$B$39)/$B$12,0) -> 7000 | C40: unità | D40: 7000 | E40: =IF(ABS(B40-D40)<=0.5,"OK","DIVERSO") -> OK | F40: capitolo 9
A41: Utile netto desiderato | B41: 56000 | C41: euro | F41: capitolo 9
A42: Aliquota prevista | B42: 0.3 | C42: % | F42: capitolo 9
A43: Oneri finanziari | B43: 0 | C43: euro | F43: capitolo 9
A44: Risultato operativo necessario | B44: =$B$41/(1-$B$42)+$B$43 -> 80000 | C44: euro | D44: 80000 | E44: =IF(ABS(B44-D44)<=0.5,"OK","DIVERSO") -> OK | F44: capitolo 9
A45: Volume per l'utile netto | B45: =ROUNDUP(($B$11+$B$44)/$B$12,0) -> 7000 | C45: unità | D45: 7000 | E45: =IF(ABS(B45-D45)<=0.5,"OK","DIVERSO") -> OK | F45: capitolo 9
A47: Margine di sicurezza
A48: Quanto possono calare le vendite prima del pareggio; capitolo 9
A49: Voce | B49: Valore | C49: Unità | D49: Valore atteso (libro) | E49: Controllo | F49: Fonte nel libro
A50: Vendite previste | B50: 650000 | C50: euro | F50: capitolo 9
A51: Margine di sicurezza | B51: =$B$50-$B$34 -> 150000 | C51: euro | D51: 150000 | E51: =IF(ABS(B51-D51)<=0.5,"OK","DIVERSO") -> OK | F51: capitolo 9
A52: Margine di sicurezza percentuale | B52: =$B$51/$B$50 -> 0.23076923 | C52: % | D52: 0.231 | E52: =IF(ABS(B52-D52)<=0.0005,"OK","DIVERSO") -> OK | F52: capitolo 9
A54: Leva operativa
A55: Grado di leva operativa, anche sull'esempio del pareggio a 6.500 unità; capitolo 9
A56: Voce | B56: Valore | C56: Unità | D56: Valore atteso (libro) | E56: Controllo | F56: Fonte nel libro
A57: Margine di contribuzione (esempio) | B57: 240000 | C57: euro | F57: capitolo 9
A58: Risultato operativo (esempio) | B58: 40000 | C58: euro | F58: capitolo 9
A59: Grado di leva operativa | B59: =$B$57/$B$58 -> 6 | C59: volte | D59: 6 | E59: =IF(ABS(B59-D59)<=0.5,"OK","DIVERSO") -> OK | F59: capitolo 9
A60: Unità alle vendite previste | B60: =$B$50/$B$9 -> 6500 | C60: unità | D60: 6500 | E60: =IF(ABS(B60-D60)<=0.5,"OK","DIVERSO") -> OK | F60: capitolo 9
A61: Margine alle vendite previste | B61: =$B$60*$B$12 -> 260000 | C61: euro | D61: 260000 | E61: =IF(ABS(B61-D61)<=0.5,"OK","DIVERSO") -> OK | F61: capitolo 9
A62: Risultato alle vendite previste | B62: =$B$61-$B$11 -> 60000 | C62: euro | D62: 60000 | E62: =IF(ABS(B62-D62)<=0.5,"OK","DIVERSO") -> OK | F62: capitolo 9
A63: Grado di leva a 6.500 unità | B63: =$B$61/$B$62 -> 4.3333333 | C63: volte | D63: 4.33 | E63: =IF(ABS(B63-D63)<=0.005,"OK","DIVERSO") -> OK | F63: capitolo 9
A64: Inverso del margine di sicurezza % | B64: =1/$B$52 -> 4.3333333 | C64: volte | D64: 4.33 | E64: =IF(ABS(B64-D64)<=0.005,"OK","DIVERSO") -> OK | F64: capitolo 9
A66: Mix di vendita
A67: Pareggio multiprodotto con un pacchetto di 2 A e 1 B; capitolo 9
A68: Voce | B68: Valore | C68: Unità | D68: Valore atteso (libro) | E68: Controllo | F68: Fonte nel libro
A69: Margine unitario A | B69: 40 | C69: euro/unità | F69: capitolo 9
A70: Margine unitario B | B70: 20 | C70: euro/unità | F70: capitolo 9
A71: Unità di A nel pacchetto | B71: 2 | C71: unità/pacchetto | F71: capitolo 9
A72: Unità di B nel pacchetto | B72: 1 | C72: unità/pacchetto | F72: capitolo 9
A73: Margine del mix - A | B73: =$B$69*$B$71 -> 80 | C73: euro/pacchetto | D73: 80 | E73: =IF(ABS(B73-D73)<=0.5,"OK","DIVERSO") -> OK | F73: capitolo 9
A74: Margine del mix - B | B74: =$B$70*$B$72 -> 20 | C74: euro/pacchetto | D74: 20 | E74: =IF(ABS(B74-D74)<=0.5,"OK","DIVERSO") -> OK | F74: capitolo 9
A75: Margine del pacchetto | B75: =$B$73+$B$74 -> 100 | C75: euro/pacchetto | D75: 100 | E75: =IF(ABS(B75-D75)<=0.5,"OK","DIVERSO") -> OK | F75: capitolo 9
A76: Costi fissi | B76: 300000 | C76: euro | F76: capitolo 9
A77: Pacchetti di pareggio | B77: =ROUNDUP($B$76/$B$75,0) -> 3000 | C77: pacchetti | D77: 3000 | E77: =IF(ABS(B77-D77)<=0.5,"OK","DIVERSO") -> OK | F77: capitolo 9
A78: Unità di A al pareggio | B78: =$B$77*$B$71 -> 6000 | C78: unità | D78: 6000 | E78: =IF(ABS(B78-D78)<=0.5,"OK","DIVERSO") -> OK | F78: capitolo 9
A79: Unità di B al pareggio | B79: =$B$77*$B$72 -> 3000 | C79: unità | D79: 3000 | E79: =IF(ABS(B79-D79)<=0.5,"OK","DIVERSO") -> OK | F79: capitolo 9
A81: Sensibilità del pareggio
A82: Come si sposta il pareggio se cambiano costo variabile, prezzo o costi fissi; capitolo 9
A83: Voce | B83: Valore | C83: Unità | D83: Valore atteso (libro) | E83: Controllo | F83: Fonte nel libro
A84: Aumento del costo variabile | B84: 5 | C84: euro/unità | F84: capitolo 9
A85: Aumento del prezzo | B85: 5 | C85: euro/unità | F85: capitolo 9
A86: Aumento dei costi fissi | B86: 30000 | C86: euro | F86: capitolo 9
A87: Margine con costo variabile + 5 | B87: =$B$9-($B$10+$B$84) -> 35 | C87: euro/unità | D87: 35 | E87: =IF(ABS(B87-D87)<=0.5,"OK","DIVERSO") -> OK | F87: capitolo 9
A88: Pareggio con costo variabile + 5 | B88: =ROUNDUP($B$11/$B$87,0) -> 5715 | C88: unità | D88: 5715 | E88: =IF(ABS(B88-D88)<=0.5,"OK","DIVERSO") -> OK | F88: capitolo 9
A89: Margine con prezzo + 5 | B89: =($B$9+$B$85)-$B$10 -> 45 | C89: euro/unità | D89: 45 | E89: =IF(ABS(B89-D89)<=0.5,"OK","DIVERSO") -> OK | F89: capitolo 9
A90: Pareggio con prezzo + 5 (non arrotondato) | B90: =$B$11/$B$89 -> 4444.4444 | C90: unità | D90: 4444.4 | E90: =IF(ABS(B90-D90)<=0.05,"OK","DIVERSO") -> OK | F90: capitolo 9
A91: Pareggio con prezzo + 5 | B91: =ROUNDUP($B$90,0) -> 4445 | C91: unità | D91: 4445 | E91: =IF(ABS(B91-D91)<=0.5,"OK","DIVERSO") -> OK | F91: capitolo 9
A92: Pareggio con costi fissi + 30.000 | B92: =ROUNDUP(($B$11+$B$86)/$B$12,0) -> 5750 | C92: unità | D92: 5750 | E92: =IF(ABS(B92-D92)<=0.5,"OK","DIVERSO") -> OK | F92: capitolo 9
A94: Break-even in una decisione reale
A95: Nuovo servizio: pareggio e risultato a capacità massima, poi con prezzo 70; capitolo 9
A96: Voce | B96: Valore | C96: Unità | D96: Valore atteso (libro) | E96: Controllo | F96: Fonte nel libro
A97: Costi fissi annuali | B97: 180000 | C97: euro | F97: capitolo 9
A98: Prezzo medio | B98: 75 | C98: euro/unità | F98: capitolo 9
A99: Costo variabile | B99: 30 | C99: euro/unità | F99: capitolo 9
A100: Capacità massima | B100: 5000 | C100: unità | F100: capitolo 9
A101: Margine unitario | B101: =$B$98-$B$99 -> 45 | C101: euro/unità | D101: 45 | E101: =IF(ABS(B101-D101)<=0.5,"OK","DIVERSO") -> OK | F101: capitolo 9
A102: Pareggio in prestazioni | B102: =ROUNDUP($B$97/$B$101,0) -> 4000 | C102: unità | D102: 4000 | E102: =IF(ABS(B102-D102)<=0.5,"OK","DIVERSO") -> OK | F102: capitolo 9
A103: Risultato a capacità massima | B103: =$B$100*$B$101-$B$97 -> 45000 | C103: euro | D103: 45000 | E103: =IF(ABS(B103-D103)<=0.5,"OK","DIVERSO") -> OK | F103: capitolo 9
A104: Prezzo medio ridotto | B104: 70 | C104: euro/unità | F104: capitolo 9
A105: Margine con prezzo 70 | B105: =$B$104-$B$99 -> 40 | C105: euro/unità | D105: 40 | E105: =IF(ABS(B105-D105)<=0.5,"OK","DIVERSO") -> OK | F105: capitolo 9
A106: Pareggio con prezzo 70 | B106: =ROUNDUP($B$97/$B$105,0) -> 4500 | C106: unità | D106: 4500 | E106: =IF(ABS(B106-D106)<=0.5,"OK","DIVERSO") -> OK | F106: capitolo 9
A107: Risultato massimo con prezzo 70 | B107: =$B$100*$B$105-$B$97 -> 20000 | C107: euro | D107: 20000 | E107: =IF(ABS(B107-D107)<=0.5,"OK","DIVERSO") -> OK | F107: capitolo 9
A109: Impresa guida - pareggio in fatturato
A110: Pareggio sulla struttura base e verifica che cada sotto la soglia delle 21.000 ore; capitolo 9
...

Sheet Cap_10
A1: Capitolo 10 - Activity Based Costing
A2: Controllo di gestione con l'intelligenza artificiale - file Excel che accompagna il libro
A3: Celle blu su fondo giallo: dati da cambiare. Celle nere: formule. «Valore atteso (libro)» e «Controllo» confrontano il calcolo con il numero stampato nel libro.
A4: Le due fasi dell'ABC sull'esempio illustrativo, il TDABC, il confronto con il sistema tradizionale e il modello per canale dell'impresa guida.
A6: Risorse da ripartire
A7: Le quattro risorse che alimentano le attività dell'esempio illustrativo; capitolo 10
A8: Voce | B8: Valore | C8: Unità | D8: Valore atteso (libro) | E8: Controllo | F8: Fonte nel libro
A9: Personale indiretto | B9: 480000 | C9: euro | F9: capitolo 10
A10: Ammortamenti e manutenzioni attrezzature | B10: 150000 | C10: euro | F10: capitolo 10
A11: Sistemi informativi | B11: 90000 | C11: euro | F11: capitolo 10
A12: Metri quadrati occupati | B12: 1200 | C12: metri quadrati | F12: capitolo 10
A13: Costo per metro quadrato | B13: 50 | C13: euro/metro quadrato | F13: capitolo 10
A14: Spazi | B14: =$B$12*$B$13 -> 60000 | C14: euro | D14: 60000 | E14: =IF(ABS(B14-D14)<=0.5,"OK","DIVERSO") -> OK | F14: capitolo 10
A15: Totale risorse | B15: =$B$9+$B$10+$B$11+$B$14 -> 780000 | C15: euro | D15: 780000 | E15: =IF(ABS(B15-D15)<=0.5,"OK","DIVERSO") -> OK | F15: capitolo 10
A17: Prima fase - personale e attrezzature
A18: Ripartizione di personale (quote di tempo) e attrezzature (utilizzo) sulle attività; capitolo 10
A19: Voce | B19: Valore | C19: Unità | D19: Valore atteso (libro) | E19: Controllo | F19: Fonte nel libro
A20: Personale - quota attrezzaggi | B20: 0.25 | C20: % | F20: capitolo 10
A21: Personale - quota gestione ordini | B21: 0.35 | C21: % | F21: capitolo 10
A22: Personale - quota controllo qualità | B22: 0.15 | C22: % | F22: capitolo 10
A23: Personale - quota assistenza | B23: 0.25 | C23: % | F23: capitolo 10
A24: Personale - a attrezzaggi | B24: =$B$9*$B$20 -> 120000 | C24: euro | D24: 120000 | E24: =IF(ABS(B24-D24)<=0.5,"OK","DIVERSO") -> OK | F24: capitolo 10
A25: Personale - a gestione ordini | B25: =$B$9*$B$21 -> 168000 | C25: euro | D25: 168000 | E25: =IF(ABS(B25-D25)<=0.5,"OK","DIVERSO") -> OK | F25: capitolo 10
A26: Personale - a controllo qualità | B26: =$B$9*$B$22 -> 72000 | C26: euro | D26: 72000 | E26: =IF(ABS(B26-D26)<=0.5,"OK","DIVERSO") -> OK | F26: capitolo 10
A27: Personale - a assistenza | B27: =$B$9*$B$23 -> 120000 | C27: euro | D27: 120000 | E27: =IF(ABS(B27-D27)<=0.5,"OK","DIVERSO") -> OK | F27: capitolo 10
A28: Personale - totale ripartito | B28: =$B$24+$B$25+$B$26+$B$27 -> 480000 | C28: euro | D28: 480000 | E28: =IF(ABS(B28-D28)<=0.5,"OK","DIVERSO") -> OK | F28: capitolo 10
A29: Attrezzature - quota attrezzaggi | B29: 0.3 | C29: % | F29: capitolo 10
A30: Attrezzature - quota gestione ordini | B30: 0 | C30: % | F30: capitolo 10
A31: Attrezzature - quota controllo qualità | B31: 0.4 | C31: % | F31: capitolo 10
A32: Attrezzature - quota assistenza | B32: 0.3 | C32: % | F32: capitolo 10
A33: Attrezzature - a attrezzaggi | B33: =$B$10*$B$29 -> 45000 | C33: euro | D33: 45000 | E33: =IF(ABS(B33-D33)<=0.5,"OK","DIVERSO") -> OK | F33: capitolo 10
A34: Attrezzature - a gestione ordini | B34: =$B$10*$B$30 -> 0 | C34: euro | D34: 0 | E34: =IF(ABS(B34-D34)<=0.5,"OK","DIVERSO") -> OK | F34: capitolo 10
A35: Attrezzature - a controllo qualità | B35: =$B$10*$B$31 -> 60000 | C35: euro | D35: 60000 | E35: =IF(ABS(B35-D35)<=0.5,"OK","DIVERSO") -> OK | F35: capitolo 10
A36: Attrezzature - a assistenza | B36: =$B$10*$B$32 -> 45000 | C36: euro | D36: 45000 | E36: =IF(ABS(B36-D36)<=0.5,"OK","DIVERSO") -> OK | F36: capitolo 10
A37: Attrezzature - totale ripartito | B37: =$B$33+$B$34+$B$35+$B$36 -> 150000 | C37: euro | D37: 150000 | E37: =IF(ABS(B37-D37)<=0.5,"OK","DIVERSO") -> OK | F37: capitolo 10
A39: Prima fase - sistemi e spazi
A40: Ripartizione di sistemi (transazioni) e spazi (metri quadrati) sulle attività; capitolo 10
A41: Voce | B41: Valore | C41: Unità | D41: Valore atteso (libro) | E41: Controllo | F41: Fonte nel libro
A42: Sistemi - quota attrezzaggi | B42: 0.05 | C42: % | F42: capitolo 10
A43: Sistemi - quota gestione ordini | B43: 0.5 | C43: % | F43: capitolo 10
A44: Sistemi - quota controllo qualità | B44: 0.1 | C44: % | F44: capitolo 10
A45: Sistemi - quota assistenza | B45: 0.35 | C45: % | F45: capitolo 10
A46: Sistemi - a attrezzaggi | B46: =$B$11*$B$42 -> 4500 | C46: euro | D46: 4500 | E46: =IF(ABS(B46-D46)<=0.5,"OK","DIVERSO") -> OK | F46: capitolo 10
A47: Sistemi - a gestione ordini | B47: =$B$11*$B$43 -> 45000 | C47: euro | D47: 45000 | E47: =IF(ABS(B47-D47)<=0.5,"OK","DIVERSO") -> OK | F47: capitolo 10
A48: Sistemi - a controllo qualità | B48: =$B$11*$B$44 -> 9000 | C48: euro | D48: 9000 | E48: =IF(ABS(B48-D48)<=0.5,"OK","DIVERSO") -> OK | F48: capitolo 10
A49: Sistemi - a assistenza | B49: =$B$11*$B$45 -> 31500 | C49: euro | D49: 31500 | E49: =IF(ABS(B49-D49)<=0.5,"OK","DIVERSO") -> OK | F49: capitolo 10
A50: Sistemi - totale ripartito | B50: =$B$46+$B$47+$B$48+$B$49 -> 90000 | C50: euro | D50: 90000 | E50: =IF(ABS(B50-D50)<=0.5,"OK","DIVERSO") -> OK | F50: capitolo 10
A51: Spazi - metri quadrati attrezzaggi | B51: 210 | C51: metri quadrati | F51: capitolo 10
A52: Spazi - metri quadrati gestione ordini | B52: 540 | C52: metri quadrati | F52: capitolo 10
A53: Spazi - metri quadrati controllo qualità | B53: 180 | C53: metri quadrati | F53: capitolo 10
A54: Spazi - metri quadrati assistenza | B54: 270 | C54: metri quadrati | F54: capitolo 10
A55: Spazi - a attrezzaggi | B55: =$B$51*$B$13 -> 10500 | C55: euro | D55: 10500 | E55: =IF(ABS(B55-D55)<=0.5,"OK","DIVERSO") -> OK | F55: capitolo 10
A56: Spazi - a gestione ordini | B56: =$B$52*$B$13 -> 27000 | C56: euro | D56: 27000 | E56: =IF(ABS(B56-D56)<=0.5,"OK","DIVERSO") -> OK | F56: capitolo 10
A57: Spazi - a controllo qualità | B57: =$B$53*$B$13 -> 9000 | C57: euro | D57: 9000 | E57: =IF(ABS(B57-D57)<=0.5,"OK","DIVERSO") -> OK | F57: capitolo 10
A58: Spazi - a assistenza | B58: =$B$54*$B$13 -> 13500 | C58: euro | D58: 13500 | E58: =IF(ABS(B58-D58)<=0.5,"OK","DIVERSO") -> OK | F58: capitolo 10
A59: Spazi - totale ripartito | B59: =$B$55+$B$56+$B$57+$B$58 -> 60000 | C59: euro | D59: 60000 | E59: =IF(ABS(B59-D59)<=0.5,"OK","DIVERSO") -> OK | F59: capitolo 10
A60: Metri quadrati ripartiti meno totale | B60: =$B$51+$B$52+$B$53+$B$54-$B$12 -> 0 | C60: metri quadrati | D60: 0 | E60: =IF(ABS(B60-D60)<=0.5,"OK","DIVERSO") -> OK | F60: capitolo 10
A62: Pool di attività e tariffe
A63: Somma dei pool, quadratura con le risorse e tariffe della seconda fase; capitolo 10
A64: Voce | B64: Valore | C64: Unità | D64: Valore atteso (libro) | E64: Controllo | F64: Fonte nel libro
A65: Pool attrezzaggi | B65: =$B$24+$B$33+$B$46+$B$55 -> 180000 | C65: euro | D65: 180000 | E65: =IF(ABS(B65-D65)<=0.5,"OK","DIVERSO") -> OK | F65: capitolo 10
A66: Pool gestione ordini | B66: =$B$25+$B$34+$B$47+$B$56 -> 240000 | C66: euro | D66: 240000 | E66: =IF(ABS(B66-D66)<=0.5,"OK","DIVERSO") -> OK | F66: capitolo 10
A67: Pool controllo qualità | B67: =$B$26+$B$35+$B$48+$B$57 -> 150000 | C67: euro | D67: 150000 | E67: =IF(ABS(B67-D67)<=0.5,"OK","DIVERSO") -> OK | F67: capitolo 10
A68: Pool assistenza | B68: =$B$27+$B$36+$B$49+$B$58 -> 210000 | C68: euro | D68: 210000 | E68: =IF(ABS(B68-D68)<=0.5,"OK","DIVERSO") -> OK | F68: capitolo 10
A69: Totale pool | B69: =$B$65+$B$66+$B$67+$B$68 -> 780000 | C69: euro | D69: 780000 | E69: =IF(ABS(B69-D69)<=0.5,"OK","DIVERSO") -> OK | F69: capitolo 10
A70: Pool meno risorse (quadratura) | B70: =$B$69-$B$15 -> 0 | C70: euro | D70: 0 | E70: =IF(ABS(B70-D70)<=0.5,"OK","DIVERSO") -> OK | F70: capitolo 10
A71: Volume driver attrezzaggi | B71: 600 | C71: attrezzaggi | F71: capitolo 10
A72: Volume driver gestione ordini | B72: 12000 | C72: ordini | F72: capitolo 10
A73: Volume driver controllo qualità | B73: 3000 | C73: controlli | F73: capitolo 10
A74: Volume driver assistenza | B74: 7000 | C74: ore | F74: capitolo 10
A75: Tariffa attrezzaggi | B75: =$B$65/$B$71 -> 300 | C75: euro/attrezzaggio | D75: 300 | E75: =IF(ABS(B75-D75)<=0.5,"OK","DIVERSO") -> OK | F75: capitolo 10
A76: Tariffa gestione ordini | B76: =$B$66/$B$72 -> 20 | C76: euro/ordine | D76: 20 | E76: =IF(ABS(B76-D76)<=0.5,"OK","DIVERSO") -> OK | F76: capitolo 10
A77: Tariffa controllo qualità | B77: =$B$67/$B$73 -> 50 | C77: euro/controllo | D77: 50 | E77: =IF(ABS(B77-D77)<=0.5,"OK","DIVERSO") -> OK | F77: capitolo 10
A78: Tariffa assistenza | B78: =$B$68/$B$74 -> 30 | C78: euro/ora | D78: 30 | E78: =IF(ABS(B78-D78)<=0.5,"OK","DIVERSO") -> OK | F78: capitolo 10
A79: Quota delle risorse ripartita con i tempi del personale | B79: =$B$9/$B$15 -> 0.61538462 | C79: % | F79: capitolo 10
A81: Esempio di calcolo ABC
A82: Attrezzaggi attribuiti ai prodotti A e B con la tariffa di 300 euro; capitolo 10
A83: Voce | B83: Valore | C83: Unità | D83: Valore atteso (libro) | E83: Controllo | F83: Fonte nel libro
A84: Attrezzaggi del prodotto A | B84: 80 | C84: attrezzaggi | F84: capitolo 10
A85: Attrezzaggi del prodotto B | B85: 220 | C85: attrezzaggi | F85: capitolo 10
A86: Costo attribuito ad A | B86: =$B$84*$B$75 -> 24000 | C86: euro | D86: 24000 | E86: =IF(ABS(B86-D86)<=0.5,"OK","DIVERSO") -> OK | F86: capitolo 10
A87: Costo attribuito a B | B87: =$B$85*$B$75 -> 66000 | C87: euro | D87: 66000 | E87: =IF(ABS(B87-D87)<=0.5,"OK","DIVERSO") -> OK | F87: capitolo 10
A88: Resto agli altri prodotti | B88: =$B$65-$B$86-$B$87 -> 90000 | C88: euro | F88: capitolo 10
A90: Time-Driven ABC
A91: Costo per minuto della capacità pratica e costo di un ordine standard e complesso; capitolo 10
A92: Voce | B92: Valore | C92: Unità | D92: Valore atteso (libro) | E92: Controllo | F92: Fonte nel libro
A93: Costo del team | B93: 360000 | C93: euro | F93: capitolo 10
A94: Minuti di capacità pratica | B94: 600000 | C94: minuti | F94: capitolo 10
A95: Costo per minuto | B95: =$B$93/$B$94 -> 0.6 | C95: euro/minuto | D95: 0.6 | E95: =IF(ABS(B95-D95)<=0.005,"OK","DIVERSO") -> OK | F95: capitolo 10
A96: Minuti ordine standard | B96: 8 | C96: minuti/ordine | F96: capitolo 10
A97: Costo ordine standard | B97: =$B$96*$B$95 -> 4.8 | C97: euro/ordine | D97: 4.8 | E97: =IF(ABS(B97-D97)<=0.005,"OK","DIVERSO") -> OK | F97: capitolo 10
A98: Minuti aggiuntivi ordine complesso | B98: 12 | C98: minuti/ordine | F98: capitolo 10
A99: Minuti ordine complesso | B99: =$B$96+$B$98 -> 20 | C99: minuti/ordine | D99: 20 | E99: =IF(ABS(B99-D99)<=0.5,"OK","DIVERSO") -> OK | F99: capitolo 10
A100: Costo ordine complesso | B100: =$B$99*$B$95 -> 12 | C100: euro/ordine | D100: 12 | E100: =IF(ABS(B100-D100)<=0.005,"OK","DIVERSO") -> OK | F100: capitolo 10
A102: Tradizionale e ABC a confronto
A103: 300.000 euro di indiretti: ore macchina contro tre pool; capitolo 10
A104: Voce | B104: Valore | C104: Unità | D104: Valore atteso (libro) | E104: Controllo | F104: Fonte nel libro
A105: Costi indiretti | B105: 300000 | C105: euro | F105: capitolo 10
A106: Quota ore macchina di A | B106: 0.7 | C106: % | F106: capitolo 10
A107: Tradizionale - A | B107: =$B$105*$B$106 -> 210000 | C107: euro | D107: 210000 | E107: =IF(ABS(B107-D107)<=0.5,"OK","DIVERSO") -> OK | F107: capitolo 10
...

Sheet Cap_11
A1: Capitolo 11 - Activity Based Management
A2: Controllo di gestione con l'intelligenza artificiale - file Excel che accompagna il libro
A3: Celle blu su fondo giallo: dati da cambiare. Celle nere: formule. «Valore atteso (libro)» e «Controllo» confrontano il calcolo con il numero stampato nel libro.
A4: Capacità fornita e utilizzata, costo di servizio dei clienti X e Y e leve che separano la minore spesa dalla capacità liberata.
A6: Capacità fornita e utilizzata
A7: Team che può gestire 10.000 ordini e ne gestisce 8.000; capitolo 11
A8: Voce | B8: Valore | C8: Unità | D8: Valore atteso (libro) | E8: Controllo | F8: Fonte nel libro
A9: Ordini gestibili (capacità fornita) | B9: 10000 | C9: ordini | F9: capitolo 11
A10: Ordini gestiti (capacità utilizzata) | B10: 8000 | C10: ordini | F10: capitolo 11
A11: Capacità inutilizzata | B11: =$B$9-$B$10 -> 2000 | C11: ordini | F11: capitolo 11
A12: Quota di capacità inutilizzata | B12: =$B$11/$B$9 -> 0.2 | C12: % | F12: capitolo 11
A14: Impresa guida - natura dei pool
A15: Parte di ciascun pool che varia con il driver e parte che è costo di capacità; capitolo 11
A16: Voce | B16: Valore | C16: Unità | D16: Valore atteso (libro) | E16: Controllo | F16: Fonte nel libro
A17: Gestione ordini - costo variabile per ordine | B17: 0 | C17: euro/ordine | F17: capitolo 11
A18: Gestione ordini - costo di capacità | B18: =Cap_10!$B$131-$B$17*Cap_10!$B$146 -> 240000 | C18: euro | D18: 240000 | E18: =IF(ABS(B18-D18)<=0.5,"OK","DIVERSO") -> OK | F18: capitolo 11
A19: Consegne - trasporti per consegna | B19: =Cap_10!$B$132/Cap_10!$B$147 -> 23 | C19: euro/consegna | D19: 23 | E19: =IF(ABS(B19-D19)<=0.5,"OK","DIVERSO") -> OK | F19: capitolo 11
A20: Consegne - personale per consegna (capacità) | B20: =Cap_10!$B$133/Cap_10!$B$147 -> 7 | C20: euro/consegna | D20: 7 | E20: =IF(ABS(B20-D20)<=0.5,"OK","DIVERSO") -> OK | F20: capitolo 11
A21: Variabile più capacità meno tariffa | B21: =$B$19+$B$20-Cap_10!$B$150 -> 0 | C21: euro/consegna | D21: 0 | E21: =IF(ABS(B21-D21)<=0.5,"OK","DIVERSO") -> OK | F21: capitolo 11
A22: Assistenza - costo di capacità | B22: =Cap_10!$B$135 -> 118000 | C22: euro | D22: 118000 | E22: =IF(ABS(B22-D22)<=0.5,"OK","DIVERSO") -> OK | F22: capitolo 11
A23: Assistenza - ricambi e trasferte | B23: 32.000 euro variano con le ore di intervento tecnico, non con tutte le 7.500 ore (capitolo 11)
A25: Impresa guida - clienti X e Y
A26: Costo di servizio a tariffa e margine cliente di CL-014 e CL-027; capitolo 11
A27: Voce | B27: Valore | C27: Unità | D27: Valore atteso (libro) | E27: Controllo | F27: Fonte nel libro
A28: Ricavi di ciascun cliente | B28: 240000 | C28: euro | F28: capitolo 11
A29: Margine di prodotto di ciascun cliente | B29: 84000 | C29: euro | F29: capitolo 11
A30: X - ordini | B30: 600 | C30: ordini | F30: capitolo 11
A31: X - consegne | B31: 300 | C31: consegne | F31: capitolo 11
A32: X - ore di assistenza | B32: 250 | C32: ore | F32: capitolo 11
A33: X - costo di servizio | B33: =$B$30*Cap_10!$B$149+$B$31*Cap_10!$B$150+$B$32*Cap_10!$B$151 -> 26000 | C33: euro | D33: 26000 | E33: =IF(ABS(B33-D33)<=0.5,"OK","DIVERSO") -> OK | F33: capitolo 11
A34: X - margine cliente | B34: =$B$29-$B$33 -> 58000 | C34: euro | D34: 58000 | E34: =IF(ABS(B34-D34)<=0.5,"OK","DIVERSO") -> OK | F34: capitolo 11
A35: X - margine cliente % | B35: =$B$34/$B$28 -> 0.24166667 | C35: % | D35: 0.242 | E35: =IF(ABS(B35-D35)<=0.0005,"OK","DIVERSO") -> OK | F35: capitolo 11
A36: Y - ordini | B36: 150 | C36: ordini | F36: capitolo 11
A37: Y - consegne | B37: 60 | C37: consegne | F37: capitolo 11
A38: Y - ore di assistenza | B38: 40 | C38: ore | F38: capitolo 11
A39: Y - costo di servizio | B39: =$B$36*Cap_10!$B$149+$B$37*Cap_10!$B$150+$B$38*Cap_10!$B$151 -> 5600 | C39: euro | D39: 5600 | E39: =IF(ABS(B39-D39)<=0.5,"OK","DIVERSO") -> OK | F39: capitolo 11
A40: Y - margine cliente | B40: =$B$29-$B$39 -> 78400 | C40: euro | D40: 78400 | E40: =IF(ABS(B40-D40)<=0.5,"OK","DIVERSO") -> OK | F40: capitolo 11
A41: Y - margine cliente % | B41: =$B$40/$B$28 -> 0.32666667 | C41: % | D41: 0.327 | E41: =IF(ABS(B41-D41)<=0.0005,"OK","DIVERSO") -> OK | F41: capitolo 11
A43: Impresa guida - leve su X
A44: Ordini da 600 a 300 e consegne da 300 a 24: riduzione a tariffa, minore spesa e capacità liberata; capitolo 11
A45: Voce | B45: Valore | C45: Unità | D45: Valore atteso (libro) | E45: Controllo | F45: Fonte nel libro
A46: X - ordini dopo la leva | B46: 300 | C46: ordini | F46: capitolo 11
A47: X - consegne dopo la leva | B47: 24 | C47: consegne | F47: capitolo 11
A48: X - ore dopo la leva (invariate) | B48: =$B$32 -> 250 | C48: ore | D48: 250 | E48: =IF(ABS(B48-D48)<=0.5,"OK","DIVERSO") -> OK | F48: capitolo 11
A49: Ordini in meno | B49: =$B$30-$B$46 -> 300 | C49: ordini | D49: 300 | E49: =IF(ABS(B49-D49)<=0.5,"OK","DIVERSO") -> OK | F49: capitolo 11
A50: Consegne in meno | B50: =$B$31-$B$47 -> 276 | C50: consegne | D50: 276 | E50: =IF(ABS(B50-D50)<=0.5,"OK","DIVERSO") -> OK | F50: capitolo 11
A51: Ore in meno | B51: =$B$32-$B$48 -> 0 | C51: ore | D51: 0 | E51: =IF(ABS(B51-D51)<=0.5,"OK","DIVERSO") -> OK | F51: capitolo 11
A52: Ordini - riduzione a tariffa | B52: =$B$49*Cap_10!$B$149 -> 6000 | C52: euro | D52: 6000 | E52: =IF(ABS(B52-D52)<=0.5,"OK","DIVERSO") -> OK | F52: capitolo 11
A53: Ordini - minore spesa | B53: =$B$49*$B$17 -> 0 | C53: euro | D53: 0 | E53: =IF(ABS(B53-D53)<=0.5,"OK","DIVERSO") -> OK | F53: capitolo 11
A54: Ordini - capacità liberata | B54: =$B$52-$B$53 -> 6000 | C54: euro | D54: 6000 | E54: =IF(ABS(B54-D54)<=0.5,"OK","DIVERSO") -> OK | F54: capitolo 11
A55: Consegne - riduzione a tariffa | B55: =$B$50*Cap_10!$B$150 -> 8280 | C55: euro | D55: 8280 | E55: =IF(ABS(B55-D55)<=0.5,"OK","DIVERSO") -> OK | F55: capitolo 11
A56: Consegne - minore spesa | B56: =$B$50*$B$19 -> 6348 | C56: euro | D56: 6348 | E56: =IF(ABS(B56-D56)<=0.5,"OK","DIVERSO") -> OK | F56: capitolo 11
A57: Consegne - capacità liberata | B57: =$B$55-$B$56 -> 1932 | C57: euro | D57: 1932 | E57: =IF(ABS(B57-D57)<=0.5,"OK","DIVERSO") -> OK | F57: capitolo 11
A58: Assistenza - riduzione a tariffa | B58: =$B$51*Cap_10!$B$151 -> 0 | C58: euro | D58: 0 | E58: =IF(ABS(B58-D58)<=0.5,"OK","DIVERSO") -> OK | F58: capitolo 11
A59: Assistenza - minore spesa | B59: =0*$B$51 -> 0 | C59: euro | D59: 0 | E59: =IF(ABS(B59-D59)<=0.5,"OK","DIVERSO") -> OK | F59: capitolo 11
A60: Assistenza - capacità liberata | B60: =$B$58-$B$59 -> 0 | C60: euro | D60: 0 | E60: =IF(ABS(B60-D60)<=0.5,"OK","DIVERSO") -> OK | F60: capitolo 11
A61: Totale riduzione a tariffa | B61: =$B$52+$B$55+$B$58 -> 14280 | C61: euro | D61: 14280 | E61: =IF(ABS(B61-D61)<=0.5,"OK","DIVERSO") -> OK | F61: capitolo 11
A62: Totale minore spesa | B62: =$B$53+$B$56+$B$59 -> 6348 | C62: euro | D62: 6348 | E62: =IF(ABS(B62-D62)<=0.5,"OK","DIVERSO") -> OK | F62: capitolo 11
A63: Totale capacità liberata | B63: =$B$54+$B$57+$B$60 -> 7932 | C63: euro | D63: 7932 | E63: =IF(ABS(B63-D63)<=0.5,"OK","DIVERSO") -> OK | F63: capitolo 11
A65: Impresa guida - X dopo le leve
A66: Costo di servizio e margine di X a tariffa e ciò che il Conto Economico registra subito; capitolo 11
A67: Voce | B67: Valore | C67: Unità | D67: Valore atteso (libro) | E67: Controllo | F67: Fonte nel libro
A68: X - costo di servizio dopo le leve | B68: =$B$33-$B$61 -> 11720 | C68: euro | D68: 11720 | E68: =IF(ABS(B68-D68)<=0.5,"OK","DIVERSO") -> OK | F68: capitolo 11
A69: X - margine cliente dopo le leve | B69: =$B$29-$B$68 -> 72280 | C69: euro | D69: 72280 | E69: =IF(ABS(B69-D69)<=0.5,"OK","DIVERSO") -> OK | F69: capitolo 11
A70: X - margine cliente % dopo le leve | B70: =$B$69/$B$28 -> 0.30116667 | C70: % | D70: 0.301 | E70: =IF(ABS(B70-D70)<=0.0005,"OK","DIVERSO") -> OK | F70: capitolo 11
A71: Risparmio registrato subito nel Conto Economico | B71: =$B$62 -> 6348 | C71: euro | D71: 6348 | E71: =IF(ABS(B71-D71)<=0.5,"OK","DIVERSO") -> OK | F71: capitolo 11
A72: Capacità liberata da ridurre o reimpiegare | B72: =$B$63 -> 7932 | C72: euro | D72: 7932 | E72: =IF(ABS(B72-D72)<=0.5,"OK","DIVERSO") -> OK | F72: capitolo 11

Sheet Cap_12
A1: Capitolo 12 - Budget
A2: Controllo di gestione con l'intelligenza artificiale - file Excel che accompagna il libro
A3: Celle blu su fondo giallo: dati da cambiare. Celle nere: formule. «Valore atteso (libro)» e «Controllo» confrontano il calcolo con il numero stampato nel libro.
A4: Il budget dell'impresa guida dall'esercizio corrente, separato in run rate, driver e iniziative, con la sensibilità sul recupero di prezzo della linea B.
A6: Esercizio corrente (run rate)
A7: Valori di chiusura dell'esercizio corrente dal foglio Impresa_guida; capitolo 12, tabella
A8: Voce | B8: Valore | C8: Unità | D8: Valore atteso (libro) | E8: Controllo | F8: Fonte nel libro
A9: Risultato operativo esercizio corrente | B9: =Impresa_guida!$B$36-Impresa_guida!$B$41 -> 242000 | C9: euro | D9: 242000 | E9: =IF(ABS(B9-D9)<=0.5,"OK","DIVERSO") -> OK | F9: capitolo 12
A10: Margine unitario corrente linea A | B10: =Impresa_guida!$B$9-Impresa_guida!$B$10 -> 63 | C10: euro/unità | D10: 63 | E10: =IF(ABS(B10-D10)<=0.5,"OK","DIVERSO") -> OK | F10: capitolo 14
A11: Margine unitario corrente linea B | B11: =Impresa_guida!$B$13-Impresa_guida!$B$14 -> 38 | C11: euro/unità | D11: 38 | E11: =IF(ABS(B11-D11)<=0.5,"OK","DIVERSO") -> OK | F11: capitolo 12
A12: Margine unitario corrente linea C | B12: =Impresa_guida!$B$17-Impresa_guida!$B$18 -> 51 | C12: euro/unità | D12: 51 | E12: =IF(ABS(B12-D12)<=0.5,"OK","DIVERSO") -> OK | F12: capitolo 12
A14: Proposta commerciale di budget
A15: Volumi e prezzi proposti dalla direzione commerciale; costi variabili, tempi di ciclo e struttura base invariati; capitolo 12
A16: Voce | B16: Valore | C16: Unità | D16: Valore atteso (libro) | E16: Controllo | F16: Fonte nel libro
A17: Linea A - unità di budget | B17: =Impresa_guida!$B$8 -> 8000 | C17: unità | D17: 8000 | E17: =IF(ABS(B17-D17)<=0.5,"OK","DIVERSO") -> OK | F17: capitolo 12
A18: Linea A - prezzo di budget | B18: =Impresa_guida!$B$9 -> 180 | C18: euro/unità | D18: 180 | E18: =IF(ABS(B18-D18)<=0.5,"OK","DIVERSO") -> OK | F18: capitolo 12
A19: Linea B - unità di budget | B19: 11400 | C19: unità | F19: capitolo 12
A20: Linea B - prezzo di budget | B20: 118 | C20: euro/unità | F20: capitolo 12
A21: Linea C - unità di budget (obiettivo da verificare) | B21: 2100 | C21: unità | F21: capitolo 12
A22: Linea C - prezzo di budget | B22: =Impresa_guida!$B$17 -> 289 | C22: euro/unità | D22: 289 | E22: =IF(ABS(B22-D22)<=0.5,"OK","DIVERSO") -> OK | F22: capitolo 12
A24: Budget a margine dell'esercizio
A25: Ricavi, margine, ore, capacità esterna e risultato del budget; capitolo 12, capitolo 13
A26: Voce | B26: Valore | C26: Unità | D26: Valore atteso (libro) | E26: Controllo | F26: Fonte nel libro
A27: Unità vendute di budget | B27: =$B$17+$B$19+$B$21 -> 21500 | C27: unità | D27: 21500 | E27: =IF(ABS(B27-D27)<=0.5,"OK","DIVERSO") -> OK | F27: capitolo 13
A28: Ricavi di budget | B28: =$B$17*$B$18+$B$19*$B$20+$B$21*$B$22 -> 3392100 | C28: euro | D28: 3392100 | E28: =IF(ABS(B28-D28)<=0.5,"OK","DIVERSO") -> OK | F28: capitolo 13
A29: Costi variabili di budget | B29: =$B$17*Impresa_guida!$B$10+$B$19*Impresa_guida!$B$14+$B$21*Impresa_guida!$B$18 -> 2302200 | C29: euro | F29: capitolo 12
A30: Margine di contribuzione di budget | B30: =$B$28-$B$29 -> 1089900 | C30: euro | D30: 1089900 | E30: =IF(ABS(B30-D30)<=0.5,"OK","DIVERSO") -> OK | F30: capitolo 12
A31: Ore macchina di budget | B31: =$B$17*Impresa_guida!$B$11+$B$19*Impresa_guida!$B$15+$B$21*Impresa_guida!$B$19 -> 24000 | C31: ore | D31: 24000 | E31: =IF(ABS(B31-D31)<=0.5,"OK","DIVERSO") -> OK | F31: capitolo 12, capitolo 13
A32: Ore di capacità esterna | B32: =MAX($B$31-Impresa_guida!$B$26,0) -> 3000 | C32: ore | D32: 3000 | E32: =IF(ABS(B32-D32)<=0.5,"OK","DIVERSO") -> OK | F32: capitolo 12
A33: Costo della capacità esterna | B33: =$B$32*Impresa_guida!$B$27 -> 84000 | C33: euro | D33: 84000 | E33: =IF(ABS(B33-D33)<=0.5,"OK","DIVERSO") -> OK | F33: capitolo 12
A34: Costi della struttura di budget | B34: =Impresa_guida!$B$40+$B$33 -> 820000 | C34: euro | D34: 820000 | E34: =IF(ABS(B34-D34)<=0.5,"OK","DIVERSO") -> OK | F34: capitolo 12
A35: Risultato operativo di budget | B35: =$B$30-$B$34 -> 269900 | C35: euro | D35: 269900 | E35: =IF(ABS(B35-D35)<=0.5,"OK","DIVERSO") -> OK | F35: capitolo 12
A36: Miglioramento rispetto all'esercizio corrente | B36: =$B$35-$B$9 -> 27900 | C36: euro | D36: 27900 | E36: =IF(ABS(B36-D36)<=0.5,"OK","DIVERSO") -> OK | F36: capitolo 12
A38: Run rate, driver e iniziative
A39: Scomposizione del miglioramento in run rate, driver di volume e iniziativa di prezzo; capitolo 12, tabella
A40: Voce | B40: Valore | C40: Unità | D40: Valore atteso (libro) | E40: Controllo | F40: Fonte nel libro
A41: Driver: volume linea B | B41: =($B$19-Impresa_guida!$B$12)*$B$11 -> -22800 | C41: euro | D41: -22800 | E41: =IF(ABS(B41-D41)<=0.5,"OK","DIVERSO") -> OK | F41: capitolo 12
A42: Driver: volume linea C | B42: =($B$21-Impresa_guida!$B$16)*$B$12 -> 5100 | C42: euro | D42: 5100 | E42: =IF(ABS(B42-D42)<=0.5,"OK","DIVERSO") -> OK | F42: capitolo 12
A43: Iniziativa: recupero di prezzo linea B | B43: =($B$20-Impresa_guida!$B$13)*$B$19 -> 45600 | C43: euro | D43: 45600 | E43: =IF(ABS(B43-D43)<=0.5,"OK","DIVERSO") -> OK | F43: capitolo 12
A44: Variazione costi della struttura | B44: =Impresa_guida!$B$41-$B$34 -> 0 | C44: euro | D44: 0 | E44: =IF(ABS(B44-D44)<=0.5,"OK","DIVERSO") -> OK | F44: capitolo 12
A45: Ore liberate dalla linea B | B45: =(Impresa_guida!$B$12-$B$19)*Impresa_guida!$B$15 -> 300 | C45: ore | D45: 300 | E45: =IF(ABS(B45-D45)<=0.5,"OK","DIVERSO") -> OK | F45: capitolo 12
A46: Ore assorbite dalle unità aggiuntive di C | B46: =($B$21-Impresa_guida!$B$16)*Impresa_guida!$B$19 -> 300 | C46: ore | D46: 300 | E46: =IF(ABS(B46-D46)<=0.5,"OK","DIVERSO") -> OK | F46: capitolo 12
A47: Budget ricostruito dal ponte | B47: =$B$9+$B$41+$B$42+$B$43+$B$44 -> 269900 | C47: euro | D47: 269900 | E47: =IF(ABS(B47-D47)<=0.5,"OK","DIVERSO") -> OK | F47: capitolo 12
A48: Controllo ponte contro budget | B48: =IF(ABS($B$47-$B$35)<0.01,"Quadra","Non quadra") -> Quadra | D48: Quadra | E48: =IF(B48=D48,"OK","DIVERSO") -> OK | F48: capitolo 12
A50: Sensibilità sull'iniziativa
A51: Risultato senza iniziativa e con recupero di prezzo da luglio (ipotesi del caso); capitolo 12
A52: Voce | B52: Valore | C52: Unità | D52: Valore atteso (libro) | E52: Controllo | F52: Fonte nel libro
A53: Risultato senza l'iniziativa | B53: =$B$35-$B$43 -> 224300 | C53: euro | D53: 224300 | E53: =IF(ABS(B53-D53)<=0.5,"OK","DIVERSO") -> OK | F53: capitolo 12
A54: Differenza dall'esercizio corrente | B54: =$B$53-$B$9 -> -17700 | C54: euro | D54: -17700 | E54: =IF(ABS(B54-D54)<=0.5,"OK","DIVERSO") -> OK | F54: capitolo 12
A55: Quota dei volumi di B nel secondo semestre | B55: 0.5 | C55: % | F55: capitolo 12
A56: Unità di B da luglio | B56: =$B$19*$B$55 -> 5700 | C56: unità | D56: 5700 | E56: =IF(ABS(B56-D56)<=0.5,"OK","DIVERSO") -> OK | F56: capitolo 12
A57: Beneficio con avvio a luglio | B57: =($B$20-Impresa_guida!$B$13)*$B$56 -> 22800 | C57: euro | D57: 22800 | E57: =IF(ABS(B57-D57)<=0.5,"OK","DIVERSO") -> OK | F57: capitolo 12
A58: Risultato con avvio a luglio | B58: =$B$53+$B$57 -> 247100 | C58: euro | D58: 247100 | E58: =IF(ABS(B58-D58)<=0.5,"OK","DIVERSO") -> OK | F58: capitolo 12

Sheet Cap_13
A1: Capitolo 13 - Budget operativo
A2: Controllo di gestione con l'intelligenza artificiale - file Excel che accompagna il libro
A3: Celle blu su fondo giallo: dati da cambiare. Celle nere: formule. «Valore atteso (libro)» e «Controllo» confrontano il calcolo con il numero stampato nel libro.
A4: Dalle vendite a produzione, ore, capacità e cassa: gli esempi del capitolo e il budget operativo dell'impresa guida, annuale e di marzo.
A6: Programma delle vendite (esempio)
A7: Ricavi = quantità x prezzo per due prodotti generici, non le linee dell'impresa guida; capitolo 13
A8: Voce | B8: Valore | C8: Unità | D8: Valore atteso (libro) | E8: Controllo | F8: Fonte nel libro
A9: Prodotto A - quantità | B9: 8000 | C9: unità | F9: capitolo 13
A10: Prodotto A - prezzo medio | B10: 120 | C10: euro/unità | F10: capitolo 13
A11: Prodotto B - quantità | B11: 5000 | C11: unità | F11: capitolo 13
A12: Prodotto B - prezzo medio | B12: 80 | C12: euro/unità | F12: capitolo 13
A13: Ricavi prodotto A | B13: =$B$9*$B$10 -> 960000 | C13: euro | D13: 960000 | E13: =IF(ABS(B13-D13)<=0.5,"OK","DIVERSO") -> OK | F13: capitolo 13
A14: Ricavi prodotto B | B14: =$B$11*$B$12 -> 400000 | C14: euro | D14: 400000 | E14: =IF(ABS(B14-D14)<=0.5,"OK","DIVERSO") -> OK | F14: capitolo 13
A15: Quantità totale | B15: =$B$9+$B$11 -> 13000 | C15: unità | D15: 13000 | E15: =IF(ABS(B15-D15)<=0.5,"OK","DIVERSO") -> OK | F15: capitolo 13
A16: Ricavi totali | B16: =$B$13+$B$14 -> 1360000 | C16: euro | D16: 1360000 | E16: =IF(ABS(B16-D16)<=0.5,"OK","DIVERSO") -> OK | F16: capitolo 13
A18: Produzione, materiali e lavoro (esempio)
A19: Produzione = vendite + scorte finali - scorte iniziali; fabbisogno materiali e ore; capitolo 13
A20: Voce | B20: Valore | C20: Unità | D20: Valore atteso (libro) | E20: Controllo | F20: Fonte nel libro
A21: Vendite previste | B21: 8000 | C21: unità | F21: capitolo 13
A22: Scorta finale desiderata | B22: 1200 | C22: unità | F22: capitolo 13
A23: Scorta iniziale | B23: 900 | C23: unità | F23: capitolo 13
A24: Produzione | B24: =$B$21+$B$22-$B$23 -> 8300 | C24: unità | D24: 8300 | E24: =IF(ABS(B24-D24)<=0.5,"OK","DIVERSO") -> OK | F24: capitolo 13
A25: Consumo standard per unità (kg) | B25: 3 | C25: kg/unità | F25: capitolo 13
A26: Fabbisogno di materiale (kg) | B26: =$B$24*$B$25 -> 24900 | C26: kg | D26: 24900 | E26: =IF(ABS(B26-D26)<=0.5,"OK","DIVERSO") -> OK | F26: capitolo 13
A27: Tempo standard per unità | B27: 0.5 | C27: ore/unità | F27: capitolo 13
A28: Ore di lavoro diretto necessarie | B28: =$B$24*$B$27 -> 4150 | C28: ore | D28: 4150 | E28: =IF(ABS(B28-D28)<=0.5,"OK","DIVERSO") -> OK | F28: capitolo 13
A30: Dal volume alla cassa (esempio)
A31: Margine del mese e incasso del mese di vendita; capitolo 13
A32: Voce | B32: Valore | C32: Unità | D32: Valore atteso (libro) | E32: Controllo | F32: Fonte nel libro
A33: Unità vendute nel mese | B33: 2000 | C33: unità | F33: capitolo 13
A34: Prezzo | B34: 150 | C34: euro/unità | F34: capitolo 13
A35: Costo variabile industriale unitario | B35: 70 | C35: euro/unità | F35: capitolo 13
A36: Spese variabili commerciali su ricavi | B36: 0.05 | C36: % | F36: capitolo 13
A37: Quota incassata nel mese | B37: 0.4 | C37: % | F37: capitolo 13
A38: Ricavi | B38: =$B$33*$B$34 -> 300000 | C38: euro | D38: 300000 | E38: =IF(ABS(B38-D38)<=0.5,"OK","DIVERSO") -> OK | F38: capitolo 13
A39: Costi variabili industriali | B39: =$B$33*$B$35 -> 140000 | C39: euro | D39: 140000 | E39: =IF(ABS(B39-D39)<=0.5,"OK","DIVERSO") -> OK | F39: capitolo 13
A40: Spese variabili commerciali | B40: =$B$38*$B$36 -> 15000 | C40: euro | D40: 15000 | E40: =IF(ABS(B40-D40)<=0.5,"OK","DIVERSO") -> OK | F40: capitolo 13
A41: Margine di contribuzione | B41: =$B$38-$B$39-$B$40 -> 145000 | C41: euro | D41: 145000 | E41: =IF(ABS(B41-D41)<=0.5,"OK","DIVERSO") -> OK | F41: capitolo 13
A42: Incassi del mese di vendita | B42: =$B$38*$B$37 -> 120000 | C42: euro | D42: 120000 | E42: =IF(ABS(B42-D42)<=0.5,"OK","DIVERSO") -> OK | F42: capitolo 13
A44: Budget operativo annuale per linea
A45: Produzione con scorte finali uguali alle iniziali e ore per linea; ricavi e capacità dal capitolo 12; capitolo 13, tabella
A46: Voce | B46: Valore | C46: Unità | D46: Valore atteso (libro) | E46: Controllo | F46: Fonte nel libro
A47: Scorte finali meno iniziali (ipotesi del caso) | B47: 0 | C47: unità | F47: capitolo 13
A48: Produzione linea A | B48: =Cap_12!$B$17+$B$47 -> 8000 | C48: unità | D48: 8000 | E48: =IF(ABS(B48-D48)<=0.5,"OK","DIVERSO") -> OK | F48: capitolo 13
A49: Produzione linea B | B49: =Cap_12!$B$19+$B$47 -> 11400 | C49: unità | D49: 11400 | E49: =IF(ABS(B49-D49)<=0.5,"OK","DIVERSO") -> OK | F49: capitolo 13
A50: Produzione linea C | B50: =Cap_12!$B$21+$B$47 -> 2100 | C50: unità | D50: 2100 | E50: =IF(ABS(B50-D50)<=0.5,"OK","DIVERSO") -> OK | F50: capitolo 13
A51: Produzione totale | B51: =$B$48+$B$49+$B$50 -> 21500 | C51: unità | D51: 21500 | E51: =IF(ABS(B51-D51)<=0.5,"OK","DIVERSO") -> OK | F51: capitolo 13
A52: Ore macchina linea A | B52: =$B$48*Impresa_guida!$B$11 -> 12000 | C52: ore | D52: 12000 | E52: =IF(ABS(B52-D52)<=0.5,"OK","DIVERSO") -> OK | F52: capitolo 13
A53: Ore macchina linea B | B53: =$B$49*Impresa_guida!$B$15 -> 5700 | C53: ore | D53: 5700 | E53: =IF(ABS(B53-D53)<=0.5,"OK","DIVERSO") -> OK | F53: capitolo 13
A54: Ore macchina linea C | B54: =$B$50*Impresa_guida!$B$19 -> 6300 | C54: ore | D54: 6300 | E54: =IF(ABS(B54-D54)<=0.5,"OK","DIVERSO") -> OK | F54: capitolo 13
A55: Ore macchina richieste | B55: =$B$52+$B$53+$B$54 -> 24000 | C55: ore | D55: 24000 | E55: =IF(ABS(B55-D55)<=0.5,"OK","DIVERSO") -> OK | F55: capitolo 13
A56: Controllo ore contro capitolo 12 | B56: =IF(ABS($B$55-Cap_12!$B$31)<0.01,"Quadra","Non quadra") -> Quadra | D56: Quadra | E56: =IF(B56=D56,"OK","DIVERSO") -> OK | F56: capitolo 13
A57: Ricavi di budget (capitolo 12) | B57: =Cap_12!$B$28 -> 3392100 | C57: euro | D57: 3392100 | E57: =IF(ABS(B57-D57)<=0.5,"OK","DIVERSO") -> OK | F57: capitolo 13
A58: Costi della struttura (capitolo 12) | B58: =Cap_12!$B$34 -> 820000 | C58: euro | D58: 820000 | E58: =IF(ABS(B58-D58)<=0.5,"OK","DIVERSO") -> OK | F58: capitolo 13
A60: Budget di marzo e capacità mensile
A61: Catena dal volume alla capacità sul mese di marzo, scorte invariate; capitolo 13 e paragrafo 19.5
A62: Voce | B62: Valore | C62: Unità | D62: Valore atteso (libro) | E62: Controllo | F62: Fonte nel libro
A63: Capacità ordinaria mensile | B63: =Impresa_guida!$B$26/12 -> 1750 | C63: ore | D63: 1750 | E63: =IF(ABS(B63-D63)<=0.5,"OK","DIVERSO") -> OK | F63: capitolo 13
A64: Marzo - unità linea A | B64: 600 | C64: unità | F64: capitolo 13
A65: Marzo - unità linea B | B65: 1000 | C65: unità | F65: capitolo 13
A66: Marzo - unità linea C | B66: 200 | C66: unità | F66: capitolo 13
A67: Marzo - unità vendute e prodotte | B67: =$B$64+$B$65+$B$66 -> 1800 | C67: unità | D67: 1800 | E67: =IF(ABS(B67-D67)<=0.5,"OK","DIVERSO") -> OK | F67: capitolo 13
A68: Marzo - ricavi di budget | B68: =$B$64*Cap_12!$B$18+$B$65*Cap_12!$B$20+$B$66*Cap_12!$B$22 -> 283800 | C68: euro | D68: 283800 | E68: =IF(ABS(B68-D68)<=0.5,"OK","DIVERSO") -> OK | F68: capitolo 13
A69: Marzo - ore linea A | B69: =$B$64*Impresa_guida!$B$11 -> 900 | C69: ore | D69: 900 | E69: =IF(ABS(B69-D69)<=0.5,"OK","DIVERSO") -> OK | F69: capitolo 13
A70: Marzo - ore linea B | B70: =$B$65*Impresa_guida!$B$15 -> 500 | C70: ore | D70: 500 | E70: =IF(ABS(B70-D70)<=0.5,"OK","DIVERSO") -> OK | F70: capitolo 13
A71: Marzo - ore linea C | B71: =$B$66*Impresa_guida!$B$19 -> 600 | C71: ore | D71: 600 | E71: =IF(ABS(B71-D71)<=0.5,"OK","DIVERSO") -> OK | F71: capitolo 13
A72: Marzo - ore macchina richieste | B72: =$B$69+$B$70+$B$71 -> 2000 | C72: ore | D72: 2000 | E72: =IF(ABS(B72-D72)<=0.5,"OK","DIVERSO") -> OK | F72: capitolo 13
A73: Marzo - ore da acquistare all'esterno | B73: =MAX($B$72-$B$63,0) -> 250 | C73: ore | D73: 250 | E73: =IF(ABS(B73-D73)<=0.5,"OK","DIVERSO") -> OK | F73: capitolo 13
A74: Marzo - costo della capacità esterna | B74: =$B$73*Impresa_guida!$B$27 -> 7000 | C74: euro | D74: 7000 | E74: =IF(ABS(B74-D74)<=0.5,"OK","DIVERSO") -> OK | F74: capitolo 13
A75: Marzo - struttura base (calendario di budget) | B75: 62200 | C75: euro | F75: capitolo 13
A76: Marzo - costi della struttura | B76: =$B$75+$B$74 -> 69200 | C76: euro | D76: 69200 | E76: =IF(ABS(B76-D76)<=0.5,"OK","DIVERSO") -> OK | F76: capitolo 13
A78: Politica di scorta: 100 unità di C in più
A79: Effetti di una scorta finale di C superiore di 100 unità, lettura a margine; capitolo 13
A80: Voce | B80: Valore | C80: Unità | D80: Valore atteso (libro) | E80: Controllo | F80: Fonte nel libro
A81: Aumento della scorta di C (ipotesi del caso) | B81: 100 | C81: unità | F81: capitolo 13
A82: Produzione di C | B82: =Cap_12!$B$21+$B$81 -> 2200 | C82: unità | D82: 2200 | E82: =IF(ABS(B82-D82)<=0.5,"OK","DIVERSO") -> OK | F82: capitolo 13
A83: Ore macchina | B83: =Cap_12!$B$31+$B$81*Impresa_guida!$B$19 -> 24300 | C83: ore | D83: 24300 | E83: =IF(ABS(B83-D83)<=0.5,"OK","DIVERSO") -> OK | F83: capitolo 13
A84: Ore esterne | B84: =MAX($B$83-Impresa_guida!$B$26,0) -> 3300 | C84: ore | D84: 3300 | E84: =IF(ABS(B84-D84)<=0.5,"OK","DIVERSO") -> OK | F84: capitolo 13
A85: Capacità esterna in più | B85: =($B$84-Cap_12!$B$32)*Impresa_guida!$B$27 -> 8400 | C85: euro | D85: 8400 | E85: =IF(ABS(B85-D85)<=0.5,"OK","DIVERSO") -> OK | F85: capitolo 13
A86: Costi variabili delle 100 unità | B86: =$B$81*Impresa_guida!$B$18 -> 23800 | C86: euro | D86: 23800 | E86: =IF(ABS(B86-D86)<=0.5,"OK","DIVERSO") -> OK | F86: capitolo 13
A87: Uscita di cassa prima della vendita | B87: =$B$85+$B$86 -> 32200 | C87: euro | D87: 32200 | E87: =IF(ABS(B87-D87)<=0.5,"OK","DIVERSO") -> OK | F87: capitolo 13
A88: Risultato operativo a margine | B88: =Cap_12!$B$35-$B$85 -> 261500 | C88: euro | D88: 261500 | E88: =IF(ABS(B88-D88)<=0.5,"OK","DIVERSO") -> OK | F88: capitolo 13
A90: Politica di scorta: lettura a costo pieno
A91: Costo industriale delle 100 unità, costi fissi rinviati e riconciliazione con il prospetto a margine (coefficiente del capitolo 7); capitolo 13
A92: Voce | B92: Valore | C92: Unità | D92: Valore atteso (libro) | E92: Controllo | F92: Fonte nel libro
A93: Costi indiretti di produzione per ora macchina | B93: =Impresa_guida!$B$24/Impresa_guida!$B$37 -> 5 | C93: euro/ora | D93: 5 | E93: =IF(ABS(B93-D93)<=0.5,"OK","DIVERSO") -> OK | F93: capitolo 13
A94: Costi indiretti per unità di C | B94: =Impresa_guida!$B$19*$B$93 -> 15 | C94: euro/unità | D94: 15 | E94: =IF(ABS(B94-D94)<=0.5,"OK","DIVERSO") -> OK | F94: capitolo 13
A95: Costo industriale unitario di C | B95: =Impresa_guida!$B$18+$B$94 -> 253 | C95: euro/unità | D95: 253 | E95: =IF(ABS(B95-D95)<=0.5,"OK","DIVERSO") -> OK | F95: capitolo 13
A96: Valore delle 100 unità a costo industriale | B96: =$B$81*$B$95 -> 25300 | C96: euro | D96: 25300 | E96: =IF(ABS(B96-D96)<=0.5,"OK","DIVERSO") -> OK | F96: capitolo 13
A97: Costi fissi trattenuti in magazzino | B97: =$B$81*$B$94 -> 1500 | C97: euro | D97: 1500 | E97: =IF(ABS(B97-D97)<=0.5,"OK","DIVERSO") -> OK | F97: capitolo 13
A98: Risultato operativo a costo pieno | B98: =$B$88+$B$97 -> 263000 | C98: euro | D98: 263000 | E98: =IF(ABS(B98-D98)<=0.5,"OK","DIVERSO") -> OK | F98: capitolo 13
A99: Costi indiretti assorbiti a 24.300 ore | B99: =$B$83*$B$93 -> 121500 | C99: euro | D99: 121500 | E99: =IF(ABS(B99-D99)<=0.5,"OK","DIVERSO") -> OK | F99: capitolo 13
A100: Sovrassorbimento | B100: =$B$99-Impresa_guida!$B$24 -> 1500 | C100: euro | D100: 1500 | E100: =IF(ABS(B100-D100)<=0.5,"OK","DIVERSO") -> OK | F100: capitolo 13
A102: Verifica del doppio conteggio
A103: La capacità esterna entra una sola volta nei costi della struttura; errore se sommata due volte; capitolo 13
A104: Voce | B104: Valore | C104: Unità | D104: Valore atteso (libro) | E104: Controllo | F104: Fonte nel libro
A105: Struttura con capacità esterna contata due volte | B105: =Cap_12!$B$34+Cap_12!$B$33 -> 904000 | C105: euro | D105: 904000 | E105: =IF(ABS(B105-D105)<=0.5,"OK","DIVERSO") -> OK | F105: capitolo 13
A106: Risultato con il doppio conteggio | B106: =Cap_12!$B$30-$B$105 -> 185900 | C106: euro | D106: 185900 | E106: =IF(ABS(B106-D106)<=0.5,"OK","DIVERSO") -> OK | F106: capitolo 13
A108: Cassa del budget
A109: Raccordo dal risultato operativo al flusso di cassa, con crediti e debiti invariati e investimenti pari agli ammortamenti; capitolo 13
...

Sheet Cap_14
A1: Capitolo 14 - Budget, consuntivo e analisi degli scostamenti
A2: Controllo di gestione con l'intelligenza artificiale - file Excel che accompagna il libro
A3: Celle blu su fondo giallo: dati da cambiare. Celle nere: formule. «Valore atteso (libro)» e «Controllo» confrontano il calcolo con il numero stampato nel libro.
A4: Budget flessibile e scostamenti: il caso completo del capitolo e il ponte di marzo dell'impresa guida, a margine e a costo pieno.
A6: Budget flessibile dei materiali (esempio)
A7: Budget statico, flessibile e consuntivo del costo dei materiali; capitolo 14
A8: Voce | B8: Valore | C8: Unità | D8: Valore atteso (libro) | E8: Controllo | F8: Fonte nel libro
A9: Unità di budget | B9: 10000 | C9: unità | F9: capitolo 14
A10: Unità effettive | B10: 11000 | C10: unità | F10: capitolo 14
A11: Costo standard materiale per unità | B11: 6 | C11: euro/unità | F11: capitolo 14
A12: Costo materiali consuntivo | B12: 68200 | C12: euro | F12: capitolo 14
A13: Budget statico materiali | B13: =$B$9*$B$11 -> 60000 | C13: euro | D13: 60000 | E13: =IF(ABS(B13-D13)<=0.5,"OK","DIVERSO") -> OK | F13: capitolo 14
A14: Budget flessibile materiali | B14: =$B$10*$B$11 -> 66000 | C14: euro | D14: 66000 | E14: =IF(ABS(B14-D14)<=0.5,"OK","DIVERSO") -> OK | F14: capitolo 14
A15: Effetto volume (non F né S) | B15: =$B$14-$B$13 -> 6000 | C15: euro | D15: 6000 | E15: =IF(ABS(B15-D15)<=0.5,"OK","DIVERSO") -> OK | F15: capitolo 14
A16: Scostamento operativo (maggior costo, S) | B16: =$B$12-$B$14 -> 2200 | C16: euro | D16: 2200 | E16: =IF(ABS(B16-D16)<=0.5,"OK","DIVERSO") -> OK | F16: capitolo 14
A17: Confronto diretto statico-consuntivo | B17: =$B$12-$B$13 -> 8200 | C17: euro | D17: 8200 | E17: =IF(ABS(B17-D17)<=0.5,"OK","DIVERSO") -> OK | F17: capitolo 14
A19: Ponte del risultato (esempio)
A20: Dal risultato di budget al consuntivo per effetti, come impatto sul risultato; capitolo 14, tabella
A21: Voce | B21: Valore | C21: Unità | D21: Valore atteso (libro) | E21: Controllo | F21: Fonte nel libro
A22: Risultato di budget | B22: 120000 | C22: euro | F22: capitolo 14
A23: Volume | B23: 25000 | C23: euro | F23: capitolo 14
A24: Mix | B24: -12000 | C24: euro | F24: capitolo 14
A25: Prezzo | B25: -18000 | C25: euro | F25: capitolo 14
A26: Materiali | B26: -9000 | C26: euro | F26: capitolo 14
A27: Efficienza | B27: 6000 | C27: euro | F27: capitolo 14
A28: Struttura | B28: -7000 | C28: euro | F28: capitolo 14
A29: Risultato consuntivo | B29: =$B$22+$B$23+$B$24+$B$25+$B$26+$B$27+$B$28 -> 105000 | C29: euro | D29: 105000 | E29: =IF(ABS(B29-D29)<=0.5,"OK","DIVERSO") -> OK | F29: capitolo 14
A31: Caso completo: dati
A32: Standard di budget e consuntivo; unità e costo standard materiale dal primo blocco; capitolo 14
A33: Voce | B33: Valore | C33: Unità | D33: Valore atteso (libro) | E33: Controllo | F33: Fonte nel libro
A34: Prezzo di budget | B34: 25 | C34: euro/unità | F34: capitolo 14
A35: Kg standard per unità | B35: 2 | C35: kg/unità | F35: capitolo 14
A36: Prezzo standard per kg | B36: 3 | C36: euro/kg | F36: capitolo 14
A37: Ore standard per unità | B37: 0.25 | C37: ore/unità | F37: capitolo 14
A38: Tariffa standard | B38: 24 | C38: euro/ora | F38: capitolo 14
A39: Costi fissi di budget | B39: 80000 | C39: euro | F39: capitolo 14
A40: Prezzo effettivo | B40: 24.5 | C40: euro/unità | F40: capitolo 14
A41: Kg consumati | B41: 24800 | C41: kg | F41: capitolo 14
A42: Prezzo effettivo per kg | B42: 2.75 | C42: euro/kg | F42: capitolo 14
A43: Ore lavorate | B43: 2900 | C43: ore | F43: capitolo 14
A44: Tariffa effettiva | B44: 25 | C44: euro/ora | F44: capitolo 14
A45: Costi fissi effettivi | B45: 82000 | C45: euro | F45: capitolo 14
A46: Margine unitario di budget | B46: =$B$34-$B$35*$B$36-$B$37*$B$38 -> 13 | C46: euro/unità | D46: 13 | E46: =IF(ABS(B46-D46)<=0.5,"OK","DIVERSO") -> OK | F46: capitolo 14
A48: Caso completo: statico, flessibile, consuntivo
A49: I tre prospetti affiancati; capitolo 14
A50: Voce | B50: Valore | C50: Unità | D50: Valore atteso (libro) | E50: Controllo | F50: Fonte nel libro
A51: Ricavi - budget statico | B51: =$B$9*$B$34 -> 250000 | C51: euro | D51: 250000 | E51: =IF(ABS(B51-D51)<=0.5,"OK","DIVERSO") -> OK | F51: capitolo 14
A52: Lavoro diretto - budget statico | B52: =$B$9*$B$37*$B$38 -> 60000 | C52: euro | D52: 60000 | E52: =IF(ABS(B52-D52)<=0.5,"OK","DIVERSO") -> OK | F52: capitolo 14
A53: Margine - budget statico | B53: =$B$51-$B$13-$B$52 -> 130000 | C53: euro | D53: 130000 | E53: =IF(ABS(B53-D53)<=0.5,"OK","DIVERSO") -> OK | F53: capitolo 14
A54: Risultato - budget statico | B54: =$B$53-$B$39 -> 50000 | C54: euro | D54: 50000 | E54: =IF(ABS(B54-D54)<=0.5,"OK","DIVERSO") -> OK | F54: capitolo 14
A55: Ricavi - budget flessibile | B55: =$B$10*$B$34 -> 275000 | C55: euro | D55: 275000 | E55: =IF(ABS(B55-D55)<=0.5,"OK","DIVERSO") -> OK | F55: capitolo 14
A56: Lavoro diretto - budget flessibile | B56: =$B$10*$B$37*$B$38 -> 66000 | C56: euro | D56: 66000 | E56: =IF(ABS(B56-D56)<=0.5,"OK","DIVERSO") -> OK | F56: capitolo 14
A57: Margine - budget flessibile | B57: =$B$55-$B$14-$B$56 -> 143000 | C57: euro | D57: 143000 | E57: =IF(ABS(B57-D57)<=0.5,"OK","DIVERSO") -> OK | F57: capitolo 14
A58: Risultato - budget flessibile | B58: =$B$57-$B$39 -> 63000 | C58: euro | D58: 63000 | E58: =IF(ABS(B58-D58)<=0.5,"OK","DIVERSO") -> OK | F58: capitolo 14
A59: Ricavi - consuntivo | B59: =$B$10*$B$40 -> 269500 | C59: euro | D59: 269500 | E59: =IF(ABS(B59-D59)<=0.5,"OK","DIVERSO") -> OK | F59: capitolo 14
A60: Materiali - consuntivo | B60: =$B$41*$B$42 -> 68200 | C60: euro | D60: 68200 | E60: =IF(ABS(B60-D60)<=0.5,"OK","DIVERSO") -> OK | F60: capitolo 14
A61: Lavoro diretto - consuntivo | B61: =$B$43*$B$44 -> 72500 | C61: euro | D61: 72500 | E61: =IF(ABS(B61-D61)<=0.5,"OK","DIVERSO") -> OK | F61: capitolo 14
A62: Margine - consuntivo | B62: =$B$59-$B$60-$B$61 -> 128800 | C62: euro | D62: 128800 | E62: =IF(ABS(B62-D62)<=0.5,"OK","DIVERSO") -> OK | F62: capitolo 14
A63: Risultato - consuntivo | B63: =$B$62-$B$45 -> 46800 | C63: euro | D63: 46800 | E63: =IF(ABS(B63-D63)<=0.5,"OK","DIVERSO") -> OK | F63: capitolo 14
A65: Caso completo: scostamenti
A66: Ogni scostamento come impatto sul risultato; capitolo 14, tabella
A67: Voce | B67: Valore | C67: Unità | D67: Valore atteso (libro) | E67: Controllo | F67: Fonte nel libro
A68: Kg standard ammessi | B68: =$B$10*$B$35 -> 22000 | C68: kg | D68: 22000 | E68: =IF(ABS(B68-D68)<=0.5,"OK","DIVERSO") -> OK | F68: capitolo 14
A69: Ore standard ammesse | B69: =$B$10*$B$37 -> 2750 | C69: ore | D69: 2750 | E69: =IF(ABS(B69-D69)<=0.5,"OK","DIVERSO") -> OK | F69: capitolo 14
A70: Volume | B70: =($B$10-$B$9)*$B$46 -> 13000 | C70: euro | D70: 13000 | E70: =IF(ABS(B70-D70)<=0.5,"OK","DIVERSO") -> OK | F70: capitolo 14
A71: Prezzo di vendita | B71: =($B$40-$B$34)*$B$10 -> -5500 | C71: euro | D71: -5500 | E71: =IF(ABS(B71-D71)<=0.5,"OK","DIVERSO") -> OK | F71: capitolo 14
A72: Prezzo materiali | B72: =-($B$42-$B$36)*$B$41 -> 6200 | C72: euro | D72: 6200 | E72: =IF(ABS(B72-D72)<=0.5,"OK","DIVERSO") -> OK | F72: capitolo 14
A73: Impiego materiali | B73: =-($B$41-$B$68)*$B$36 -> -8400 | C73: euro | D73: -8400 | E73: =IF(ABS(B73-D73)<=0.5,"OK","DIVERSO") -> OK | F73: capitolo 14
A74: Tariffa lavoro | B74: =-($B$44-$B$38)*$B$43 -> -2900 | C74: euro | D74: -2900 | E74: =IF(ABS(B74-D74)<=0.5,"OK","DIVERSO") -> OK | F74: capitolo 14
A75: Efficienza lavoro | B75: =-($B$43-$B$69)*$B$38 -> -3600 | C75: euro | D75: -3600 | E75: =IF(ABS(B75-D75)<=0.5,"OK","DIVERSO") -> OK | F75: capitolo 14
A76: Spesa costi fissi | B76: =-($B$45-$B$39) -> -2000 | C76: euro | D76: -2000 | E76: =IF(ABS(B76-D76)<=0.5,"OK","DIVERSO") -> OK | F76: capitolo 14
A77: Totale scostamenti | B77: =$B$70+$B$71+$B$72+$B$73+$B$74+$B$75+$B$76 -> -3200 | C77: euro | D77: -3200 | E77: =IF(ABS(B77-D77)<=0.5,"OK","DIVERSO") -> OK | F77: capitolo 14
A78: Controllo: totale = consuntivo - statico | B78: =IF(ABS($B$77-($B$63-$B$54))<0.01,"Quadra","Non quadra") -> Quadra | D78: Quadra | E78: =IF(B78=D78,"OK","DIVERSO") -> OK | F78: capitolo 14
A79: Effetti sottratti al volume | B79: =$B$77-$B$70 -> -16200 | C79: euro | D79: -16200 | E79: =IF(ABS(B79-D79)<=0.5,"OK","DIVERSO") -> OK | F79: capitolo 14
A81: Impresa guida: marzo, budget e consuntivo
A82: Budget di marzo (dal capitolo 13) e consuntivo; margini unitari di budget; capitolo 14, paragrafo 19.5
A83: Voce | B83: Valore | C83: Unità | D83: Valore atteso (libro) | E83: Controllo | F83: Fonte nel libro
A84: Margine unitario di budget A | B84: =Cap_12!$B$18-Impresa_guida!$B$10 -> 63 | C84: euro/unità | D84: 63 | E84: =IF(ABS(B84-D84)<=0.5,"OK","DIVERSO") -> OK | F84: capitolo 14
A85: Margine unitario di budget B | B85: =Cap_12!$B$20-Impresa_guida!$B$14 -> 42 | C85: euro/unità | D85: 42 | E85: =IF(ABS(B85-D85)<=0.5,"OK","DIVERSO") -> OK | F85: capitolo 14
A86: Margine unitario di budget C | B86: =Cap_12!$B$22-Impresa_guida!$B$18 -> 51 | C86: euro/unità | D86: 51 | E86: =IF(ABS(B86-D86)<=0.5,"OK","DIVERSO") -> OK | F86: capitolo 14
A87: Budget marzo - margine | B87: =Cap_13!$B$64*$B$84+Cap_13!$B$65*$B$85+Cap_13!$B$66*$B$86 -> 90000 | C87: euro | D87: 90000 | E87: =IF(ABS(B87-D87)<=0.5,"OK","DIVERSO") -> OK | F87: capitolo 14
A88: Budget marzo - risultato operativo | B88: =$B$87-Cap_13!$B$76 -> 20800 | C88: euro | D88: 20800 | E88: =IF(ABS(B88-D88)<=0.5,"OK","DIVERSO") -> OK | F88: capitolo 14
A89: Consuntivo marzo - unità A | B89: 600 | C89: unità | F89: capitolo 14
A90: Consuntivo marzo - unità B | B90: 1100 | C90: unità | F90: capitolo 14
A91: Consuntivo marzo - unità C | B91: 170 | C91: unità | F91: capitolo 14
A92: Consuntivo marzo - prezzo B | B92: 114 | C92: euro/unità | F92: capitolo 14
A93: Consuntivo marzo - costo variabile A | B93: 117 | C93: euro/unità | F93: capitolo 14
A94: Consuntivo marzo - costo variabile B | B94: 76 | C94: euro/unità | F94: capitolo 14
A95: Consuntivo marzo - costo variabile C | B95: 238 | C95: euro/unità | F95: capitolo 14
A96: Consuntivo marzo - costo capacità esterna | B96: 5516 | C96: euro | F96: capitolo 14
A97: Consuntivo marzo - struttura base | B97: 62884 | C97: euro | F97: capitolo 14
A98: Consuntivo marzo - unità | B98: =$B$89+$B$90+$B$91 -> 1870 | C98: unità | D98: 1870 | E98: =IF(ABS(B98-D98)<=0.5,"OK","DIVERSO") -> OK | F98: capitolo 14
A99: Consuntivo marzo - ricavi | B99: =$B$89*Cap_12!$B$18+$B$90*$B$92+$B$91*Cap_12!$B$22 -> 282530 | C99: euro | D99: 282530 | E99: =IF(ABS(B99-D99)<=0.5,"OK","DIVERSO") -> OK | F99: capitolo 14
A100: Consuntivo marzo - margine | B100: =$B$89*(Cap_12!$B$18-$B$93)+$B$90*($B$92-$B$94)+$B$91*(Cap_12!$B$22-$B$95) -> 88270 | C100: euro | D100: 88270 | E100: =IF(ABS(B100-D100)<=0.5,"OK","DIVERSO") -> OK | F100: capitolo 14
A101: Consuntivo marzo - costi della struttura | B101: =$B$97+$B$96 -> 68400 | C101: euro | D101: 68400 | E101: =IF(ABS(B101-D101)<=0.5,"OK","DIVERSO") -> OK | F101: capitolo 14
A102: Consuntivo marzo - risultato operativo | B102: =$B$100-$B$101 -> 19870 | C102: euro | D102: 19870 | E102: =IF(ABS(B102-D102)<=0.5,"OK","DIVERSO") -> OK | F102: capitolo 14
A103: Scostamento del risultato | B103: =$B$102-$B$88 -> -930 | C103: euro | D103: -930 | E103: =IF(ABS(B103-D103)<=0.5,"OK","DIVERSO") -> OK | F103: capitolo 14
A104: Scostamento del margine | B104: =$B$100-$B$87 -> -1730 | C104: euro | D104: -1730 | E104: =IF(ABS(B104-D104)<=0.5,"OK","DIVERSO") -> OK | F104: paragrafo 19.5
A105: Margine percentuale di budget | B105: =$B$87/Cap_13!$B$68 -> 0.31712474 | C105: % | D105: 0.317 | E105: =IF(ABS(B105-D105)<=0.0005,"OK","DIVERSO") -> OK | F105: paragrafo 19.5
A106: Margine percentuale consuntivo | B106: =$B$100/$B$99 -> 0.312427 | C106: % | D106: 0.312 | E106: =IF(ABS(B106-D106)<=0.0005,"OK","DIVERSO") -> OK | F106: paragrafo 19.5
...

Sheet Cap_15
A1: Capitolo 15 - Costi rilevanti e decisioni
A2: Controllo di gestione con l'intelligenza artificiale - file Excel che accompagna il libro
A3: Celle blu su fondo giallo: dati da cambiare. Celle nere: formule. «Valore atteso (libro)» e «Controllo» confrontano il calcolo con il numero stampato nel libro.
A4: Risultato differenziale, VAN e TIR, punti di indifferenza e le tre alternative per la linea C dell'impresa guida.
A6: Risultato differenziale di un ordine aggiuntivo
A7: Ricavi differenziali meno costi differenziali; ammortamenti e struttura esistente restano fuori; capitolo 15
A8: Voce | B8: Valore | C8: Unità | D8: Valore atteso (libro) | E8: Controllo | F8: Fonte nel libro
A9: Ricavi dell'ordine | B9: 50000 | C9: euro | F9: capitolo 15
A10: Materiali e lavorazioni | B10: 28000 | C10: euro | F10: capitolo 15
A11: Trasporto dedicato | B11: 5000 | C11: euro | F11: capitolo 15
A12: Straordinari | B12: 4000 | C12: euro | F12: capitolo 15
A13: Risultato differenziale | B13: =$B$9-$B$10-$B$11-$B$12 -> 13000 | C13: euro | D13: 13000 | E13: =IF(ABS(B13-D13)<=0.5,"OK","DIVERSO") -> OK | F13: capitolo 15
A15: VAN dell'impianto con scorte aggiuntive
A16: Flussi differenziali per anno, fattori all'8%, VAN e TIR; ammortamenti esclusi; capitolo 15
A17: Voce | B17: Valore | C17: Unità | D17: Valore atteso (libro) | E17: Controllo | F17: Fonte nel libro
A18: Costo dell'impianto | B18: 200000 | C18: euro | F18: capitolo 15
A19: Riduzione annua dei costi operativi | B19: 55000 | C19: euro | F19: capitolo 15
A20: Scorte aggiuntive (pagate all'avvio, recuperate alla fine) | B20: 30000 | C20: euro | F20: capitolo 15
A21: Valore di cessione al quinto anno | B21: 20000 | C21: euro | F21: capitolo 15
A22: Tasso richiesto | B22: 0.08 | C22: % | F22: capitolo 15
A23: Flusso anno 0 | B23: =-($B$18+$B$20) -> -230000 | C23: euro | D23: -230000 | E23: =IF(ABS(B23-D23)<=0.5,"OK","DIVERSO") -> OK | F23: capitolo 15
A24: Flusso anno 1 | B24: =$B$19 -> 55000 | C24: euro | D24: 55000 | E24: =IF(ABS(B24-D24)<=0.5,"OK","DIVERSO") -> OK | F24: capitolo 15
A25: Flusso anno 2 | B25: =$B$19 -> 55000 | C25: euro | D25: 55000 | E25: =IF(ABS(B25-D25)<=0.5,"OK","DIVERSO") -> OK | F25: capitolo 15
A26: Flusso anno 3 | B26: =$B$19 -> 55000 | C26: euro | D26: 55000 | E26: =IF(ABS(B26-D26)<=0.5,"OK","DIVERSO") -> OK | F26: capitolo 15
A27: Flusso anno 4 | B27: =$B$19 -> 55000 | C27: euro | D27: 55000 | E27: =IF(ABS(B27-D27)<=0.5,"OK","DIVERSO") -> OK | F27: capitolo 15
A28: Flusso anno 5 | B28: =$B$19+$B$21+$B$20 -> 105000 | C28: euro | D28: 105000 | E28: =IF(ABS(B28-D28)<=0.5,"OK","DIVERSO") -> OK | F28: capitolo 15
A29: Fattore di attualizzazione anno 1 | B29: =1/(1+$B$22)^1 -> 0.92592593 | C29: volte | D29: 0.9259 | E29: =IF(ABS(B29-D29)<=0.00005,"OK","DIVERSO") -> OK | F29: capitolo 15
A30: Fattore di attualizzazione anno 2 | B30: =1/(1+$B$22)^2 -> 0.85733882 | C30: volte | D30: 0.8573 | E30: =IF(ABS(B30-D30)<=0.00005,"OK","DIVERSO") -> OK | F30: capitolo 15
A31: Fattore di attualizzazione anno 3 | B31: =1/(1+$B$22)^3 -> 0.79383224 | C31: volte | D31: 0.7938 | E31: =IF(ABS(B31-D31)<=0.00005,"OK","DIVERSO") -> OK | F31: capitolo 15
A32: Fattore di attualizzazione anno 4 | B32: =1/(1+$B$22)^4 -> 0.73502985 | C32: volte | D32: 0.735 | E32: =IF(ABS(B32-D32)<=0.00005,"OK","DIVERSO") -> OK | F32: capitolo 15
A33: Fattore di attualizzazione anno 5 | B33: =1/(1+$B$22)^5 -> 0.6805832 | C33: volte | D33: 0.6806 | E33: =IF(ABS(B33-D33)<=0.00005,"OK","DIVERSO") -> OK | F33: capitolo 15
A34: Valore attuale anno 1 | B34: =$B$24*$B$29 -> 50925.926 | C34: euro | D34: 50926 | E34: =IF(ABS(B34-D34)<=0.5,"OK","DIVERSO") -> OK | F34: capitolo 15
A35: Valore attuale anno 2 | B35: =$B$25*$B$30 -> 47153.635 | C35: euro | D35: 47154 | E35: =IF(ABS(B35-D35)<=0.5,"OK","DIVERSO") -> OK | F35: capitolo 15
A36: Valore attuale anno 3 | B36: =$B$26*$B$31 -> 43660.773 | C36: euro | D36: 43661 | E36: =IF(ABS(B36-D36)<=0.5,"OK","DIVERSO") -> OK | F36: capitolo 15
A37: Valore attuale anno 4 | B37: =$B$27*$B$32 -> 40426.642 | C37: euro | D37: 40427 | E37: =IF(ABS(B37-D37)<=0.5,"OK","DIVERSO") -> OK | F37: capitolo 15
A38: Valore attuale anno 5 | B38: =$B$28*$B$33 -> 71461.236 | C38: euro | D38: 71461 | E38: =IF(ABS(B38-D38)<=0.5,"OK","DIVERSO") -> OK | F38: capitolo 15
A39: VAN | B39: =$B$23+NPV($B$22,$B$24,$B$25,$B$26,$B$27,$B$28) -> 23628.212 | C39: euro | D39: 23628 | E39: =IF(ABS(B39-D39)<=0.5,"OK","DIVERSO") -> OK | F39: capitolo 15
A40: Somma dei valori attuali arrotondati all'euro | B40: =$B$23+ROUND($B$34,0)+ROUND($B$35,0)+ROUND($B$36,0)+ROUND($B$37,0)+ROUND($B$38,0) -> 23629 | C40: euro | D40: 23629 | E40: =IF(ABS(B40-D40)<=0.5,"OK","DIVERSO") -> OK | F40: capitolo 15
A41: TIR | B41: =IRR($B$23:$B$28) -> 0.11461454 | C41: % | D41: 0.115 | E41: =IF(ABS(B41-D41)<=0.0005,"OK","DIVERSO") -> OK | F41: capitolo 15
A43: VAN senza le scorte aggiuntive
A44: Stessi flussi senza capitale circolante: il costo delle scorte è la differenza fra i due VAN; capitolo 15
A45: Voce | B45: Valore | C45: Unità | D45: Valore atteso (libro) | E45: Controllo | F45: Fonte nel libro
A46: Flusso anno 0 senza scorte | B46: =-$B$18 -> -200000 | C46: euro | D46: -200000 | E46: =IF(ABS(B46-D46)<=0.5,"OK","DIVERSO") -> OK | F46: capitolo 15
A47: Flusso anno 1 senza scorte | B47: =$B$19 -> 55000 | C47: euro | F47: capitolo 15
A48: Flusso anno 2 senza scorte | B48: =$B$19 -> 55000 | C48: euro | F48: capitolo 15
A49: Flusso anno 3 senza scorte | B49: =$B$19 -> 55000 | C49: euro | F49: capitolo 15
A50: Flusso anno 4 senza scorte | B50: =$B$19 -> 55000 | C50: euro | F50: capitolo 15
A51: Flusso anno 5 senza scorte | B51: =$B$19+$B$21 -> 75000 | C51: euro | D51: 75000 | E51: =IF(ABS(B51-D51)<=0.5,"OK","DIVERSO") -> OK | F51: capitolo 15
A52: VAN senza scorte | B52: =$B$46+NPV($B$22,$B$47,$B$48,$B$49,$B$50,$B$51) -> 33210.716 | C52: euro | D52: 33211 | E52: =IF(ABS(B52-D52)<=0.5,"OK","DIVERSO") -> OK | F52: capitolo 15
A53: TIR senza scorte | B53: =IRR($B$46:$B$51) -> 0.13841671 | C53: % | D53: 0.138 | E53: =IF(ABS(B53-D53)<=0.0005,"OK","DIVERSO") -> OK | F53: capitolo 15
A54: Costo delle scorte in valore attuale | B54: =$B$52-$B$39 -> 9582.5041 | C54: euro | D54: 9583 | E54: =IF(ABS(B54-D54)<=0.5,"OK","DIVERSO") -> OK | F54: capitolo 15
A56: Punto di indifferenza fra due alternative
A57: Differenza costi fissi / differenza costi variabili unitari; capitolo 15
A58: Voce | B58: Valore | C58: Unità | D58: Valore atteso (libro) | E58: Controllo | F58: Fonte nel libro
A59: Alternativa A - costi fissi | B59: 50000 | C59: euro | F59: capitolo 15
A60: Alternativa A - costo variabile unitario | B60: 12 | C60: euro/unità | F60: capitolo 15
A61: Alternativa B - costi fissi | B61: 80000 | C61: euro | F61: capitolo 15
A62: Alternativa B - costo variabile unitario | B62: 8 | C62: euro/unità | F62: capitolo 15
A63: Differenza costi fissi | B63: =$B$61-$B$59 -> 30000 | C63: euro | D63: 30000 | E63: =IF(ABS(B63-D63)<=0.5,"OK","DIVERSO") -> OK | F63: capitolo 15
A64: Vantaggio variabile di B | B64: =$B$60-$B$62 -> 4 | C64: euro/unità | D64: 4 | E64: =IF(ABS(B64-D64)<=0.5,"OK","DIVERSO") -> OK | F64: capitolo 15
A65: Punto di indifferenza | B65: =$B$63/$B$64 -> 7500 | C65: unità | D65: 7500 | E65: =IF(ABS(B65-D65)<=0.5,"OK","DIVERSO") -> OK | F65: capitolo 15
A66: Volume atteso | B66: 7600 | C66: unità | F66: capitolo 15
A67: Alternativa preferibile al volume atteso | B67: =IF($B$66>$B$65,"B","A") -> B | D67: B | E67: =IF(B67=D67,"OK","DIVERSO") -> OK | F67: capitolo 15
A69: Eliminare un prodotto
A70: Margine perso contro costi fissi evitabili; i costi comuni allocati restano; capitolo 15
A71: Voce | B71: Valore | C71: Unità | D71: Valore atteso (libro) | E71: Controllo | F71: Fonte nel libro
A72: Margine del prodotto | B72: 120000 | C72: euro | F72: capitolo 15
A73: Costi fissi specifici evitabili | B73: 80000 | C73: euro | F73: capitolo 15
A74: Costi comuni allocati che restano | B74: 70000 | C74: euro | F74: capitolo 15
A75: Contributo alla struttura comune (riduzione del risultato se eliminato) | B75: =$B$72-$B$73 -> 40000 | C75: euro | D75: 40000 | E75: =IF(ABS(B75-D75)<=0.5,"OK","DIVERSO") -> OK | F75: capitolo 15
A76: Risultato pieno del prodotto | B76: =$B$75-$B$74 -> -30000 | C76: euro | F76: capitolo 15
A78: Impresa guida - la linea C nel prospetto a costo pieno
A79: Quote allocate alla linea C nel prospetto del capitolo 7 e quota della capacità esterna; capitolo 15
A80: Voce | B80: Valore | C80: Unità | D80: Valore atteso (libro) | E80: Controllo | F80: Fonte nel libro
A81: Coefficiente costi indiretti per ora macchina | B81: =Impresa_guida!$B$24/Impresa_guida!$B$37 -> 5 | C81: euro/ora | D81: 5 | E81: =IF(ABS(B81-D81)<=0.5,"OK","DIVERSO") -> OK | F81: capitolo 16
A82: Costi indiretti di produzione allocati a C | B82: =$B$81*Impresa_guida!$B$16*Impresa_guida!$B$19 -> 30000 | C82: euro | D82: 30000 | E82: =IF(ABS(B82-D82)<=0.5,"OK","DIVERSO") -> OK | F82: capitolo 15
A83: Struttura ripartita sui ricavi a C | B83: =(Impresa_guida!$B$41-Impresa_guida!$B$24)*Impresa_guida!$B$33/Impresa_guida!$B$34 -> 119492.03 | C83: euro | D83: 119492 | E83: =IF(ABS(B83-D83)<=0.5,"OK","DIVERSO") -> OK | F83: capitolo 15
A84: Risultato pieno della linea C | B84: =Impresa_guida!$B$33-Impresa_guida!$B$16*Impresa_guida!$B$18-$B$82-$B$83 -> -47492.026 | C84: euro | D84: -47492 | E84: =IF(ABS(B84-D84)<=0.5,"OK","DIVERSO") -> OK | F84: capitolo 15
A85: Totale allocato alla linea C | B85: =$B$82+$B$83 -> 149492.03 | C85: euro | D85: 149492 | E85: =IF(ABS(B85-D85)<=0.5,"OK","DIVERSO") -> OK | F85: capitolo 15
A86: Quota della capacità esterna assegnata a C | B86: =Impresa_guida!$B$39*Impresa_guida!$B$33/Impresa_guida!$B$34 -> 14339.043 | C86: euro | D86: 14339 | E86: =IF(ABS(B86-D86)<=0.5,"OK","DIVERSO") -> OK | F86: capitolo 15
A87: Ammortamento impianti di reparto (costo sommerso) | B87: =Cap_01!$B$44 -> 74000 | C87: euro | F87: capitolo 15
A89: Impresa guida - margine per ora macchina
A90: Margine unitario e margine per ora di ogni linea; ore richieste da A e B; capitolo 15
A91: Voce | B91: Valore | C91: Unità | D91: Valore atteso (libro) | E91: Controllo | F91: Fonte nel libro
A92: Linea A - margine unitario | B92: =Impresa_guida!$B$9-Impresa_guida!$B$10 -> 63 | C92: euro/unità | D92: 63 | E92: =IF(ABS(B92-D92)<=0.5,"OK","DIVERSO") -> OK | F92: capitolo 15
A93: Linea A - margine per ora | B93: =$B$92/Impresa_guida!$B$11 -> 42 | C93: euro/ora | D93: 42 | E93: =IF(ABS(B93-D93)<=0.5,"OK","DIVERSO") -> OK | F93: capitolo 15
A94: Linea B - margine unitario | B94: =Impresa_guida!$B$13-Impresa_guida!$B$14 -> 38 | C94: euro/unità | D94: 38 | E94: =IF(ABS(B94-D94)<=0.5,"OK","DIVERSO") -> OK | F94: capitolo 15
A95: Linea B - margine per ora | B95: =$B$94/Impresa_guida!$B$15 -> 76 | C95: euro/ora | D95: 76 | E95: =IF(ABS(B95-D95)<=0.5,"OK","DIVERSO") -> OK | F95: capitolo 15
A96: Linea C - margine unitario | B96: =Impresa_guida!$B$17-Impresa_guida!$B$18 -> 51 | C96: euro/unità | D96: 51 | E96: =IF(ABS(B96-D96)<=0.5,"OK","DIVERSO") -> OK | F96: capitolo 15
A97: Linea C - margine per ora | B97: =$B$96/Impresa_guida!$B$19 -> 17 | C97: euro/ora | D97: 17 | E97: =IF(ABS(B97-D97)<=0.5,"OK","DIVERSO") -> OK | F97: capitolo 15
A98: Ore richieste dalla linea A | B98: =Impresa_guida!$B$8*Impresa_guida!$B$11 -> 12000 | C98: ore | D98: 12000 | E98: =IF(ABS(B98-D98)<=0.5,"OK","DIVERSO") -> OK | F98: capitolo 15
A99: Ore richieste dalla linea B | B99: =Impresa_guida!$B$12*Impresa_guida!$B$15 -> 6000 | C99: ore | D99: 6000 | E99: =IF(ABS(B99-D99)<=0.5,"OK","DIVERSO") -> OK | F99: capitolo 15
A100: Volume di C servibile con le ore interne | B100: =(Impresa_guida!$B$26-$B$98-$B$99)/Impresa_guida!$B$19 -> 1000 | C100: unità | D100: 1000 | E100: =IF(ABS(B100-D100)<=0.5,"OK","DIVERSO") -> OK | F100: capitolo 15
A102: Impresa guida - tre alternative per la linea C
A103: Mantenere, eliminare o ridurre la linea C: ore, margine, struttura, capacità esterna, risultato; capitolo 15
A104: Voce | B104: Valore | C104: Unità | D104: Valore atteso (libro) | E104: Controllo | F104: Fonte nel libro
A105: Ore - mantenere C a 2.000 | B105: =Impresa_guida!$B$37 -> 24000 | C105: ore | D105: 24000 | E105: =IF(ABS(B105-D105)<=0.5,"OK","DIVERSO") -> OK | F105: capitolo 15
A106: Ore - eliminare C | B106: =$B$98+$B$99 -> 18000 | C106: ore | D106: 18000 | E106: =IF(ABS(B106-D106)<=0.5,"OK","DIVERSO") -> OK | F106: capitolo 15
A107: Ore - ridurre C a 1.000 | B107: =$B$98+$B$99+$B$100*Impresa_guida!$B$19 -> 21000 | C107: ore | D107: 21000 | E107: =IF(ABS(B107-D107)<=0.5,"OK","DIVERSO") -> OK | F107: capitolo 15
A108: Margine - mantenere | B108: =Impresa_guida!$B$36 -> 1062000 | C108: euro | D108: 1062000 | E108: =IF(ABS(B108-D108)<=0.5,"OK","DIVERSO") -> OK | F108: capitolo 15
...

Sheet Cap_16
A1: Capitolo 16 - Make or Buy
A2: Controllo di gestione con l'intelligenza artificiale - file Excel che accompagna il libro
A3: Celle blu su fondo giallo: dati da cambiare. Celle nere: formule. «Valore atteso (libro)» e «Controllo» confrontano il calcolo con il numero stampato nel libro.
A4: Costo rilevante del Make e del Buy, volume di indifferenza e il turno aggiuntivo dell'impresa guida contro le ore esterne.
A6: Esempio economico Make or Buy
A7: Costo pieno contro costo rilevante: solo 2 dei 6 euro di fissi sono evitabili; capitolo 16
A8: Voce | B8: Valore | C8: Unità | D8: Valore atteso (libro) | E8: Controllo | F8: Fonte nel libro
A9: Quantità | B9: 10000 | C9: unità | F9: capitolo 16
A10: Materiali per unità | B10: 6 | C10: euro/unità | F10: capitolo 16
A11: Lavoro per unità (evitabile) | B11: 4 | C11: euro/unità | F11: capitolo 16
A12: Costi variabili indiretti per unità | B12: 2 | C12: euro/unità | F12: capitolo 16
A13: Costi fissi allocati per unità | B13: 6 | C13: euro/unità | F13: capitolo 16
A14: di cui evitabili per unità | B14: 2 | C14: euro/unità | F14: capitolo 16
A15: Prezzo del fornitore | B15: 14 | C15: euro/unità | F15: capitolo 16
A16: Trasporto e controlli (Buy) | B16: 8000 | C16: euro | F16: capitolo 16
A17: Costo pieno interno per unità | B17: =$B$10+$B$11+$B$12+$B$13 -> 18 | C17: euro/unità | D17: 18 | E17: =IF(ABS(B17-D17)<=0.5,"OK","DIVERSO") -> OK | F17: capitolo 16
A18: Risparmio apparente per unità | B18: =$B$17-$B$15 -> 4 | C18: euro/unità | D18: 4 | E18: =IF(ABS(B18-D18)<=0.5,"OK","DIVERSO") -> OK | F18: capitolo 16
A19: Make - materiali | B19: =$B$9*$B$10 -> 60000 | C19: euro | D19: 60000 | E19: =IF(ABS(B19-D19)<=0.5,"OK","DIVERSO") -> OK | F19: capitolo 16
A20: Make - lavoro evitabile | B20: =$B$9*$B$11 -> 40000 | C20: euro | D20: 40000 | E20: =IF(ABS(B20-D20)<=0.5,"OK","DIVERSO") -> OK | F20: capitolo 16
A21: Make - variabili indiretti | B21: =$B$9*$B$12 -> 20000 | C21: euro | D21: 20000 | E21: =IF(ABS(B21-D21)<=0.5,"OK","DIVERSO") -> OK | F21: capitolo 16
A22: Make - fissi evitabili | B22: =$B$9*$B$14 -> 20000 | C22: euro | D22: 20000 | E22: =IF(ABS(B22-D22)<=0.5,"OK","DIVERSO") -> OK | F22: capitolo 16
A23: Make rilevante totale | B23: =$B$19+$B$20+$B$21+$B$22 -> 140000 | C23: euro | D23: 140000 | E23: =IF(ABS(B23-D23)<=0.5,"OK","DIVERSO") -> OK | F23: capitolo 16
A24: Buy - prezzo fornitore | B24: =$B$9*$B$15 -> 140000 | C24: euro | D24: 140000 | E24: =IF(ABS(B24-D24)<=0.5,"OK","DIVERSO") -> OK | F24: capitolo 16
A25: Buy rilevante totale | B25: =$B$24+$B$16 -> 148000 | C25: euro | D25: 148000 | E25: =IF(ABS(B25-D25)<=0.5,"OK","DIVERSO") -> OK | F25: capitolo 16
A26: Maggior costo del Buy | B26: =$B$25-$B$23 -> 8000 | C26: euro | D26: 8000 | E26: =IF(ABS(B26-D26)<=0.5,"OK","DIVERSO") -> OK | F26: capitolo 16
A27: Costi fissi allocati che restano | B27: =$B$9*($B$13-$B$14) -> 40000 | C27: euro | D27: 40000 | E27: =IF(ABS(B27-D27)<=0.5,"OK","DIVERSO") -> OK | F27: capitolo 16
A28: Scelta senza costo opportunità | B28: =IF($B$23<$B$25,"Make","Buy") -> Make | D28: Make | E28: =IF(B28=D28,"OK","DIVERSO") -> OK | F28: capitolo 16
A30: Volume di indifferenza Make or Buy
A31: Fissi evitabili del Make / (prezzo Buy - variabile Make); capitolo 16
A32: Voce | B32: Valore | C32: Unità | D32: Valore atteso (libro) | E32: Controllo | F32: Fonte nel libro
A33: Make - costi fissi evitabili | B33: 120000 | C33: euro | F33: capitolo 16
A34: Make - costo variabile unitario | B34: 9 | C34: euro/unità | F34: capitolo 16
A35: Buy - prezzo unitario | B35: 15 | C35: euro/unità | F35: capitolo 16
A36: Vantaggio unitario del Make | B36: =$B$35-$B$34 -> 6 | C36: euro/unità | D36: 6 | E36: =IF(ABS(B36-D36)<=0.5,"OK","DIVERSO") -> OK | F36: capitolo 16
A37: Volume di indifferenza | B37: =$B$33/$B$36 -> 20000 | C37: unità | D37: 20000 | E37: =IF(ABS(B37-D37)<=0.5,"OK","DIVERSO") -> OK | F37: capitolo 16
A38: Volume previsto | B38: 25000 | C38: unità | F38: capitolo 16
A39: Vantaggio del Make al volume previsto | B39: =$B$38*$B$36-$B$33 -> 30000 | C39: euro | D39: 30000 | E39: =IF(ABS(B39-D39)<=0.5,"OK","DIVERSO") -> OK | F39: capitolo 16
A41: Impresa guida - turno aggiuntivo contro ore esterne
A42: Make (turno) e Buy (ore esterne a 28 euro) sulle stesse 3.000 ore; ipotesi del caso non presente nel dataset; capitolo 16
A43: Voce | B43: Valore | C43: Unità | D43: Valore atteso (libro) | E43: Controllo | F43: Fonte nel libro
A44: Turno - costi fissi evitabili annui | B44: 36000 | C44: euro | F44: capitolo 16
A45: Turno - costi variabili per ora | B45: 14 | C45: euro/ora | F45: capitolo 16
A46: Ore macchina aggiuntive (Make e Buy) | B46: =Impresa_guida!$B$37-Impresa_guida!$B$26 -> 3000 | C46: ore | D46: 3000 | E46: =IF(ABS(B46-D46)<=0.5,"OK","DIVERSO") -> OK | F46: capitolo 16
A47: Costo rilevante - Make | B47: =$B$44+$B$45*$B$46 -> 78000 | C47: euro | D47: 78000 | E47: =IF(ABS(B47-D47)<=0.5,"OK","DIVERSO") -> OK | F47: capitolo 16
A48: Costo rilevante - Buy | B48: =$B$46*Impresa_guida!$B$27 -> 84000 | C48: euro | D48: 84000 | E48: =IF(ABS(B48-D48)<=0.5,"OK","DIVERSO") -> OK | F48: capitolo 16
A49: Costo per ora - Make | B49: =$B$47/$B$46 -> 26 | C49: euro/ora | D49: 26 | E49: =IF(ABS(B49-D49)<=0.5,"OK","DIVERSO") -> OK | F49: capitolo 16
A50: Costo per ora - Buy | B50: =$B$48/$B$46 -> 28 | C50: euro/ora | D50: 28 | E50: =IF(ABS(B50-D50)<=0.5,"OK","DIVERSO") -> OK | F50: capitolo 16
A51: Margine - Make e Buy | B51: =Impresa_guida!$B$36 -> 1062000 | C51: euro | D51: 1062000 | E51: =IF(ABS(B51-D51)<=0.5,"OK","DIVERSO") -> OK | F51: capitolo 16
A52: Risultato operativo - Make | B52: =$B$51-Impresa_guida!$B$40-$B$47 -> 248000 | C52: euro | D52: 248000 | E52: =IF(ABS(B52-D52)<=0.5,"OK","DIVERSO") -> OK | F52: capitolo 16
A53: Risultato operativo - Buy | B53: =$B$51-Impresa_guida!$B$40-$B$48 -> 242000 | C53: euro | D53: 242000 | E53: =IF(ABS(B53-D53)<=0.5,"OK","DIVERSO") -> OK | F53: capitolo 16
A54: Risultato operativo - rinunciare a 1.000 unità di C | B54: =Cap_15!$B$117 -> 275000 | C54: euro | D54: 275000 | E54: =IF(ABS(B54-D54)<=0.5,"OK","DIVERSO") -> OK | F54: capitolo 16
A55: Vantaggio del Make sul Buy | B55: =$B$48-$B$47 -> 6000 | C55: euro | D55: 6000 | E55: =IF(ABS(B55-D55)<=0.5,"OK","DIVERSO") -> OK | F55: capitolo 16
A57: Impresa guida - il confronto a costo pieno inganna
A58: Caricare sul solo turno la quota di costi indiretti a 5 euro per ora rovescia la scelta; capitolo 16
A59: Voce | B59: Valore | C59: Unità | D59: Valore atteso (libro) | E59: Controllo | F59: Fonte nel libro
A60: Quota costi indiretti sulle 3.000 ore | B60: =Cap_15!$B$81*$B$46 -> 15000 | C60: euro | D60: 15000 | E60: =IF(ABS(B60-D60)<=0.5,"OK","DIVERSO") -> OK | F60: capitolo 16
A61: Make a costo pieno | B61: =$B$47+$B$60 -> 93000 | C61: euro | D61: 93000 | E61: =IF(ABS(B61-D61)<=0.5,"OK","DIVERSO") -> OK | F61: capitolo 16
A62: Maggior costo apparente del Make | B62: =$B$61-$B$48 -> 9000 | C62: euro | D62: 9000 | E62: =IF(ABS(B62-D62)<=0.5,"OK","DIVERSO") -> OK | F62: capitolo 16
A64: Impresa guida - soglie e alternativa di non produrre
A65: Volume di indifferenza in ore, perdita di Make e Buy contro il margine servito, ore necessarie per scendere sotto 17 euro; capitolo 16
A66: Voce | B66: Valore | C66: Unità | D66: Valore atteso (libro) | E66: Controllo | F66: Fonte nel libro
A67: Volume di indifferenza fra turno e ore esterne | B67: =$B$44/(Impresa_guida!$B$27-$B$45) -> 2571.4286 | C67: ore | D67: 2571 | E67: =IF(ABS(B67-D67)<=0.5,"OK","DIVERSO") -> OK | F67: capitolo 16
A68: Margine delle 1.000 unità di C servite | B68: =Cap_15!$B$96*(Impresa_guida!$B$16-Cap_15!$B$100) -> 51000 | C68: euro | D68: 51000 | E68: =IF(ABS(B68-D68)<=0.5,"OK","DIVERSO") -> OK | F68: capitolo 16
A69: Perdita con il turno | B69: =$B$47-$B$68 -> 27000 | C69: euro | D69: 27000 | E69: =IF(ABS(B69-D69)<=0.5,"OK","DIVERSO") -> OK | F69: capitolo 16
A70: Perdita con le ore esterne | B70: =$B$48-$B$68 -> 33000 | C70: euro | D70: 33000 | E70: =IF(ABS(B70-D70)<=0.5,"OK","DIVERSO") -> OK | F70: capitolo 16
A71: Ore oltre le quali il turno costa meno di 17 euro per ora | B71: =$B$44/(Cap_15!$B$128-$B$45) -> 12000 | C71: ore | D71: 12000 | E71: =IF(ABS(B71-D71)<=0.5,"OK","DIVERSO") -> OK | F71: capitolo 16
A72: Soglia rispetto al fabbisogno | B72: =$B$71/$B$46 -> 4 | C72: volte | D72: 4 | E72: =IF(ABS(B72-D72)<=0.5,"OK","DIVERSO") -> OK | F72: capitolo 16
A73: Alternativa migliore | B73: =IF($B$54>MAX($B$52,$B$53),"Rinunciare a 1.000 unità di C",IF($B$52>$B$53,"Make","Buy")) -> Rinunciare a 1.000 unità di C | D73: Rinunciare a 1.000 unità di C | E73: =IF(B73=D73,"OK","DIVERSO") -> OK | F73: capitolo 16

Sheet Cap_17
A1: Capitolo 17 - Pricing
A2: Controllo di gestione con l'intelligenza artificiale - file Excel che accompagna il libro
A3: Celle blu su fondo giallo: dati da cambiare. Celle nere: formule. «Valore atteso (libro)» e «Controllo» confrontano il calcolo con il numero stampato nel libro.
A4: Ricarico e margine, cascata dal listino al prezzo netto, volume dopo uno sconto e prezzi minimi delle tre linee dell'impresa guida.
A6: Cost plus e target costing
A7: Ricarico sul costo e margine sul prezzo non coincidono; il target costing parte dal prezzo; capitolo 17
A8: Voce | B8: Valore | C8: Unità | D8: Valore atteso (libro) | E8: Controllo | F8: Fonte nel libro
A9: Costo | B9: 80 | C9: euro/unità | F9: capitolo 17
A10: Ricarico sul costo | B10: 0.25 | C10: % | F10: capitolo 17
A11: Prezzo con ricarico | B11: =$B$9*(1+$B$10) -> 100 | C11: euro/unità | D11: 100 | E11: =IF(ABS(B11-D11)<=0.5,"OK","DIVERSO") -> OK | F11: capitolo 17
A12: Margine sul prezzo | B12: =($B$11-$B$9)/$B$11 -> 0.2 | C12: % | D12: 0.2 | E12: =IF(ABS(B12-D12)<=0.0005,"OK","DIVERSO") -> OK | F12: capitolo 17
A13: Prezzo di mercato | B13: 100 | C13: euro/unità | F13: capitolo 17
A14: Margine obiettivo sul prezzo | B14: 0.2 | C14: % | F14: capitolo 17
A15: Costo obiettivo | B15: =$B$13*(1-$B$14) -> 80 | C15: euro/unità | D15: 80 | E15: =IF(ABS(B15-D15)<=0.5,"OK","DIVERSO") -> OK | F15: capitolo 17
A17: Dal listino al prezzo netto realizzato
A18: Riduzioni del corrispettivo fino al ricavo netto, poi il costo di servizio; capitolo 17
A19: Voce | B19: Valore | C19: Unità | D19: Valore atteso (libro) | E19: Controllo | F19: Fonte nel libro
A20: Prezzo di listino | B20: 120 | C20: euro/unità | F20: capitolo 17
A21: Sconto commerciale | B21: 12 | C21: euro/unità | F21: capitolo 17
A22: Premio fine anno | B22: 4 | C22: euro/unità | F22: capitolo 17
A23: Resi e rettifiche attesi | B23: 1 | C23: euro/unità | F23: capitolo 17
A24: Ricavo netto unitario | B24: =$B$20-$B$21-$B$22-$B$23 -> 103 | C24: euro/unità | D24: 103 | E24: =IF(ABS(B24-D24)<=0.5,"OK","DIVERSO") -> OK | F24: capitolo 17
A25: Trasporto incluso (costo di servizio) | B25: 3 | C25: euro/unità | F25: capitolo 17
A26: Prezzo netto realizzato | B26: =$B$24-$B$25 -> 100 | C26: euro/unità | D26: 100 | E26: =IF(ABS(B26-D26)<=0.5,"OK","DIVERSO") -> OK | F26: capitolo 17
A28: Sconto e volume necessario
A29: Uno sconto del 5% taglia il margine del 16,7% e richiede il 20% di volume in più; capitolo 17
A30: Voce | B30: Valore | C30: Unità | D30: Valore atteso (libro) | E30: Controllo | F30: Fonte nel libro
A31: Prezzo | B31: 100 | C31: euro/unità | F31: capitolo 17
A32: Costo variabile | B32: 70 | C32: euro/unità | F32: capitolo 17
A33: Sconto | B33: 5 | C33: euro/unità | F33: capitolo 17
A34: Volume dello scenario base | B34: 1000 | C34: unità | F34: capitolo 17
A35: Margine unitario base | B35: =$B$31-$B$32 -> 30 | C35: euro/unità | D35: 30 | E35: =IF(ABS(B35-D35)<=0.5,"OK","DIVERSO") -> OK | F35: capitolo 17
A36: Prezzo scontato | B36: =$B$31-$B$33 -> 95 | C36: euro/unità | D36: 95 | E36: =IF(ABS(B36-D36)<=0.5,"OK","DIVERSO") -> OK | F36: capitolo 17
A37: Sconto in percentuale | B37: =$B$33/$B$31 -> 0.05 | C37: % | D37: 0.05 | E37: =IF(ABS(B37-D37)<=0.0005,"OK","DIVERSO") -> OK | F37: capitolo 17
A38: Margine unitario dopo lo sconto | B38: =$B$36-$B$32 -> 25 | C38: euro/unità | D38: 25 | E38: =IF(ABS(B38-D38)<=0.5,"OK","DIVERSO") -> OK | F38: capitolo 17
A39: Riduzione del margine unitario | B39: =1-$B$38/$B$35 -> 0.16666667 | C39: % | D39: 0.167 | E39: =IF(ABS(B39-D39)<=0.0005,"OK","DIVERSO") -> OK | F39: capitolo 17
A40: Margine totale base | B40: =$B$35*$B$34 -> 30000 | C40: euro | D40: 30000 | E40: =IF(ABS(B40-D40)<=0.5,"OK","DIVERSO") -> OK | F40: capitolo 17
A41: Volume necessario dopo lo sconto | B41: =$B$40/$B$38 -> 1200 | C41: unità | D41: 1200 | E41: =IF(ABS(B41-D41)<=0.5,"OK","DIVERSO") -> OK | F41: capitolo 17
A42: Margine totale scenario sconto | B42: =$B$38*$B$41 -> 30000 | C42: euro | D42: 30000 | E42: =IF(ABS(B42-D42)<=0.5,"OK","DIVERSO") -> OK | F42: capitolo 17
A43: Volume aggiuntivo richiesto | B43: =$B$41/$B$34-1 -> 0.2 | C43: % | D43: 0.2 | E43: =IF(ABS(B43-D43)<=0.0005,"OK","DIVERSO") -> OK | F43: capitolo 17
A45: Impresa guida - la cascata della linea B
A46: Dal listino di 120 al prezzo netto di 114 e margine contro ricarico; capitolo 17
A47: Voce | B47: Valore | C47: Unità | D47: Valore atteso (libro) | E47: Controllo | F47: Fonte nel libro
A48: Linea B - listino | B48: =Cap_08!$B$98 -> 120 | C48: euro/unità | F48: capitolo 17
A49: Sconto commerciale | B49: 4 | C49: euro/unità | F49: capitolo 17
A50: Premio di fine anno | B50: 1.2 | C50: euro/unità | F50: capitolo 17
A51: Altre concessioni sul corrispettivo | B51: 0.8 | C51: euro/unità | F51: capitolo 17
A52: Ricavo netto unitario (prezzo netto) | B52: =$B$48-$B$49-$B$50-$B$51 -> 114 | C52: euro/unità | D52: 114 | E52: =IF(ABS(B52-D52)<=0.5,"OK","DIVERSO") -> OK | F52: capitolo 17
A53: Differenza dal prezzo del dataset (deve essere zero) | B53: =$B$52-Impresa_guida!$B$13 -> 0 | C53: euro/unità | F53: capitolo 17
A54: Margine sul prezzo | B54: =Cap_15!$B$94/Impresa_guida!$B$13 -> 0.33333333 | C54: % | D54: 0.333 | E54: =IF(ABS(B54-D54)<=0.0005,"OK","DIVERSO") -> OK | F54: capitolo 17
A55: Ricarico sul costo variabile | B55: =Cap_15!$B$94/Impresa_guida!$B$14 -> 0.5 | C55: % | D55: 0.5 | E55: =IF(ABS(B55-D55)<=0.0005,"OK","DIVERSO") -> OK | F55: capitolo 17
A57: Impresa guida - linea B contro il budget
A58: Scostamento di prezzo e margine e volume necessario per il margine di budget; capitolo 17
A59: Voce | B59: Valore | C59: Unità | D59: Valore atteso (libro) | E59: Controllo | F59: Fonte nel libro
A60: Prezzo di budget | B60: =Cap_12!$B$20 -> 118 | C60: euro/unità | F60: capitolo 17
A61: Margine di budget della linea B | B61: =Cap_12!$B$19*$B$62 -> 478800 | C61: euro | F61: capitolo 17
A62: Margine unitario di budget | B62: =$B$60-Impresa_guida!$B$14 -> 42 | C62: euro/unità | D62: 42 | E62: =IF(ABS(B62-D62)<=0.5,"OK","DIVERSO") -> OK | F62: capitolo 17
A63: Scostamento del prezzo | B63: =Impresa_guida!$B$13/$B$60-1 -> -0.033898305 | C63: % | D63: -0.034 | E63: =IF(ABS(B63-D63)<=0.0005,"OK","DIVERSO") -> OK | F63: capitolo 17
A64: Scostamento del margine unitario | B64: =Cap_15!$B$94/$B$62-1 -> -0.095238095 | C64: % | D64: -0.095 | E64: =IF(ABS(B64-D64)<=0.0005,"OK","DIVERSO") -> OK | F64: capitolo 17
A65: Volume necessario per il margine di budget | B65: =$B$61/Cap_15!$B$94 -> 12600 | C65: unità | D65: 12600 | E65: =IF(ABS(B65-D65)<=0.5,"OK","DIVERSO") -> OK | F65: capitolo 17
A66: Margine non recuperato servendo tutta la domanda | B66: =$B$61-Cap_15!$B$94*Impresa_guida!$B$12 -> 22800 | C66: euro | D66: 22800 | E66: =IF(ABS(B66-D66)<=0.5,"OK","DIVERSO") -> OK | F66: capitolo 17
A67: Trasporto per consegna - parte variabile | B67: =Cap_11!$B$19 -> 23 | C67: euro/consegna | F67: capitolo 17
A68: Consegna - tariffa piena | B68: =Cap_10!$B$150 -> 30 | C68: euro/consegna | F68: capitolo 17
A69: di cui personale di spedizione (costo di capacità) | B69: =$B$68-$B$67 -> 7 | C69: euro/consegna | D69: 7 | E69: =IF(ABS(B69-D69)<=0.5,"OK","DIVERSO") -> OK | F69: capitolo 17
A71: Impresa guida - prezzi minimi per linea
A72: Capacità libera, vincolo con ore tolte alla linea C (17 euro per ora) e ore esterne a 28 euro; capitolo 17
A73: Voce | B73: Valore | C73: Unità | D73: Valore atteso (libro) | E73: Controllo | F73: Fonte nel libro
A74: Linea A - prezzo minimo con capacità libera | B74: =Impresa_guida!$B$10 -> 117 | C74: euro/unità | D74: 117 | E74: =IF(ABS(B74-D74)<=0.5,"OK","DIVERSO") -> OK | F74: capitolo 17
A75: Linea A - prezzo minimo con vincolo | B75: =Impresa_guida!$B$10+Impresa_guida!$B$11*Cap_15!$B$97 -> 142.5 | C75: euro/unità | D75: 142.5 | E75: =IF(ABS(B75-D75)<=0.005,"OK","DIVERSO") -> OK | F75: capitolo 17
A76: Linea A - prezzo con ore esterne | B76: =Impresa_guida!$B$10+Impresa_guida!$B$11*Impresa_guida!$B$27 -> 159 | C76: euro/unità | D76: 159 | E76: =IF(ABS(B76-D76)<=0.005,"OK","DIVERSO") -> OK | F76: capitolo 17
A77: Linea B - prezzo minimo con capacità libera | B77: =Impresa_guida!$B$14 -> 76 | C77: euro/unità | D77: 76 | E77: =IF(ABS(B77-D77)<=0.5,"OK","DIVERSO") -> OK | F77: capitolo 17
A78: Linea B - prezzo minimo con vincolo | B78: =Impresa_guida!$B$14+Impresa_guida!$B$15*Cap_15!$B$97 -> 84.5 | C78: euro/unità | D78: 84.5 | E78: =IF(ABS(B78-D78)<=0.005,"OK","DIVERSO") -> OK | F78: capitolo 17
A79: Linea B - prezzo con ore esterne | B79: =Impresa_guida!$B$14+Impresa_guida!$B$15*Impresa_guida!$B$27 -> 90 | C79: euro/unità | D79: 90 | E79: =IF(ABS(B79-D79)<=0.005,"OK","DIVERSO") -> OK | F79: capitolo 17
A80: Linea C - prezzo minimo con capacità libera | B80: =Impresa_guida!$B$18 -> 238 | C80: euro/unità | D80: 238 | E80: =IF(ABS(B80-D80)<=0.5,"OK","DIVERSO") -> OK | F80: capitolo 17
A81: Linea C - prezzo minimo con vincolo | B81: =Impresa_guida!$B$18+Impresa_guida!$B$19*Cap_15!$B$97 -> 289 | C81: euro/unità | D81: 289 | E81: =IF(ABS(B81-D81)<=0.005,"OK","DIVERSO") -> OK | F81: capitolo 17
A82: Linea C - prezzo con ore esterne | B82: =Impresa_guida!$B$18+Impresa_guida!$B$19*Impresa_guida!$B$27 -> 322 | C82: euro/unità | D82: 322 | E82: =IF(ABS(B82-D82)<=0.005,"OK","DIVERSO") -> OK | F82: capitolo 17
A83: Aumento necessario del prezzo di C | B83: =$B$82/Impresa_guida!$B$17-1 -> 0.11418685 | C83: % | D83: 0.114 | E83: =IF(ABS(B83-D83)<=0.0005,"OK","DIVERSO") -> OK | F83: capitolo 17
A84: Listino attuale della linea C | B84: =Cap_08!$B$99 -> 305 | C84: euro/unità | F84: capitolo 17
A85: Prezzo con ore esterne rispetto al listino | B85: =IF($B$82>$B$84,"Sopra il listino","Entro il listino") -> Sopra il listino | D85: Sopra il listino | E85: =IF(B85=D85,"OK","DIVERSO") -> OK | F85: capitolo 17

Sheet Cap_18
A1: Capitolo 18 - Ottimizzazione dei margini e alternative produttive
A2: Controllo di gestione con l'intelligenza artificiale - file Excel che accompagna il libro
A3: Celle blu su fondo giallo: dati da cambiare. Celle nere: formule. «Valore atteso (libro)» e «Controllo» confrontano il calcolo con il numero stampato nel libro.
A4: Margine per fattore scarso, mix con uno e due vincoli, prezzi ombra e scenari di mix dell'impresa guida.
A6: Margine per fattore scarso
A7: Margine unitario diviso per le ore macchina per unità; capitolo 18
A8: Voce | B8: Valore | C8: Unità | D8: Valore atteso (libro) | E8: Controllo | F8: Fonte nel libro
A9: Prodotto A - margine unitario | B9: 60 | C9: euro/unità | F9: capitolo 18
A10: Prodotto A - ore macchina per unità | B10: 3 | C10: ore/unità | F10: capitolo 18
A11: Prodotto B - margine unitario | B11: 45 | C11: euro/unità | F11: capitolo 18
A12: Prodotto B - ore macchina per unità | B12: 1.5 | C12: ore/unità | F12: capitolo 18
A13: Prodotto A - margine per ora | B13: =$B$9/$B$10 -> 20 | C13: euro/ora | D13: 20 | E13: =IF(ABS(B13-D13)<=0.5,"OK","DIVERSO") -> OK | F13: capitolo 18
A14: Prodotto B - margine per ora | B14: =$B$11/$B$12 -> 30 | C14: euro/ora | D14: 30 | E14: =IF(ABS(B14-D14)<=0.5,"OK","DIVERSO") -> OK | F14: capitolo 18
A15: Prodotto con priorità | B15: =IF($B$14>$B$13,"B","A") -> B | D15: B | E15: =IF(B15=D15,"OK","DIVERSO") -> OK | F15: capitolo 18
A17: Mix produttivo con 9.000 ore
A18: Capacità assegnata a B fino alla domanda massima, poi ad A; capitolo 18
A19: Voce | B19: Valore | C19: Unità | D19: Valore atteso (libro) | E19: Controllo | F19: Fonte nel libro
A20: Ore macchina disponibili | B20: 9000 | C20: ore | F20: capitolo 18
A21: Domanda massima di B | B21: 4000 | C21: unità | F21: capitolo 18
A22: Ore assorbite da B | B22: =$B$21*$B$12 -> 6000 | C22: ore | D22: 6000 | E22: =IF(ABS(B22-D22)<=0.5,"OK","DIVERSO") -> OK | F22: capitolo 18
A23: Margine di B | B23: =$B$21*$B$11 -> 180000 | C23: euro | D23: 180000 | E23: =IF(ABS(B23-D23)<=0.5,"OK","DIVERSO") -> OK | F23: capitolo 18
A24: Ore residue per A | B24: =$B$20-$B$22 -> 3000 | C24: ore | D24: 3000 | E24: =IF(ABS(B24-D24)<=0.5,"OK","DIVERSO") -> OK | F24: capitolo 18
A25: Unità di A | B25: =$B$24/$B$10 -> 1000 | C25: unità | D25: 1000 | E25: =IF(ABS(B25-D25)<=0.5,"OK","DIVERSO") -> OK | F25: capitolo 18
A26: Margine di A | B26: =$B$25*$B$9 -> 60000 | C26: euro | D26: 60000 | E26: =IF(ABS(B26-D26)<=0.5,"OK","DIVERSO") -> OK | F26: capitolo 18
A27: Quantità totale | B27: =$B$21+$B$25 -> 5000 | C27: unità | D27: 5000 | E27: =IF(ABS(B27-D27)<=0.5,"OK","DIVERSO") -> OK | F27: capitolo 18
A28: Margine totale | B28: =$B$23+$B$26 -> 240000 | C28: euro | D28: 240000 | E28: =IF(ABS(B28-D28)<=0.5,"OK","DIVERSO") -> OK | F28: capitolo 18
A30: Valore della capacità aggiuntiva
A31: Con B saturata un'ora in più vale il margine orario di A; confronto con due costi; capitolo 18
A32: Voce | B32: Valore | C32: Unità | D32: Valore atteso (libro) | E32: Controllo | F32: Fonte nel libro
A33: Valore di un'ora aggiuntiva | B33: =$B$13 -> 20 | C33: euro/ora | D33: 20 | E33: =IF(ABS(B33-D33)<=0.5,"OK","DIVERSO") -> OK | F33: capitolo 18
A34: Costo di un'ora - caso 1 | B34: 15 | C34: euro/ora | F34: capitolo 18
A35: Costo di un'ora - caso 2 | B35: 22 | C35: euro/ora | F35: capitolo 18
A36: Esito caso 1 | B36: =IF($B$34<$B$33,"Conveniente","Non conveniente") -> Conveniente | D36: Conveniente | E36: =IF(B36=D36,"OK","DIVERSO") -> OK | F36: capitolo 18
A37: Esito caso 2 | B37: =IF($B$35<$B$33,"Conveniente","Non conveniente") -> Non conveniente | D37: Non conveniente | E37: =IF(B37=D37,"OK","DIVERSO") -> OK | F37: capitolo 18
A39: Due vincoli - dati e ordinamenti su un solo rapporto
A40: Aggiunta del lavoro specializzato: il mix precedente non è realizzabile e l'ordinamento per ora di lavoro dà 195.000; capitolo 18
A41: Voce | B41: Valore | C41: Unità | D41: Valore atteso (libro) | E41: Controllo | F41: Fonte nel libro
A42: Prodotto A - ore di lavoro per unità | B42: 1 | C42: ore/unità | F42: capitolo 18
A43: Prodotto B - ore di lavoro per unità | B43: 2 | C43: ore/unità | F43: capitolo 18
A44: Ore di lavoro disponibili | B44: 7500 | C44: ore | F44: capitolo 18
A45: Domanda massima di A | B45: 2500 | C45: unità | F45: capitolo 18
A46: Ore di lavoro del mix per ora macchina | B46: =$B$25*$B$42+$B$21*$B$43 -> 9000 | C46: ore | D46: 9000 | E46: =IF(ABS(B46-D46)<=0.5,"OK","DIVERSO") -> OK | F46: capitolo 18
A47: Prodotto A - margine per ora di lavoro | B47: =$B$9/$B$42 -> 60 | C47: euro/ora | D47: 60 | E47: =IF(ABS(B47-D47)<=0.5,"OK","DIVERSO") -> OK | F47: capitolo 18
A48: Prodotto B - margine per ora di lavoro | B48: =$B$11/$B$43 -> 22.5 | C48: euro/ora | D48: 22.5 | E48: =IF(ABS(B48-D48)<=0.005,"OK","DIVERSO") -> OK | F48: capitolo 18
A49: Unità di B con le ore macchina residue | B49: =($B$20-$B$45*$B$10)/$B$12 -> 1000 | C49: unità | D49: 1000 | E49: =IF(ABS(B49-D49)<=0.5,"OK","DIVERSO") -> OK | F49: capitolo 18
A50: Margine dell'ordinamento per ora di lavoro | B50: =$B$45*$B$9+$B$49*$B$11 -> 195000 | C50: euro | D50: 195000 | E50: =IF(ABS(B50-D50)<=0.5,"OK","DIVERSO") -> OK | F50: capitolo 18
A52: Due vincoli - i vertici dell'area ammissibile
A53: Ore e margine in ogni vertice; l'ottimo satura entrambe le risorse; capitolo 18
A54: Voce | B54: Valore | C54: Unità | D54: Valore atteso (libro) | E54: Controllo | F54: Fonte nel libro
A55: Vertice 1 (solo A) - A | B55: =$B$45 -> 2500 | C55: unità | D55: 2500 | E55: =IF(ABS(B55-D55)<=0.5,"OK","DIVERSO") -> OK | F55: capitolo 18
A56: Vertice 1 - ore macchina | B56: =$B$55*$B$10 -> 7500 | C56: ore | D56: 7500 | E56: =IF(ABS(B56-D56)<=0.5,"OK","DIVERSO") -> OK | F56: capitolo 18
A57: Vertice 1 - ore lavoro | B57: =$B$55*$B$42 -> 2500 | C57: ore | D57: 2500 | E57: =IF(ABS(B57-D57)<=0.5,"OK","DIVERSO") -> OK | F57: capitolo 18
A58: Vertice 1 - margine | B58: =$B$55*$B$9 -> 150000 | C58: euro | D58: 150000 | E58: =IF(ABS(B58-D58)<=0.5,"OK","DIVERSO") -> OK | F58: capitolo 18
A59: Vertice 2 (A massimo, macchina satura) - ore lavoro | B59: =$B$45*$B$42+$B$49*$B$43 -> 4500 | C59: ore | D59: 4500 | E59: =IF(ABS(B59-D59)<=0.5,"OK","DIVERSO") -> OK | F59: capitolo 18
A60: Vertice 3 (macchina e lavoro saturi) - A | B60: =($B$20*$B$43-$B$12*$B$44)/($B$10*$B$43-$B$12*$B$42) -> 1500 | C60: unità | D60: 1500 | E60: =IF(ABS(B60-D60)<=0.5,"OK","DIVERSO") -> OK | F60: capitolo 18
A61: Vertice 3 - B | B61: =($B$10*$B$44-$B$20*$B$42)/($B$10*$B$43-$B$12*$B$42) -> 3000 | C61: unità | D61: 3000 | E61: =IF(ABS(B61-D61)<=0.5,"OK","DIVERSO") -> OK | F61: capitolo 18
A62: Vertice 3 - ore macchina | B62: =$B$60*$B$10+$B$61*$B$12 -> 9000 | C62: ore | D62: 9000 | E62: =IF(ABS(B62-D62)<=0.5,"OK","DIVERSO") -> OK | F62: capitolo 18
A63: Vertice 3 - ore lavoro | B63: =$B$60*$B$42+$B$61*$B$43 -> 7500 | C63: ore | D63: 7500 | E63: =IF(ABS(B63-D63)<=0.5,"OK","DIVERSO") -> OK | F63: capitolo 18
A64: Vertice 3 - margine | B64: =$B$60*$B$9+$B$61*$B$11 -> 225000 | C64: euro | D64: 225000 | E64: =IF(ABS(B64-D64)<=0.5,"OK","DIVERSO") -> OK | F64: capitolo 18
A65: Vertice 4 (solo B, lavoro saturo) - B | B65: =$B$44/$B$43 -> 3750 | C65: unità | D65: 3750 | E65: =IF(ABS(B65-D65)<=0.5,"OK","DIVERSO") -> OK | F65: capitolo 18
A66: Vertice 4 - ore macchina | B66: =$B$65*$B$12 -> 5625 | C66: ore | D66: 5625 | E66: =IF(ABS(B66-D66)<=0.5,"OK","DIVERSO") -> OK | F66: capitolo 18
A67: Vertice 4 - margine | B67: =$B$65*$B$11 -> 168750 | C67: euro | D67: 168750 | E67: =IF(ABS(B67-D67)<=0.5,"OK","DIVERSO") -> OK | F67: capitolo 18
A68: Margine ottimo | B68: =MAX($B$58,$B$50,$B$64,$B$67) -> 225000 | C68: euro | D68: 225000 | E68: =IF(ABS(B68-D68)<=0.5,"OK","DIVERSO") -> OK | F68: capitolo 18
A70: Due vincoli - prezzi ombra
A71: Valore di un'ora in più di ciascuna risorsa e verifica sul margine ottimo; capitolo 18
A72: Voce | B72: Valore | C72: Unità | D72: Valore atteso (libro) | E72: Controllo | F72: Fonte nel libro
A73: Prezzo ombra dell'ora macchina | B73: =($B$9*$B$43-$B$42*$B$11)/($B$10*$B$43-$B$42*$B$12) -> 16.666667 | C73: euro/ora | D73: 16.67 | E73: =IF(ABS(B73-D73)<=0.005,"OK","DIVERSO") -> OK | F73: capitolo 18
A74: Prezzo ombra dell'ora di lavoro | B74: =($B$10*$B$11-$B$12*$B$9)/($B$10*$B$43-$B$42*$B$12) -> 10 | C74: euro/ora | D74: 10 | E74: =IF(ABS(B74-D74)<=0.5,"OK","DIVERSO") -> OK | F74: capitolo 18
A75: Capacità valorizzate ai prezzi ombra | B75: =$B$20*$B$73+$B$44*$B$74 -> 225000 | C75: euro | D75: 225000 | E75: =IF(ABS(B75-D75)<=0.5,"OK","DIVERSO") -> OK | F75: capitolo 18
A77: Costo di una deviazione dal mix
A78: 200 unità di A imposte al posto di B con il solo vincolo delle ore macchina; capitolo 18
A79: Voce | B79: Valore | C79: Unità | D79: Valore atteso (libro) | E79: Controllo | F79: Fonte nel libro
A80: Unità aggiuntive di A imposte | B80: 200 | C80: unità | F80: capitolo 18
A81: Ore assorbite | B81: =$B$80*$B$10 -> 600 | C81: ore | D81: 600 | E81: =IF(ABS(B81-D81)<=0.5,"OK","DIVERSO") -> OK | F81: capitolo 18
A82: Unità di B perse | B82: =$B$81/$B$12 -> 400 | C82: unità | D82: 400 | E82: =IF(ABS(B82-D82)<=0.5,"OK","DIVERSO") -> OK | F82: capitolo 18
A83: Margine guadagnato su A | B83: =$B$80*$B$9 -> 12000 | C83: euro | D83: 12000 | E83: =IF(ABS(B83-D83)<=0.5,"OK","DIVERSO") -> OK | F83: capitolo 18
A84: Margine perso su B | B84: =$B$82*$B$11 -> 18000 | C84: euro | D84: 18000 | E84: =IF(ABS(B84-D84)<=0.5,"OK","DIVERSO") -> OK | F84: capitolo 18
A85: Margine perso | B85: =$B$84-$B$83 -> 6000 | C85: euro | D85: 6000 | E85: =IF(ABS(B85-D85)<=0.5,"OK","DIVERSO") -> OK | F85: capitolo 18
A86: Verifica: ore per differenza di margine orario | B86: =$B$81*($B$14-$B$13) -> 6000 | C86: euro | D86: 6000 | E86: =IF(ABS(B86-D86)<=0.5,"OK","DIVERSO") -> OK | F86: capitolo 18
A88: Impresa guida - quattro scenari di mix
A89: Mix per margine orario (ottimo), C servita con ore comprate o tolte ad A, mix per margine unitario; margini per ora nel foglio Cap_15; capitolo 18
A90: Voce | B90: Valore | C90: Unità | D90: Valore atteso (libro) | E90: Controllo | F90: Fonte nel libro
A91: Mix per margine per ora - margine | B91: =Cap_15!$B$110 -> 1011000 | C91: euro | D91: 1011000 | E91: =IF(ABS(B91-D91)<=0.5,"OK","DIVERSO") -> OK | F91: capitolo 18
A92: Mix per margine per ora - risultato | B92: =Cap_15!$B$117 -> 275000 | C92: euro | D92: 275000 | E92: =IF(ABS(B92-D92)<=0.5,"OK","DIVERSO") -> OK | F92: capitolo 18
A93: C a 2.000 con ore comprate - margine | B93: =Cap_15!$B$108 -> 1062000 | C93: euro | D93: 1062000 | E93: =IF(ABS(B93-D93)<=0.5,"OK","DIVERSO") -> OK | F93: capitolo 18
A94: C a 2.000 con ore comprate - capacità esterna | B94: =Cap_15!$B$112 -> 84000 | C94: euro | D94: 84000 | E94: =IF(ABS(B94-D94)<=0.5,"OK","DIVERSO") -> OK | F94: capitolo 18
A95: C a 2.000 con ore comprate - risultato | B95: =Cap_15!$B$115 -> 242000 | C95: euro | D95: 242000 | E95: =IF(ABS(B95-D95)<=0.5,"OK","DIVERSO") -> OK | F95: capitolo 18
A96: C a 2.000 con ore tolte ad A - unità di A | B96: =(Impresa_guida!$B$26-Cap_15!$B$99-Impresa_guida!$B$16*Impresa_guida!$B$19)/Impresa_guida!$B$11 -> 6000 | C96: unità | D96: 6000 | E96: =IF(ABS(B96-D96)<=0.5,"OK","DIVERSO") -> OK | F96: capitolo 18
A97: C a 2.000 con ore tolte ad A - margine | B97: =$B$96*Cap_15!$B$92+Impresa_guida!$B$12*Cap_15!$B$94+Impresa_guida!$B$16*Cap_15!$B$96 -> 936000 | C97: euro | D97: 936000 | E97: =IF(ABS(B97-D97)<=0.5,"OK","DIVERSO") -> OK | F97: capitolo 18
A98: C a 2.000 con ore tolte ad A - risultato | B98: =$B$97-Impresa_guida!$B$40 -> 200000 | C98: euro | D98: 200000 | E98: =IF(ABS(B98-D98)<=0.5,"OK","DIVERSO") -> OK | F98: capitolo 18
A99: Mix per margine unitario - unità di B | B99: =(Impresa_guida!$B$26-Cap_15!$B$98-Impresa_guida!$B$16*Impresa_guida!$B$19)/Impresa_guida!$B$15 -> 6000 | C99: unità | D99: 6000 | E99: =IF(ABS(B99-D99)<=0.5,"OK","DIVERSO") -> OK | F99: capitolo 18
A100: Mix per margine unitario - margine | B100: =Impresa_guida!$B$8*Cap_15!$B$92+$B$99*Cap_15!$B$94+Impresa_guida!$B$16*Cap_15!$B$96 -> 834000 | C100: euro | D100: 834000 | E100: =IF(ABS(B100-D100)<=0.5,"OK","DIVERSO") -> OK | F100: capitolo 18
A101: Mix per margine unitario - risultato | B101: =$B$100-Impresa_guida!$B$40 -> 98000 | C101: euro | D101: 98000 | E101: =IF(ABS(B101-D101)<=0.5,"OK","DIVERSO") -> OK | F101: capitolo 18
A102: Margine perso ordinando per margine unitario | B102: =$B$91-$B$100 -> 177000 | C102: euro | D102: 177000 | E102: =IF(ABS(B102-D102)<=0.5,"OK","DIVERSO") -> OK | F102: capitolo 18
A104: Impresa guida - valore dell'ora e costo delle deviazioni
A105: Un'ora in più vale 17 euro per 3.000 ore; servire tutta la C costa 33.000 euro con ore comprate o 75.000 togliendo ore ad A; capitolo 18
A106: Voce | B106: Valore | C106: Unità | D106: Valore atteso (libro) | E106: Controllo | F106: Fonte nel libro
A107: Valore di un'ora aggiuntiva | B107: =Cap_15!$B$97 -> 17 | C107: euro/ora | D107: 17 | E107: =IF(ABS(B107-D107)<=0.5,"OK","DIVERSO") -> OK | F107: capitolo 18
A108: Ore per cui vale (domanda di C non servita) | B108: =(Impresa_guida!$B$16-Cap_15!$B$100)*Impresa_guida!$B$19 -> 3000 | C108: ore | D108: 3000 | E108: =IF(ABS(B108-D108)<=0.5,"OK","DIVERSO") -> OK | F108: capitolo 18
A109: Perdita per ogni ora comprata a 28 euro | B109: =Impresa_guida!$B$27-$B$107 -> 11 | C109: euro/ora | D109: 11 | E109: =IF(ABS(B109-D109)<=0.5,"OK","DIVERSO") -> OK | F109: capitolo 18
...

Sheet Cap_19
A1: Capitolo 19 - L'intelligenza artificiale nel controllo di gestione
A2: Controllo di gestione con l'intelligenza artificiale - file Excel che accompagna il libro
A3: Celle blu su fondo giallo: dati da cambiare. Celle nere: formule. «Valore atteso (libro)» e «Controllo» confrontano il calcolo con il numero stampato nel libro.
A4: Il foglio con cui si collaudano le risposte degli strumenti di IA: ricalcola in formule, dai dati dell'impresa guida, i numeri da ritrovare nel collaudo dei quindici lavori e dei processi dei paragrafi 19.2 e 19.5.
A6: 19.2 - Previsione di chiusura dopo il primo trimestre
A7: Scenario di prosecuzione (rapporto consuntivo/budget del trimestre applicato ai nove mesi residui) contro il trimestre moltiplicato per quattro; il budget annuo viene dal blocco del lavoro 8; il libro arrotonda alle centinaia; paragrafo 19.2
A8: Voce | B8: Valore | C8: Unità | D8: Valore atteso (libro) | E8: Controllo | F8: Fonte nel libro
A9: Primo trimestre - ricavi netti consuntivi | B9: 842300 | C9: euro | F9: paragrafo 19.2
A10: Primo trimestre - margine di contribuzione consuntivo | B10: 262900 | C10: euro | F10: paragrafo 19.2
A11: Primo trimestre - costi della struttura consuntivi | B11: 204500 | C11: euro | F11: paragrafo 19.2
A12: Primo trimestre - ricavi netti di budget | B12: 846500 | C12: euro | F12: paragrafo 19.2
A13: Primo trimestre - margine di budget | B13: 268000 | C13: euro | F13: paragrafo 19.2
A14: Primo trimestre - costi della struttura di budget | B14: 205500 | C14: euro | F14: paragrafo 19.2
A15: Ore esterne dei nove mesi residui rispetto al budget | B15: -100 | C15: ore | F15: paragrafo 19.2
A16: Primo trimestre - risultato operativo | B16: =$B$10-$B$11 -> 58400 | C16: euro | D16: 58400 | E16: =IF(ABS(B16-D16)<=0.5,"OK","DIVERSO") -> OK | F16: paragrafo 19.2
A17: Prosecuzione - ricavi dell'esercizio | B17: =$B$9+($B$100-$B$12)*$B$9/$B$12 -> 3375269.7 | C17: euro | D17: 3375300 | E17: =IF(ABS(B17-D17)<=50,"OK","DIVERSO") -> OK | F17: paragrafo 19.2
A18: Prosecuzione - margine dell'esercizio | B18: =$B$10+($B$101-$B$13)*$B$10/$B$13 -> 1069159.4 | C18: euro | D18: 1069200 | E18: =IF(ABS(B18-D18)<=50,"OK","DIVERSO") -> OK | F18: paragrafo 19.2
A19: Prosecuzione - costi della struttura | B19: =$B$11+($B$104-$B$14)+$B$15*Impresa_guida!$B$27 -> 816200 | C19: euro | D19: 816200 | E19: =IF(ABS(B19-D19)<=0.5,"OK","DIVERSO") -> OK | F19: paragrafo 19.2
A20: Previsione di chiusura - risultato operativo | B20: =$B$18-$B$19 -> 252959.37 | C20: euro | D20: 253000 | E20: =IF(ABS(B20-D20)<=50,"OK","DIVERSO") -> OK | F20: paragrafo 19.2
A21: Errore tipico: trimestre x 4 - risultato operativo | B21: =4*($B$10-$B$11) -> 233600 | C21: euro | D21: 233600 | E21: =IF(ABS(B21-D21)<=0.5,"OK","DIVERSO") -> OK | F21: paragrafo 19.2
A22: Differenza fra prosecuzione e trimestre x 4 | B22: =$B$20-$B$21 -> 19359.366 | C22: euro | D22: 19400 | E22: =IF(ABS(B22-D22)<=50,"OK","DIVERSO") -> OK | F22: paragrafo 19.2
A24: Lavori 1, 2 e 3 - Classificare i costi, capacità mensile, Conto Economico a margine
A25: Costi che variano rispetto a un driver e costi di capacità; ore mancanti; capacità mensile usata nel lavoro 2 e nel 19.5; incidenze del prospetto a margine; capitolo 19, lavori 1, 2 e 3
A26: Voce | B26: Valore | C26: Unità | D26: Valore atteso (libro) | E26: Controllo | F26: Fonte nel libro
A27: Trasporti su vendite | B27: =Cap_02!$B$22 -> 138000 | C27: euro | F27: capitolo 19, lavoro 1
A28: Ricambi e trasferte di assistenza | B28: =Cap_02!$B$25 -> 32000 | C28: euro | F28: capitolo 19, lavoro 1
A29: Costi che variano rispetto a un driver | B29: =Impresa_guida!$B$39+$B$27+$B$28 -> 254000 | C29: euro | D29: 254000 | E29: =IF(ABS(B29-D29)<=0.5,"OK","DIVERSO") -> OK | F29: capitolo 19, lavoro 1
A30: Costi di capacità | B30: =Impresa_guida!$B$41-$B$29 -> 566000 | C30: euro | D30: 566000 | E30: =IF(ABS(B30-D30)<=0.5,"OK","DIVERSO") -> OK | F30: capitolo 19, lavoro 1
A31: Ore mancanti ricavate dalla capacità esterna (84.000 / 28) | B31: =Impresa_guida!$B$39/Impresa_guida!$B$27 -> 3000 | C31: ore | D31: 3000 | E31: =IF(ABS(B31-D31)<=0.5,"OK","DIVERSO") -> OK | F31: capitolo 19, lavoro 1
A32: Capacità ordinaria al mese | B32: =Impresa_guida!$B$26/12 -> 1750 | C32: ore | D32: 1750 | E32: =IF(ABS(B32-D32)<=0.5,"OK","DIVERSO") -> OK | F32: capitolo 19, lavoro 2
A33: Margine di contribuzione in % dei ricavi | B33: =Impresa_guida!$B$36/Impresa_guida!$B$34 -> 0.31364442 | C33: % | D33: 0.314 | E33: =IF(ABS(B33-D33)<=0.0005,"OK","DIVERSO") -> OK | F33: capitolo 19, lavoro 3
A34: Incidenza dei costi variabili | B34: =Impresa_guida!$B$35/Impresa_guida!$B$34 -> 0.68635558 | C34: % | D34: 0.686 | E34: =IF(ABS(B34-D34)<=0.0005,"OK","DIVERSO") -> OK | F34: capitolo 19, lavoro 3
A35: Incidenza dei costi della struttura | B35: =Impresa_guida!$B$41/Impresa_guida!$B$34 -> 0.24217366 | C35: % | D35: 0.242 | E35: =IF(ABS(B35-D35)<=0.0005,"OK","DIVERSO") -> OK | F35: capitolo 19, lavoro 3
A36: Incidenza del risultato operativo | B36: =Impresa_guida!$B$42/Impresa_guida!$B$34 -> 0.071470762 | C36: % | D36: 0.071 | E36: =IF(ABS(B36-D36)<=0.0005,"OK","DIVERSO") -> OK | F36: capitolo 19, lavoro 3
A38: Lavoro 4 - Allocare i costi indiretti
A39: Ribaltamento a cascata dei centri ausiliari sul centro Lavorazione e allocazione per ore macchina; capitolo 19, lavoro 4
A40: Voce | B40: Valore | C40: Unità | D40: Valore atteso (libro) | E40: Controllo | F40: Fonte nel libro
A41: Manutenzione - costo diretto | B41: =Cap_05!$B$22 -> 36000 | C41: euro | F41: capitolo 19, lavoro 4
A42: Programmazione e qualità - costo diretto | B42: =Cap_05!$B$23 -> 18000 | C42: euro | F42: capitolo 19, lavoro 4
A43: Lavorazione - costo diretto | B43: =Cap_05!$B$24 -> 66000 | C43: euro | F43: capitolo 19, lavoro 4
A44: Quota di Manutenzione a Programmazione e qualità | B44: =Cap_06!$B$109 -> 0.25 | C44: % | F44: capitolo 19, lavoro 4
A45: Lavorazione dopo i ribaltamenti | B45: =$B$43+$B$41*(1-$B$44)+($B$42+$B$41*$B$44) -> 120000 | C45: euro | D45: 120000 | E45: =IF(ABS(B45-D45)<=0.5,"OK","DIVERSO") -> OK | F45: capitolo 19, lavoro 4
A46: Coefficiente per ora macchina | B46: =$B$45/Impresa_guida!$B$37 -> 5 | C46: euro/ora | D46: 5 | E46: =IF(ABS(B46-D46)<=0.005,"OK","DIVERSO") -> OK | F46: capitolo 19, lavoro 4
A47: Linea A - costo allocato per unità | B47: =$B$46*Impresa_guida!$B$11 -> 7.5 | C47: euro/unità | D47: 7.5 | E47: =IF(ABS(B47-D47)<=0.005,"OK","DIVERSO") -> OK | F47: capitolo 19, lavoro 4
A48: Linea A - costo allocato | B48: =$B$47*Impresa_guida!$B$8 -> 60000 | C48: euro | D48: 60000 | E48: =IF(ABS(B48-D48)<=0.5,"OK","DIVERSO") -> OK | F48: capitolo 19, lavoro 4
A49: Linea B - costo allocato per unità | B49: =$B$46*Impresa_guida!$B$15 -> 2.5 | C49: euro/unità | D49: 2.5 | E49: =IF(ABS(B49-D49)<=0.005,"OK","DIVERSO") -> OK | F49: capitolo 19, lavoro 4
A50: Linea B - costo allocato | B50: =$B$49*Impresa_guida!$B$12 -> 30000 | C50: euro | D50: 30000 | E50: =IF(ABS(B50-D50)<=0.5,"OK","DIVERSO") -> OK | F50: capitolo 19, lavoro 4
A51: Linea C - costo allocato per unità | B51: =$B$46*Impresa_guida!$B$19 -> 15 | C51: euro/unità | D51: 15 | E51: =IF(ABS(B51-D51)<=0.005,"OK","DIVERSO") -> OK | F51: capitolo 19, lavoro 4
A52: Linea C - costo allocato | B52: =$B$51*Impresa_guida!$B$16 -> 30000 | C52: euro | D52: 30000 | E52: =IF(ABS(B52-D52)<=0.5,"OK","DIVERSO") -> OK | F52: capitolo 19, lavoro 4
A54: Lavori 5 e 6 - Modello per attività e costo di servizio
A55: Tariffe di capacità (capacità pratica pari ai volumi), costo fuori perimetro, costo di servizio e margine dei clienti X e Y; capitolo 19, lavori 5 e 6
A56: Voce | B56: Valore | C56: Unità | D56: Valore atteso (libro) | E56: Controllo | F56: Fonte nel libro
A57: Pool gestione ordini | B57: =Cap_10!$B$131 -> 240000 | C57: euro | F57: capitolo 19, lavoro 5
A58: Pool consegne | B58: =Cap_10!$B$134 -> 180000 | C58: euro | F58: capitolo 19, lavoro 5
A59: Pool assistenza tecnica | B59: =Cap_10!$B$137 -> 150000 | C59: euro | F59: capitolo 19, lavoro 5
A60: Ordini (capacità pratica) | B60: =Cap_10!$B$146 -> 12000 | C60: ordini | F60: capitolo 19, lavoro 5
A61: Consegne (capacità pratica) | B61: =Cap_10!$B$147 -> 6000 | C61: consegne | F61: capitolo 19, lavoro 5
A62: Ore di assistenza (capacità pratica) | B62: =Cap_10!$B$148 -> 7500 | C62: ore | F62: capitolo 19, lavoro 5
A63: Tariffa per ordine | B63: =$B$57/$B$60 -> 20 | C63: euro/ordine | D63: 20 | E63: =IF(ABS(B63-D63)<=0.005,"OK","DIVERSO") -> OK | F63: capitolo 19, lavoro 5
A64: Tariffa per consegna | B64: =$B$58/$B$61 -> 30 | C64: euro/consegna | D64: 30 | E64: =IF(ABS(B64-D64)<=0.005,"OK","DIVERSO") -> OK | F64: capitolo 19, lavoro 5
A65: Tariffa per ora di assistenza | B65: =$B$59/$B$62 -> 20 | C65: euro/ora | D65: 20 | E65: =IF(ABS(B65-D65)<=0.005,"OK","DIVERSO") -> OK | F65: capitolo 19, lavoro 5
A66: Struttura fuori dal modello | B66: =Impresa_guida!$B$41-($B$57+$B$58+$B$59) -> 250000 | C66: euro | D66: 250000 | E66: =IF(ABS(B66-D66)<=0.5,"OK","DIVERSO") -> OK | F66: capitolo 19, lavoro 5
A67: Clienti X e Y - ricavi netti (uguali) | B67: =Cap_11!$B$28 -> 240000 | C67: euro | F67: capitolo 19, lavoro 6
A68: Clienti X e Y - margine di prodotto (uguale) | B68: =Cap_11!$B$29 -> 84000 | C68: euro | F68: capitolo 19, lavoro 6
A69: Cliente X - ordini | B69: =Cap_11!$B$30 -> 600 | C69: ordini | F69: capitolo 19, lavoro 6
A70: Cliente X - consegne | B70: =Cap_11!$B$31 -> 300 | C70: consegne | F70: capitolo 19, lavoro 6
A71: Cliente X - ore di assistenza | B71: =Cap_11!$B$32 -> 250 | C71: ore | F71: capitolo 19, lavoro 6
A72: Cliente Y - ordini | B72: =Cap_11!$B$36 -> 150 | C72: ordini | F72: capitolo 19, lavoro 6
A73: Cliente Y - consegne | B73: =Cap_11!$B$37 -> 60 | C73: consegne | F73: capitolo 19, lavoro 6
A74: Cliente Y - ore di assistenza | B74: =Cap_11!$B$38 -> 40 | C74: ore | F74: capitolo 19, lavoro 6
A75: Cliente X - costo di servizio | B75: =$B$69*$B$63+$B$70*$B$64+$B$71*$B$65 -> 26000 | C75: euro | D75: 26000 | E75: =IF(ABS(B75-D75)<=0.5,"OK","DIVERSO") -> OK | F75: capitolo 19, lavoro 6
A76: Cliente X - margine cliente | B76: =$B$68-$B$75 -> 58000 | C76: euro | D76: 58000 | E76: =IF(ABS(B76-D76)<=0.5,"OK","DIVERSO") -> OK | F76: capitolo 19, lavoro 6
A77: Cliente X - margine cliente in % | B77: =$B$76/$B$67 -> 0.24166667 | C77: % | D77: 0.242 | E77: =IF(ABS(B77-D77)<=0.0005,"OK","DIVERSO") -> OK | F77: capitolo 19, lavoro 6
A78: Cliente Y - costo di servizio | B78: =$B$72*$B$63+$B$73*$B$64+$B$74*$B$65 -> 5600 | C78: euro | D78: 5600 | E78: =IF(ABS(B78-D78)<=0.5,"OK","DIVERSO") -> OK | F78: capitolo 19, lavoro 6
A79: Cliente Y - margine cliente | B79: =$B$68-$B$78 -> 78400 | C79: euro | D79: 78400 | E79: =IF(ABS(B79-D79)<=0.5,"OK","DIVERSO") -> OK | F79: capitolo 19, lavoro 6
A80: Cliente Y - margine cliente in % | B80: =$B$79/$B$67 -> 0.32666667 | C80: % | D80: 0.327 | E80: =IF(ABS(B80-D80)<=0.0005,"OK","DIVERSO") -> OK | F80: capitolo 19, lavoro 6
A82: Lavoro 7 - Costo pieno e margine sulla stessa decisione
A83: Struttura diversa dai costi indiretti ripartita sui ricavi; risultati per linea a costo pieno e simulazione dell'eliminazione della linea C nelle due ipotesi; capitolo 19, lavoro 7
A84: Voce | B84: Valore | C84: Unità | D84: Valore atteso (libro) | E84: Controllo | F84: Fonte nel libro
A85: Struttura da ripartire (esclusi i costi indiretti) | B85: =Impresa_guida!$B$41-Impresa_guida!$B$24 -> 700000 | C85: euro | D85: 700000 | E85: =IF(ABS(B85-D85)<=0.5,"OK","DIVERSO") -> OK | F85: capitolo 19, lavoro 7
A86: Linea A - risultato a costo pieno | B86: =Impresa_guida!$B$31-Impresa_guida!$B$8*Impresa_guida!$B$10-$B$48-$B$85*Impresa_guida!$B$31/Impresa_guida!$B$34 -> 146303.6 | C86: euro | D86: 146304 | E86: =IF(ABS(B86-D86)<=0.5,"OK","DIVERSO") -> OK | F86: capitolo 19, lavoro 7
A87: Linea B - risultato a costo pieno | B87: =Impresa_guida!$B$32-Impresa_guida!$B$12*Impresa_guida!$B$14-$B$50-$B$85*Impresa_guida!$B$32/Impresa_guida!$B$34 -> 143188.42 | C87: euro | D87: 143188 | E87: =IF(ABS(B87-D87)<=0.5,"OK","DIVERSO") -> OK | F87: capitolo 19, lavoro 7
A88: Linea C - risultato a costo pieno | B88: =Impresa_guida!$B$33-Impresa_guida!$B$16*Impresa_guida!$B$18-$B$52-$B$85*Impresa_guida!$B$33/Impresa_guida!$B$34 -> -47492.026 | C88: euro | D88: -47492 | E88: =IF(ABS(B88-D88)<=0.5,"OK","DIVERSO") -> OK | F88: capitolo 19, lavoro 7
A89: Somma dei risultati per linea | B89: =$B$86+$B$87+$B$88 -> 242000 | C89: euro | D89: 242000 | E89: =IF(ABS(B89-D89)<=0.5,"OK","DIVERSO") -> OK | F89: capitolo 19, lavoro 7
A90: Linea C - risultato a costo pieno per unità | B90: =$B$88/Impresa_guida!$B$16 -> -23.746013 | C90: euro/unità | D90: -23.75 | E90: =IF(ABS(B90-D90)<=0.005,"OK","DIVERSO") -> OK | F90: capitolo 19, lavoro 7
A91: Senza C, struttura invariata - risultato operativo | B91: =Impresa_guida!$B$42-Impresa_guida!$B$16*(Impresa_guida!$B$17-Impresa_guida!$B$18) -> 140000 | C91: euro | D91: 140000 | E91: =IF(ABS(B91-D91)<=0.5,"OK","DIVERSO") -> OK | F91: capitolo 19, lavoro 7
A92: Senza C, capacità esterna evitata - risultato operativo | B92: =$B$91+MIN(Impresa_guida!$B$16*Impresa_guida!$B$19,Impresa_guida!$B$38)*Impresa_guida!$B$27 -> 224000 | C92: euro | D92: 224000 | E92: =IF(ABS(B92-D92)<=0.5,"OK","DIVERSO") -> OK | F92: capitolo 19, lavoro 7
A94: Lavori 8 e 9 - Budget operativo
A95: Budget dell'esercizio successivo con verifica di fattibilità sulle ore e capacità esterna iscritta una sola volta; per il lavoro 9 il collaudo è la quadratura dei nove mesi, senza un numero da ricalcolare; capitolo 19, lavoro 8
A96: Voce | B96: Valore | C96: Unità | D96: Valore atteso (libro) | E96: Controllo | F96: Fonte nel libro
A97: Linea B - volume di budget | B97: =Cap_12!$B$19 -> 11400 | C97: unità | F97: capitolo 19, lavoro 8
A98: Linea B - prezzo netto di budget | B98: =Cap_12!$B$20 -> 118 | C98: euro/unità | F98: capitolo 19, lavoro 8
A99: Linea C - volume di budget | B99: =Cap_12!$B$21 -> 2100 | C99: unità | F99: capitolo 19, lavoro 8
A100: Ricavi netti di budget | B100: =Impresa_guida!$B$8*Impresa_guida!$B$9+$B$97*$B$98+$B$99*Impresa_guida!$B$17 -> 3392100 | C100: euro | D100: 3392100 | E100: =IF(ABS(B100-D100)<=0.5,"OK","DIVERSO") -> OK | F100: capitolo 19, lavoro 8
A101: Margine di contribuzione di budget | B101: =Impresa_guida!$B$8*(Impresa_guida!$B$9-Impresa_guida!$B$10)+$B$97*($B$98-Impresa_guida!$B$14)+$B$99*(Impresa_guida!$B$17-Impresa_guida!$B$18) -> 1089900 | C101: euro | D101: 1089900 | E101: =IF(ABS(B101-D101)<=0.5,"OK","DIVERSO") -> OK | F101: capitolo 19, lavoro 8
A102: Margine di budget in % | B102: =$B$101/$B$100 -> 0.32130539 | C102: % | D102: 0.321 | E102: =IF(ABS(B102-D102)<=0.0005,"OK","DIVERSO") -> OK | F102: capitolo 19, lavoro 8
A103: Ore macchina richieste dal budget | B103: =Impresa_guida!$B$8*Impresa_guida!$B$11+$B$97*Impresa_guida!$B$15+$B$99*Impresa_guida!$B$19 -> 24000 | C103: ore | D103: 24000 | E103: =IF(ABS(B103-D103)<=0.5,"OK","DIVERSO") -> OK | F103: capitolo 19, lavoro 8
A104: Costi della struttura di budget (capacità esterna una volta) | B104: =Impresa_guida!$B$40+MAX($B$103-Impresa_guida!$B$26,0)*Impresa_guida!$B$27 -> 820000 | C104: euro | D104: 820000 | E104: =IF(ABS(B104-D104)<=0.5,"OK","DIVERSO") -> OK | F104: capitolo 19, lavoro 8
A105: Risultato operativo di budget | B105: =$B$101-$B$104 -> 269900 | C105: euro | D105: 269900 | E105: =IF(ABS(B105-D105)<=0.5,"OK","DIVERSO") -> OK | F105: capitolo 19, lavoro 8
A107: Lavori 10 e 12 - Ponte del margine e prezzo della linea B
...

Sheet Cap_20
A1: Capitolo 20 - KPI essenziali per il controllo di gestione
A2: Controllo di gestione con l'intelligenza artificiale - file Excel che accompagna il libro
A3: Celle blu su fondo giallo: dati da cambiare. Celle nere: formule. «Valore atteso (libro)» e «Controllo» confrontano il calcolo con il numero stampato nel libro.
A4: Gli esempi numerici delle 24 schede KPI e, a parte, i KPI dell'impresa guida del 20.9 con i saldi medi del 19.3.
A6: Schede 1-4 - Redditività e capitale investito
A7: Esempi numerici delle schede KPI 1-4 (EBITDA margin, ROS, rotazione, ROI); il ROI riprende EBIT e capitale delle schede 2 e 3; il controllo ROS x rotazione (capitolo 20) è mostrato sull'impresa guida; capitolo 20
A8: Voce | B8: Valore | C8: Unità | D8: Valore atteso (libro) | E8: Controllo | F8: Fonte nel libro
A9: KPI 1 - EBITDA | B9: 180000 | C9: euro | F9: capitolo 20
A10: KPI 1 - Ricavi netti | B10: 1200000 | C10: euro | F10: capitolo 20
A11: KPI 1 - EBITDA margin | B11: =$B$9/$B$10 -> 0.15 | C11: % | D11: 0.15 | E11: =IF(ABS(B11-D11)<=0.00005,"OK","DIVERSO") -> OK | F11: capitolo 20
A12: KPI 2 - EBIT | B12: 120000 | C12: euro | F12: capitolo 20
A13: KPI 2 - ROS (ricavi 1.200.000 della scheda 1) | B13: =$B$12/$B$10 -> 0.1 | C13: % | D13: 0.1 | E13: =IF(ABS(B13-D13)<=0.00005,"OK","DIVERSO") -> OK | F13: capitolo 20
A14: KPI 3 - Capitale operativo iniziale | B14: 580000 | C14: euro | F14: capitolo 20
A15: KPI 3 - Capitale operativo finale | B15: 620000 | C15: euro | F15: capitolo 20
A16: KPI 3 - Capitale operativo medio | B16: =($B$14+$B$15)/2 -> 600000 | C16: euro | D16: 600000 | E16: =IF(ABS(B16-D16)<=0.5,"OK","DIVERSO") -> OK | F16: capitolo 20
A17: KPI 3 - Rotazione del capitale (ricavi 1.200.000) | B17: =$B$10/$B$16 -> 2 | C17: volte | D17: 2 | E17: =IF(ABS(B17-D17)<=0.005,"OK","DIVERSO") -> OK | F17: capitolo 20
